Workbook

Sheet README
A1: Section | B1: Content
A2: Purpose | B2: Full-season 2026 ESPN full-PPR point forecasts and a calibrated probability of a missed-time injury for every fantasy-position player on the August 9, 2026 roster snapshot, combined into a transparent draft score.
A3: Forecast origin | B3: Inputs are frozen as of 2026-08-09. No 2026 statistics, depth charts, injury reports, projections, or ADP enter either model. The current-injury listing columns come from a separate dated screen (2026-08-14) and do not change the models.
A4: Overall Draft Score | B4: Cross-position ranking used on the ALL page. Points Over Replacement = projected points minus the projected points of the replacement-level player at the position (QB12, RB24, WR36, TE12, K12). Overall Value = points over replacement divided by the largest points over replacement on the board (negative values count as 0), so magnitudes are preserved across positions. It is blended with the player's healthy probability relative to position peers: 100 * ((1 - w) * overall value + w * (healthy probability - position mean healthy probability + 0.5)), w = 0.20. Centering on the position mean stops low-exposure positions such as kickers from gaining a blanket bonus. The custom-weight column on ALL uses the overall value and relative health columns.
A5: Position Draft Score | B5: Within-position ranking used on the QB, RB, WR, TE, and K pages: 100 * ((1 - w) * position points percentile + w * healthy probability) with the default w = 0.20, the largest weight whose discovery-fold rank accuracy against realized points stayed within 0.005 Spearman of the best weight. Edit SETTINGS!B2 to recompute the custom-weight column on every page.
A6: Projected 2026 Points | B6: Points track forecast: ext_et_all (components: ext_et_all). Locked 2022-2025 audit mean within-position-season Spearman 0.756 (95% player-cluster interval 0.732 to 0.775); prior-season points baseline 0.647. Kicker forecasts retain the Phase 2 production model and are labeled low confidence.
A7: Points P10 / P90 | B7: Empirical 10th and 90th percentile bounds from 2022-2025 audit residuals of the adopted procedure within position and predicted-point tercile. About 80% of realized totals fell inside this band on the audit seasons; it is not a guarantee.
A8: Missed-Time Injury Probability | B8: Probability that the player appears on an official report as Out or Doubtful with a physical injury, or is placed on an injury reserve list, at least once during the 2026 regular season. Model: extra_trees_all_leaf50; 2022-2024 audit ROC AUC 0.749 (95% interval 0.731 to 0.767), calibration slope 1.02, prevalence 24.7%. The label is an observed absence event, not severity or games missed, and participation is part of the signal.
A9: Injury Risk Band | B9: lower < 20%, moderate 20% to 35%, higher > 35% predicted probability.
A10: Current Injury Listing | B10: TRUE when the 2026-08-14 public screen matched an affirmative injury listing. FALSE is not evidence of health. The INJURED page repeats these players with their source details.
A11: Sheets | B11: ALL and INJURED sort by the overall draft score; QB, RB, WR, TE, and K sort by the position draft score. MODEL_EVAL, WEIGHT_ANALYSIS, FEATURES_POINTS, FEATURES_INJURY, and FAMILY_ABLATION hold the evaluation evidence and feature rankings.
A12: Leakage controls | B12: Historical candidates are prior-season roster members plus draft or combine entrants; nonparticipants keep zero points. Features use only seasons before the target. Report-based injury history uses offsets of two or more seasons because the official feed ends in 2024; roster reserve history uses offsets of one or more seasons. Model selection used 2016-2021 (points) and 2017-2021 (injury); audits ran once on 2022-2025 and 2022-2024. Negative controls: points null mean Spearman 0.0210; injury null mean AUC 0.5288.
... A14: Generated | B14: 2026-08-22T20:09:20.902824+00:00

Sheet SETTINGS
A1: Setting | B1: Value | C1: Note
A2: Injury weight used by the custom score column (0 to 1) | B2: 0.2 | C2: Edit this cell. Position pages recompute their custom score as 100 * ((1 - weight) * position points percentile + weight * healthy probability); ALL and INJURED use the overall value percentile instead. Rows stay in default order; use the column filter to re-sort.
A3: Default injury weight selected by the predeclared rule | B3: 0.2 | C3: Largest weight whose discovery-fold rank accuracy against realized points stayed within 0.005 Spearman of the best weight.

Sheet ALL
A1: Rank | B1: Player | C1: Team | D1: Pos | E1: Overall Draft Score (replacement-adjusted) | F1: Position Draft Score (default weight) | G1: Custom-Weight Score (weight from SETTINGS) | H1: Projected 2026 Points | I1: Points Over Replacement | J1: Overall Value (points over replacement / max) | K1: Points P10 | L1: Points P90 | M1: Pos Points Rank | N1: Pos Points Percentile | O1: Missed-Time Injury Probability | P1: Healthy Probability | Q1: Healthy Probability vs Position Mean (+0.5) | R1: Injury Risk Band | S1: Current Injury Listing (screen date) | T1: Current Listing Status | U1: Rookie | V1: Age | W1: Points Model Confidence | X1: Roster Status (Aug 9) | Y1: Player ID
A2: 1 | B2: Jaxon Smith-Njigba | C2: SEA | D2: WR | E2: 85.74 | F2: 90.68 | G2: =ROUND(100*((1-SETTINGS!$B$2)*J2+SETTINGS!$B$2*Q2),2) | H2: 249.73827 | I2: 127.25 | J2: 1 | K2: 181.94645 | L2: 332.01905 | M2: 1 | N2: 1 | O2: 0.46595868 | P2: 0.53404132 | Q2: 0.28689485 | R2: higher | S2: FALSE | U2: no | V2: 24.545336 | W2: standard | X2: ACT | Y2: 00-0038543
A3: 2 | B3: Amon-Ra St. Brown | C3: DET | D3: WR | E3: 75.19 | F3: 91.13 | G3: =ROUND(100*((1-SETTINGS!$B$2)*J3+SETTINGS!$B$2*Q3),2) | H3: 231.91781 | I3: 109.43 | J3: 0.86 | K3: 164.12599 | L3: 314.19859 | M3: 2 | N3: 0.99739583 | O3: 0.43314403 | P3: 0.56685597 | Q3: 0.3197095 | R3: higher | S3: FALSE | U3: no | V3: 26.856131 | W3: standard | X3: ACT | Y3: 00-0036963
A4: 3 | B4: Puka Nacua | C4: LA | D4: WR | E4: 74.24 | F4: 90.38 | G4: =ROUND(100*((1-SETTINGS!$B$2)*J4+SETTINGS!$B$2*Q4),2) | H4: 231.26732 | I4: 108.78 | J4: 0.8549 | K4: 163.4755 | L4: 313.5481 | M4: 3 | N4: 0.99479167 | O4: 0.46033059 | P4: 0.53966941 | Q4: 0.29252294 | R4: higher | S4: TRUE | T4: Questionable | U4: no | V4: 25.25993 | W4: standard | X4: ACT | Y4: 00-0039075
A5: 4 | B5: Bijan Robinson | C5: ATL | D5: RB | E5: 72.02 | F5: 88.24 | G5: =ROUND(100*((1-SETTINGS!$B$2)*J5+SETTINGS!$B$2*Q5),2) | H5: 264.68583 | I5: 107.69 | J5: 0.8463 | K5: 195.52625 | L5: 379.65372 | M5: 1 | N5: 1 | O5: 0.58776347 | P5: 0.41223653 | Q5: 0.21567287 | R5: higher | S5: FALSE | U5: no | V5: 24.586405 | W5: standard | X5: ACT | Y5: 00-0038542
A6: 5 | B6: Trey McBride | C6: AZ | D6: TE | E6: 70.59 | F6: 90.75 | G6: =ROUND(100*((1-SETTINGS!$B$2)*J6+SETTINGS!$B$2*Q6),2) | H6: 226.95633 | I6: 102.03 | J6: 0.8018 | K6: 183.20548 | L6: 299.83355 | M6: 1 | N6: 1 | O6: 0.46235352 | P6: 0.53764648 | Q6: 0.32240833 | R6: higher | S6: FALSE | U6: no | V6: 26.77673 | W6: standard | X6: ACT | Y6: 00-0037744
A7: 6 | B7: Josh Allen | C7: BUF | D7: QB | E7: 70.39 | F7: 91.32 | G7: =ROUND(100*((1-SETTINGS!$B$2)*J7+SETTINGS!$B$2*Q7),2) | H7: 322.74206 | I7: 102.95 | J7: 0.809 | K7: 213.08296 | L7: 463.3179 | M7: 1 | N7: 1 | O7: 0.43420955 | P7: 0.56579045 | Q7: 0.28356424 | R7: higher | S7: FALSE | U7: no | V7: 30.281252 | W7: standard | X7: ACT | Y7: 00-0034857
A8: 7 | B8: Ja'Marr Chase | C8: CIN | D8: WR | E8: 65.83 | F8: 91.81 | G8: =ROUND(100*((1-SETTINGS!$B$2)*J8+SETTINGS!$B$2*Q8),2) | H8: 215.27921 | I8: 92.79 | J8: 0.7292 | K8: 147.48739 | L8: 297.55999 | M8: 4 | N8: 0.9921875 | O8: 0.37819061 | P8: 0.62180939 | Q8: 0.37466292 | R8: higher | S8: FALSE | U8: no | V8: 26.502939 | W8: standard | X8: ACT | Y8: 00-0036900
A9: 8 | B9: George Pickens | C9: DAL | D9: WR | E9: 63.88 | F9: 91.25 | G9: =ROUND(100*((1-SETTINGS!$B$2)*J9+SETTINGS!$B$2*Q9),2) | H9: 212.40207 | I9: 89.92 | J9: 0.7066 | K9: 144.61025 | L9: 294.68285 | M9: 6 | N9: 0.98697917 | O9: 0.38547724 | P9: 0.61452276 | Q9: 0.36737629 | R9: higher | S9: FALSE | U9: no | V9: 25.49539 | W9: standard | X9: ACT | Y9: 00-0037247
A10: 9 | B10: Justin Jefferson | C10: MIN | D10: WR | E10: 63.83 | F10: 91.03 | G10: =ROUND(100*((1-SETTINGS!$B$2)*J10+SETTINGS!$B$2*Q10),2) | H10: 213.00414 | I10: 90.52 | J10: 0.7114 | K10: 145.21232 | L10: 295.28492 | M10: 5 | N10: 0.98958333 | O10: 0.4070599 | P10: 0.5929401 | Q10: 0.34579363 | R10: higher | S10: FALSE | U10: no | V10: 27.212057 | W10: standard | X10: ACT | Y10: 00-0036322
A11: 10 | B11: Zay Flowers | C11: BAL | D11: WR | E11: 59.1 | F11: 89.65 | G11: =ROUND(100*((1-SETTINGS!$B$2)*J11+SETTINGS!$B$2*Q11),2) | H11: 206.67381 | I11: 84.19 | J11: 0.6616 | K11: 138.88199 | L11: 288.95459 | M11: 8 | N11: 0.98177083 | O11: 0.44443044 | P11: 0.55556956 | Q11: 0.30842309 | R11: higher | S11: FALSE | U11: no | V11: 25.971786 | W11: standard | X11: ACT | Y11: 00-0039064
A12: 11 | B12: CeeDee Lamb | C12: DAL | D12: WR | E12: 58.45 | F12: 89.03 | G12: =ROUND(100*((1-SETTINGS!$B$2)*J12+SETTINGS!$B$2*Q12),2) | H12: 206.9714 | I12: 84.49 | J12: 0.664 | K12: 139.17958 | L12: 289.25218 | M12: 7 | N12: 0.984375 | O12: 0.48621738 | P12: 0.51378262 | Q12: 0.26663615 | R12: higher | S12: FALSE | U12: no | V12: 27.400974 | W12: standard | X12: ACT | Y12: 00-0036358
A13: 12 | B13: Jahmyr Gibbs | C13: DET | D13: RB | E13: 56.76 | F13: 87.83 | G13: =ROUND(100*((1-SETTINGS!$B$2)*J13+SETTINGS!$B$2*Q13),2) | H13: 240.4644 | I13: 83.47 | J13: 0.656 | K13: 171.30482 | L13: 355.4323 | M13: 2 | N13: 0.9952381 | O13: 0.5893529 | P13: 0.4106471 | Q13: 0.21408344 | R13: higher | S13: TRUE | T13: Questionable | U13: no | V13: 24.452248 | W13: standard | X13: ACT | Y13: 00-0039139
A14: 13 | B14: Jameson Williams | C14: DET | D14: WR | E14: 54.7 | F14: 88.93 | G14: =ROUND(100*((1-SETTINGS!$B$2)*J14+SETTINGS!$B$2*Q14),2) | H14: 200.4812 | I14: 78 | J14: 0.613 | K14: 132.68938 | L14: 282.76198 | M14: 9 | N14: 0.97916667 | O14: 0.47008001 | P14: 0.52991999 | Q14: 0.28277352 | R14: higher | S14: FALSE | U14: no | V14: 25.435156 | W14: standard | X14: ACT | Y14: 00-0037240
A15: 14 | B15: Derrick Henry | C15: BAL | D15: RB | E15: 52.62 | F15: 89.34 | G15: =ROUND(100*((1-SETTINGS!$B$2)*J15+SETTINGS!$B$2*Q15),2) | H15: 230.26795 | I15: 73.27 | J15: 0.5758 | K15: 161.10837 | L15: 345.23584 | M15: 4 | N15: 0.98571429 | O15: 0.47582579 | P15: 0.52417421 | Q15: 0.32761055 | R15: higher | S15: FALSE | U15: no | V15: 32.657753 | W15: standard | X15: ACT | Y15: 00-0032764
A16: 15 | B16: Drake London | C16: ATL | D16: WR | E16: 52.09 | F16: 87.69 | G16: =ROUND(100*((1-SETTINGS!$B$2)*J16+SETTINGS!$B$2*Q16),2) | H16: 197.9819 | I16: 75.5 | J16: 0.5933 | K16: 130.19008 | L16: 280.26269 | M16: 10 | N16: 0.9765625 | O16: 0.52163641 | P16: 0.47836359 | Q16: 0.23121712 | R16: higher | S16: FALSE | U16: no | V16: 25.106607 | W16: standard | X16: ACT | Y16: 00-0037238
A17: 16 | B17: De'Von Achane | C17: MIA | D17: RB | E17: 51.29 | F17: 87.47 | G17: =ROUND(100*((1-SETTINGS!$B$2)*J17+SETTINGS!$B$2*Q17),2) | H17: 231.74679 | I17: 74.75 | J17: 0.5874 | K17: 162.58721 | L17: 346.71469 | M17: 3 | N17: 0.99047619 | O17: 0.58838759 | P17: 0.41161241 | Q17: 0.21504875 | R17: higher | S17: FALSE | U17: no | V17: 24.884836 | W17: standard | X17: ACT | Y17: 00-0039040
A18: 17 | B18: Ashton Jeanty | C18: LV | D18: RB | E18: 46.99 | F18: 87.67 | G18: =ROUND(100*((1-SETTINGS!$B$2)*J18+SETTINGS!$B$2*Q18),2) | H18: 223.37205 | I18: 66.38 | J18: 0.5217 | K18: 154.21247 | L18: 338.33995 | M18: 5 | N18: 0.98095238 | O18: 0.54054458 | P18: 0.45945542 | Q18: 0.26289176 | R18: higher | S18: FALSE | U18: no | V18: 22.749269 | W18: standard | X18: ACT | Y18: 00-0040122
A19: 18 | B19: Tetairoa McMillan | C19: CAR | D19: WR | E19: 43.19 | F19: 87.24 | G19: =ROUND(100*((1-SETTINGS!$B$2)*J19+SETTINGS!$B$2*Q19),2) | H19: 184.2247 | I19: 61.74 | J19: 0.4852 | K19: 116.43288 | L19: 266.50548 | M19: 11 | N19: 0.97395833 | O19: 0.53396651 | P19: 0.46603349 | Q19: 0.21888702 | R19: higher | S19: FALSE | U19: no | V19: 23.409105 | W19: standard | X19: ACT | Y19: 00-0040124
A20: 19 | B20: Chris Olave | C20: NO | D20: WR | E20: 42.78 | F20: 89.86 | G20: =ROUND(100*((1-SETTINGS!$B$2)*J20+SETTINGS!$B$2*Q20),2) | H20: 178.73788 | I20: 56.25 | J20: 0.442 | K20: 110.94606 | L20: 261.01867 | M20: 13 | N20: 0.96875 | O20: 0.38199551 | P20: 0.61800449 | Q20: 0.37085802 | R20: higher | S20: FALSE | U20: no | V20: 26.179867 | W20: standard | X20: ACT | Y20: 00-0037239
A21: 20 | B21: Chase Brown | C21: CIN | D21: RB | E21: 41.07 | F21: 87.19 | G21: =ROUND(100*((1-SETTINGS!$B$2)*J21+SETTINGS!$B$2*Q21),2) | H21: 214.10578 | I21: 57.11 | J21: 0.4488 | K21: 144.9462 | L21: 329.07368 | M21: 6 | N21: 0.97619048 | O21: 0.54521446 | P21: 0.45478554 | Q21: 0.25822187 | R21: higher | S21: FALSE | U21: no | V21: 26.448181 | W21: standard | X21: ACT | Y21: 00-0038597
A22: 21 | B22: Nico Collins | C22: HOU | D22: WR | E22: 40.99 | F22: 87.95 | G22: =ROUND(100*((1-SETTINGS!$B$2)*J22+SETTINGS!$B$2*Q22),2) | H22: 179.27048 | I22: 56.78 | J22: 0.4462 | K22: 111.47866 | L22: 261.55126 | M22: 12 | N22: 0.97135417 | O22: 0.48793958 | P22: 0.51206042 | Q22: 0.26491395 | R22: higher | S22: FALSE | U22: no | V22: 27.455732 | W22: standard | X22: ACT | Y22: 00-0036554
A23: 22 | B23: Jaylen Waddle | C23: DEN | D23: WR | E23: 40.4 | F23: 87.71 | G23: =ROUND(100*((1-SETTINGS!$B$2)*J23+SETTINGS!$B$2*Q23),2) | H23: 178.02173 | I23: 55.54 | J23: 0.4365 | K23: 110.22991 | L23: 260.30251 | M23: 14 | N23: 0.96614583 | O23: 0.47908948 | P23: 0.52091052 | Q23: 0.27376405 | R23: higher | S23: TRUE | T23: Questionable | U23: no | V23: 27.767853 | W23: standard | X23: ACT | Y23: 00-0036613
A24: 23 | B24: A.J. Brown | C24: NE | D24: WR | E24: 39.58 | F24: 87.66 | G24: =ROUND(100*((1-SETTINGS!$B$2)*J24+SETTINGS!$B$2*Q24),2) | H24: 176.48154 | I24: 54 | J24: 0.4244 | K24: 108.68972 | L24: 258.76232 | M24: 15 | N24: 0.96354167 | O24: 0.47129817 | P24: 0.52870183 | Q24: 0.28155536 | R24: higher | S24: FALSE | U24: no | V24: 29.1724 | W24: standard | X24: ACT | Y24: 00-0035676
A25: 24 | B25: DeVonta Smith | C25: PHI | D25: WR | E25: 38.66 | F25: 87.49 | G25: =ROUND(100*((1-SETTINGS!$B$2)*J25+SETTINGS!$B$2*Q25),2) | H25: 174.96752 | I25: 52.48 | J25: 0.4124 | K25: 107.1757 | L25: 257.2483 | M25: 16 | N25: 0.9609375 | O25: 0.46928457 | P25: 0.53071543 | Q25: 0.28356896 | R25: higher | S25: TRUE | T25: Questionable | U25: no | V25: 27.79797 | W25: standard | X25: ACT | Y25: 00-0036912
A26: 25 | B26: Drake Maye | C26: NE | D26: QB | E26: 38.27 | F26: 90.36 | G26: =ROUND(100*((1-SETTINGS!$B$2)*J26+SETTINGS!$B$2*Q26),2) | H26: 272.09196 | I26: 52.3 | J26: 0.411 | K26: 162.43286 | L26: 412.6678 | M26: 2 | N26: 0.99159664 | O26: 0.44824514 | P26: 0.55175486 | Q26: 0.26952865 | R26: higher | S26: FALSE | U26: no | V26: 24.005968 | W26: standard | X26: ACT | Y26: 00-0039851
A27: 26 | B27: Wan'Dale Robinson | C27: TEN | D27: WR | E27: 36.18 | F27: 86.88 | G27: =ROUND(100*((1-SETTINGS!$B$2)*J27+SETTINGS!$B$2*Q27),2) | H27: 171.65199 | I27: 49.17 | J27: 0.3864 | K27: 103.86017 | L27: 253.93278 | M27: 17 | N27: 0.95833333 | O27: 0.48954781 | P27: 0.51045219 | Q27: 0.26330572 | R27: higher | S27: FALSE | U27: no | V27: 25.654188 | W27: standard | X27: ACT | Y27: 00-0038117
A28: 27 | B28: Jalen Hurts | C28: PHI | D28: QB | E28: 34.96 | F28: 89.23 | G28: =ROUND(100*((1-SETTINGS!$B$2)*J28+SETTINGS!$B$2*Q28),2) | H28: 267.55492 | I28: 47.76 | J28: 0.3753 | K28: 157.89582 | L28: 408.13076 | M28: 3 | N28: 0.98319328 | O28: 0.47105394 | P28: 0.52894606 | Q28: 0.24671986 | R28: higher | S28: FALSE | U28: no | V28: 28.069023 | W28: standard | X28: ACT | Y28: 00-0036389
A29: 28 | B29: Emeka Egbuka | C29: TB | D29: WR | E29: 33.62 | F29: 85.8 | G29: =ROUND(100*((1-SETTINGS!$B$2)*J29+SETTINGS!$B$2*Q29),2) | H29: 168.97355 | I29: 46.49 | J29: 0.3653 | K29: 101.18173 | L29: 251.25433 | M29: 18 | N29: 0.95572917 | O29: 0.53296324 | P29: 0.46703676 | Q29: 0.21989029 | R29: higher | S29: TRUE | T29: Questionable | U29: no | V29: 23.882763 | W29: standard | X29: ACT | Y29: 00-0040129
A30: 29 | B30: Caleb Williams | C30: CHI | D30: QB | E30: 33.32 | F30: 89.49 | G30: =ROUND(100*((1-SETTINGS!$B$2)*J30+SETTINGS!$B$2*Q30),2) | H30: 263.46877 | I30: 43.68 | J30: 0.3433 | K30: 153.80967 | L30: 404.04461 | M30: 4 | N30: 0.97478992 | O30: 0.42488997 | P30: 0.57511003 | Q30: 0.29288382 | R30: higher | S30: FALSE | U30: no | V30: 24.786272 | W30: standard | X30: ACT | Y30: 00-0039918
A31: 30 | B31: Harold Fannin Jr. | C31: CLE | D31: TE | E31: 33.07 | F31: 89.22 | G31: =ROUND(100*((1-SETTINGS!$B$2)*J31+SETTINGS!$B$2*Q31),2) | H31: 168.4083 | I31: 43.48 | J31: 0.3417 | K31: 124.65745 | L31: 241.28552 | M31: 3 | N31: 0.98974359 | O31: 0.49803494 | P31: 0.50196506 | Q31: 0.28672691 | R31: higher | S31: FALSE | U31: no | V31: 22.116814 | W31: standard | X31: ACT | Y31: 00-0040663
A32: 31 | B32: Kyle Pitts | C32: ATL | D32: TE | E32: 33 | F32: 89.2 | G32: =ROUND(100*((1-SETTINGS!$B$2)*J32+SETTINGS!$B$2*Q32),2) | H32: 168.98125 | I32: 44.05 | J32: 0.3462 | K32: 125.23039 | L32: 241.85847 | M32: 2 | N32: 0.99487179 | O32: 0.51970839 | P32: 0.48029161 | Q32: 0.26505346 | R32: higher | S32: FALSE | U32: no | V32: 25.903337 | W32: standard | X32: ACT | Y32: 00-0036970
A33: 32 | B33: Travis Kelce | C33: KC | D33: TE | E33: 32.04 | F33: 91.02 | G33: =ROUND(100*((1-SETTINGS!$B$2)*J33+SETTINGS!$B$2*Q33),2) | H33: 162.60426 | I33: 37.68 | J33: 0.2961 | K33: 118.85341 | L33: 235.48148 | M33: 5 | N33: 0.97948718 | O33: 0.36695746 | P33: 0.63304254 | Q33: 0.41780439 | R33: higher | S33: FALSE | U33: no | V33: 36.906986 | W33: standard | X33: ACT | Y33: 00-0030506
A34: 33 | B34: Kyren Williams | C34: LA | D34: RB | E34: 31.7 | F34: 87.72 | G34: =ROUND(100*((1-SETTINGS!$B$2)*J34+SETTINGS!$B$2*Q34),2) | H34: 197.75366 | I34: 40.76 | J34: 0.3203 | K34: 128.59408 | L34: 312.72156 | M34: 7 | N34: 0.97142857 | O34: 0.49950467 | P34: 0.50049533 | Q34: 0.30393166 | R34: higher | S34: FALSE | U34: no | V34: 26.015593 | W34: standard | X34: ACT | Y34: 00-0037840
A35: 34 | B35: Michael Wilson | C35: AZ | D35: WR | E35: 31.45 | F35: 85.88 | G35: =ROUND(100*((1-SETTINGS!$B$2)*J35+SETTINGS!$B$2*Q35),2) | H35: 165.04877 | I35: 42.56 | J35: 0.3345 | K35: 97.25695 | L35: 247.32955 | M35: 19 | N35: 0.953125 | O35: 0.51845499 | P35: 0.48154501 | Q35: 0.23439854 | R35: higher | S35: FALSE | U35: no | V35: 26.522104 | W35: standard | X35: ACT | Y35: 00-0038559
A36: 35 | B36: Davante Adams | C36: LA | D36: WR | E36: 31.12 | F36: 86.65 | G36: =ROUND(100*((1-SETTINGS!$B$2)*J36+SETTINGS!$B$2*Q36),2) | H36: 162.3029 | I36: 39.82 | J36: 0.3129 | K36: 94.511082 | L36: 244.58368 | M36: 22 | N36: 0.9453125 | O36: 0.44855853 | P36: 0.55144147 | Q36: 0.30429499 | R36: higher | S36: FALSE | U36: no | V36: 33.687206 | W36: standard | X36: ACT | Y36: 00-0031381
A37: 36 | B37: Michael Pittman | C37: PIT | D37: WR | E37: 31.07 | F37: 86.22 | G37: =ROUND(100*((1-SETTINGS!$B$2)*J37+SETTINGS!$B$2*Q37),2) | H37: 163.57812 | I37: 41.09 | J37: 0.3229 | K37: 95.786296 | L37: 245.8589 | M37: 20 | N37: 0.95052083 | O37: 0.49104256 | P37: 0.50895744 | Q37: 0.26181097 | R37: higher | S37: TRUE | T37: Questionable | U37: no | V37: 28.906822 | W37: standard | X37: ACT | Y37: 00-0036252
A38: 37 | B38: Courtland Sutton | C38: DEN | D38: WR | E38: 30.5 | F38: 86.09 | G38: =ROUND(100*((1-SETTINGS!$B$2)*J38+SETTINGS!$B$2*Q38),2) | H38: 162.54173 | I38: 40.06 | J38: 0.3148 | K38: 94.749911 | L38: 244.82251 | M38: 21 | N38: 0.94791667 | O38: 0.48727471 | P38: 0.51272529 | Q38: 0.26557882 | R38: higher | S38: FALSE | U38: no | V38: 30.894543 | W38: standard | X38: ACT | Y38: 00-0034348
A39: 38 | B39: James Cook | C39: BUF | D39: RB | E39: 29.63 | F39: 85.62 | G39: =ROUND(100*((1-SETTINGS!$B$2)*J39+SETTINGS!$B$2*Q39),2) | H39: 196.59144 | I39: 39.6 | J39: 0.3112 | K39: 127.43186 | L39: 311.55934 | M39: 9 | N39: 0.96190476 | O39: 0.566826 | P39: 0.433174 | Q39: 0.23661034 | R39: higher | S39: FALSE | U39: no | V39: 26.93553 | W39: standard | X39: ACT | Y39: 00-0037248
A40: 39 | B40: Breece Hall | C40: NYJ | D40: RB | E40: 29.06 | F40: 85.41 | G40: =ROUND(100*((1-SETTINGS!$B$2)*J40+SETTINGS!$B$2*Q40),2) | H40: 196.62306 | I40: 39.63 | J40: 0.3114 | K40: 127.46348 | L40: 311.59095 | M40: 8 | N40: 0.96666667 | O40: 0.59615961 | P40: 0.40384039 | Q40: 0.20727672 | R40: higher | S40: FALSE | U40: no | V40: 25.254454 | W40: standard | X40: ACT | Y40: 00-0038120
A41: 40 | B41: Bo Nix | C41: DEN | D41: QB | E41: 28.99 | F41: 88.94 | G41: =ROUND(100*((1-SETTINGS!$B$2)*J41+SETTINGS!$B$2*Q41),2) | H41: 256.37092 | I41: 36.58 | J41: 0.2875 | K41: 146.71182 | L41: 396.94676 | M41: 5 | N41: 0.96638655 | O41: 0.41847222 | P41: 0.58152778 | Q41: 0.29930158 | R41: higher | S41: FALSE | U41: no | V41: 26.51663 | W41: standard | X41: ACT | Y41: 00-0039732
A42: 41 | B42: Tyler Warren | C42: IND | D42: TE | E42: 28.93 | F42: 88.31 | G42: =ROUND(100*((1-SETTINGS!$B$2)*J42+SETTINGS!$B$2*Q42),2) | H42: 162.62031 | I42: 37.69 | J42: 0.2962 | K42: 118.86946 | L42: 235.49753 | M42: 4 | N42: 0.98461538 | O42: 0.52284604 | P42: 0.47715396 | Q42: 0.26191581 | R42: higher | S42: FALSE | U42: no | V42: 24.274284 | W42: standard | X42: ACT | Y42: 00-0040128
A43: 42 | B43: Jakobi Meyers | C43: JAX | D43: WR | E43: 27.88 | F43: 84.95 | G43: =ROUND(100*((1-SETTINGS!$B$2)*J43+SETTINGS!$B$2*Q43),2) | H43: 159.52831 | I43: 37.04 | J43: 0.2911 | K43: 91.736488 | L43: 241.80909 | M43: 23 | N43: 0.94270833 | O43: 0.52349037 | P43: 0.47650963 | Q43: 0.22936316 | R43: higher | S43: FALSE | U43: no | V43: 29.810331 | W43: standard | X43: ACT | Y43: 00-0034960
A44: 43 | B44: D'Andre Swift | C44: CHI | D44: RB | E44: 27.07 | F44: 86.1 | G44: =ROUND(100*((1-SETTINGS!$B$2)*J44+SETTINGS!$B$2*Q44),2) | H44: 191.17046 | I44: 34.17 | J44: 0.2685 | K44: 122.01088 | L44: 306.13835 | M44: 10 | N44: 0.95714286 | O44: 0.52381258 | P44: 0.47618742 | Q44: 0.27962376 | R44: higher | S44: FALSE | U44: no | V44: 27.630957 | W44: standard | X44: ACT | Y44: 00-0036275
A45: 44 | B45: Tee Higgins | C45: CIN | D45: WR | E45: 25.73 | F45: 85.16 | G45: =ROUND(100*((1-SETTINGS!$B$2)*J45+SETTINGS!$B$2*Q45),2) | H45: 155.11223 | I45: 32.63 | J45: 0.2564 | K45: 87.32041 | L45: 237.39301 | M45: 25 | N45: 0.9375 | O45: 0.4920269 | P45: 0.5079731 | Q45: 0.26082663 | R45: higher | S45: FALSE | U45: no | V45: 27.620007 | W45: standard | X45: ACT | Y45: 00-0036410
A46: 45 | B46: Cameron Dicker | C46: LAC | D46: K | E46: 25.71 | F46: 97.65 | G46: =ROUND(100*((1-SETTINGS!$B$2)*J46+SETTINGS!$B$2*Q46),2) | H46: 141.69836 | I46: 24.49 | J46: 0.1925 | K46: 49.200332 | L46: 182.32159 | M46: 1 | N46: 1 | O46: 0.11754744 | P46: 0.88245256 | Q46: 0.51546774 | R46: lower | S46: FALSE | U46: no | V46: 26.322237 | W46: low (kicker) | X46: ACT | Y46: 00-0037224
A47: 46 | B47: Jared Goff | C47: DET | D47: QB | E47: 25.69 | F47: 90.84 | G47: =ROUND(100*((1-SETTINGS!$B$2)*J47+SETTINGS!$B$2*Q47),2) | H47: 244.90236 | I47: 25.11 | J47: 0.1973 | K47: 135.24327 | L47: 385.4782 | M47: 8 | N47: 0.94117647 | O47: 0.22253456 | P47: 0.77746544 | Q47: 0.49523924 | R47: moderate | S47: FALSE | U47: no | V47: 31.882927 | W47: standard | X47: ACT | Y47: 00-0033106
A48: 47 | B48: DK Metcalf | C48: PIT | D48: WR | E48: 25.34 | F48: 84.49 | G48: =ROUND(100*((1-SETTINGS!$B$2)*J48+SETTINGS!$B$2*Q48),2) | H48: 155.88554 | I48: 33.4 | J48: 0.2625 | K48: 88.093722 | L48: 238.16632 | M48: 24 | N48: 0.94010417 | O48: 0.53604805 | P48: 0.46395195 | Q48: 0.21680548 | R48: higher | S48: TRUE | T48: Questionable | U48: no | V48: 28.715168 | W48: standard | X48: ACT | Y48: 00-0035640
A49: 48 | B49: Justin Herbert | C49: LAC | D49: QB | E49: 24.27 | F49: 88.44 | G49: =ROUND(100*((1-SETTINGS!$B$2)*J49+SETTINGS!$B$2*Q49),2) | H49: 248.61333 | I49: 28.82 | J49: 0.2265 | K49: 138.95423 | L49: 389.18917 | M49: 6 | N49: 0.95798319 | O49: 0.41010254 | P49: 0.58989746 | Q49: 0.30767125 | R49: higher | S49: FALSE | U49: no | V49: 28.47971 | W49: standard | X49: ACT | Y49: 00-0036355
A50: 49 | B50: Christian McCaffrey | C50: SF | D50: RB | E50: 23.61 | F50: 84.47 | G50: =ROUND(100*((1-SETTINGS!$B$2)*J50+SETTINGS!$B$2*Q50),2) | H50: 187.63536 | I50: 30.64 | J50: 0.2408 | K50: 118.47578 | L50: 302.60325 | M50: 11 | N50: 0.95238095 | O50: 0.58589425 | P50: 0.41410575 | Q50: 0.21754209 | R50: higher | S50: TRUE | T50: Questionable | U50: no | V50: 30.234707 | W50: standard | X50: ACT | Y50: 00-0033280
A51: 50 | B51: Ladd McConkey | C51: LAC | D51: WR | E51: 22.74 | F51: 84.16 | G51: =ROUND(100*((1-SETTINGS!$B$2)*J51+SETTINGS!$B$2*Q51),2) | H51: 151.61636 | I51: 29.13 | J51: 0.2289 | K51: 83.824541 | L51: 233.89714 | M51: 26 | N51: 0.93489583 | O51: 0.53147609 | P51: 0.46852391 | Q51: 0.22137744 | R51: higher | S51: FALSE | U51: no | V51: 24.805437 | W51: standard | X51: ACT | Y51: 00-0039915
A52: 51 | B52: Ka'imi Fairbairn | C52: HOU | D52: K | E52: 22.42 | F52: 95.44 | G52: =ROUND(100*((1-SETTINGS!$B$2)*J52+SETTINGS!$B$2*Q52),2) | H52: 137.02056 | I52: 19.81 | J52: 0.1557 | K52: 44.522534 | L52: 177.6438 | M52: 2 | N52: 0.97674419 | O52: 0.13479602 | P52: 0.86520398 | Q52: 0.49821916 | R52: lower | S52: FALSE | U52: no | V52: 32.589306 | W52: low (kicker) | X52: ACT | Y52: 00-0032726
A53: 52 | B53: Baker Mayfield | C53: TB | D53: QB | E53: 21.54 | F53: 86.99 | G53: =ROUND(100*((1-SETTINGS!$B$2)*J53+SETTINGS!$B$2*Q53),2) | H53: 245.48501 | I53: 25.69 | J53: 0.2019 | K53: 135.82591 | L53: 386.06085 | M53: 7 | N53: 0.94957983 | O53: 0.44861377 | P53: 0.55138623 | Q53: 0.26916002 | R53: higher | S53: FALSE | U53: no | V53: 31.384628 | W53: standard | X53: ACT | Y53: 00-0034855
A54: 53 | B54: Khalil Shakir | C54: BUF | D54: WR | E54: 21.08 | F54: 86.32 | G54: =ROUND(100*((1-SETTINGS!$B$2)*J54+SETTINGS!$B$2*Q54),2) | H54: 144.87719 | I54: 22.39 | J54: 0.176 | K54: 77.085368 | L54: 227.15797 | M54: 28 | N54: 0.9296875 | O54: 0.4026671 | P54: 0.5973329 | Q54: 0.35018643 | R54: higher | S54: FALSE | U54: no | V54: 26.576864 | W54: standard | X54: ACT | Y54: 00-0037261
A55: 54 | B55: Alec Pierce | C55: IND | D55: WR | E55: 20.79 | F55: 85.73 | G55: =ROUND(100*((1-SETTINGS!$B$2)*J55+SETTINGS!$B$2*Q55),2) | H55: 145.68725 | I55: 23.2 | J55: 0.1823 | K55: 77.895427 | L55: 227.96803 | M55: 27 | N55: 0.93229167 | O55: 0.4426161 | P55: 0.5573839 | Q55: 0.31023743 | R55: higher | S55: TRUE | T55: Out | U55: no | V55: 26.333189 | W55: standard | X55: ACT | Y55: 00-0037664
A56: 55 | B56: Will Reichard | C56: MIN | D56: K | E56: 19.77 | F56: 93.34 | G56: =ROUND(100*((1-SETTINGS!$B$2)*J56+SETTINGS!$B$2*Q56),2) | H56: 133.20532 | I56: 16 | J56: 0.1257 | K56: 40.707295 | L56: 173.82856 | M56: 3 | N56: 0.95348837 | O56: 0.14709952 | P56: 0.85290048 | Q56: 0.48591565 | R56: lower | S56: FALSE | U56: no | V56: 25.643236 | W56: low (kicker) | X56: ACT | Y56: 00-0039404
A57: 56 | B57: DJ Moore | C57: BUF | D57: WR | E57: 19.26 | F57: 84.85 | G57: =ROUND(100*((1-SETTINGS!$B$2)*J57+SETTINGS!$B$2*Q57),2) | H57: 143.98793 | I57: 21.5 | J57: 0.169 | K57: 76.196107 | L57: 226.26871 | M57: 29 | N57: 0.92708333 | O57: 0.46595062 | P57: 0.53404938 | Q57: 0.28690291 | R57: higher | S57: FALSE | U57: no | V57: 29.383219 | W57: standard | X57: ACT | Y57: 00-0034827
A58: 57 | B58: Brock Bowers | C58: LV | D58: TE | E58: 17.88 | F58: 86.58 | G58: =ROUND(100*((1-SETTINGS!$B$2)*J58+SETTINGS!$B$2*Q58),2) | H58: 146.4786 | I58: 21.55 | J58: 0.1694 | K58: 102.72775 | L58: 219.35582 | M58: 6 | N58: 0.97435897 | O58: 0.56835443 | P58: 0.43164557 | Q58: 0.21640742 | R58: higher | S58: FALSE | U58: no | V58: 23.718489 | W58: standard | X58: ACT | Y58: 00-0039338
A59: 58 | B59: TreVeyon Henderson | C59: NE | D59: RB | E59: 17.63 | F59: 84.94 | G59: =ROUND(100*((1-SETTINGS!$B$2)*J59+SETTINGS!$B$2*Q59),2) | H59: 176.16169 | I59: 19.17 | J59: 0.1506 | K59: 107.00211 | L59: 291.12959 | M59: 13 | N59: 0.94285714 | O59: 0.52434617 | P59: 0.47565383 | Q59: 0.27909017 | R59: higher | S59: FALSE | U59: no | V59: 23.860859 | W59: standard | X59: ACT | Y59: 00-0040734
A60: 59 | B60: Jason Myers | C60: SEA | D60: K | E60: 17.62 | F60: 92.4 | G60: =ROUND(100*((1-SETTINGS!$B$2)*J60+SETTINGS!$B$2*Q60),2) | H60: 128.30808 | I60: 11.1 | J60: 0.0872 | K60: 35.810052 | L60: 168.93131 | M60: 4 | N60: 0.93023256 | O60: 0.10072832 | P60: 0.89927168 | Q60: 0.53228686 | R60: lower | S60: FALSE | U60: no | V60: 35.308048 | W60: low (kicker) | X60: ACT | Y60: 00-0031492
A61: 60 | B61: Patrick Mahomes | C61: KC | D61: QB | E61: 17.19 | F61: 87.27 | G61: =ROUND(100*((1-SETTINGS!$B$2)*J61+SETTINGS!$B$2*Q61),2) | H61: 235.99426 | I61: 16.2 | J61: 0.1273 | K61: 126.33516 | L61: 376.5701 | M61: 9 | N61: 0.93277311 | O61: 0.36752359 | P61: 0.63247641 | Q61: 0.35025021 | R61: higher | S61: TRUE | T61: Questionable | U61: no | V61: 30.957514 | W61: standard | X61: ACT | Y61: 00-0033873
A62: 61 | B62: Saquon Barkley | C62: PHI | D62: RB | E62: 17.06 | F62: 84.3 | G62: =ROUND(100*((1-SETTINGS!$B$2)*J62+SETTINGS!$B$2*Q62),2) | H62: 176.87906 | I62: 19.88 | J62: 0.1562 | K62: 107.71948 | L62: 291.84696 | M62: 12 | N62: 0.94761905 | O62: 0.57533157 | P62: 0.42466843 | Q62: 0.22810477 | R62: higher | S62: FALSE | U62: no | V62: 29.558445 | W62: standard | X62: ACT | Y62: 00-0034844
A63: 62 | B63: Sam Darnold | C63: SEA | D63: QB | E63: 16.35 | F63: 86.6 | G63: =ROUND(100*((1-SETTINGS!$B$2)*J63+SETTINGS!$B$2*Q63),2) | H63: 234.66665 | I63: 14.87 | J63: 0.1169 | K63: 125.00756 | L63: 375.2425 | M63: 10 | N63: 0.92436975 | O63: 0.36769669 | P63: 0.63230331 | Q63: 0.35007711 | R63: higher | S63: FALSE | U63: no | V63: 29.240847 | W63: standard | X63: ACT | Y63: 00-0034869
A64: 63 | B64: Lincoln Pare | C64: IND | D64: RB | E64: 16.07 | F64: 20.76 | G64: =ROUND(100*((1-SETTINGS!$B$2)*J64+SETTINGS!$B$2*Q64),2) | H64: 0.046117284 | I64: -156.95 | J64: 0 | K64: 0 | L64: 0.046117284 | M64: 208 | N64: 0.0095238095 | O64: 2.5485981e-08 | P64: 0.99999997 | Q64: 0.80343631 | R64: lower | S64: FALSE | U64: no | W64: standard | X64: ACT | Y64: 00-0041231
A65: 64 | B65: Desmond Reid | C65: BUF | D65: RB | E65: 16.07 | F65: 20.76 | G65: =ROUND(100*((1-SETTINGS!$B$2)*J65+SETTINGS!$B$2*Q65),2) | H65: 0.046117284 | I65: -156.95 | J65: 0 | K65: 0 | L65: 0.046117284 | M65: 208 | N65: 0.0095238095 | O65: 2.5485981e-08 | P65: 0.99999997 | Q65: 0.80343631 | R65: lower | S65: FALSE | U65: no | W65: standard | X65: ACT | Y65: 00-0041273
A66: 65 | B66: Kejon Owens | C66: MIN | D66: RB | E66: 16.07 | F66: 20.76 | G66: =ROUND(100*((1-SETTINGS!$B$2)*J66+SETTINGS!$B$2*Q66),2) | H66: 0.046117284 | I66: -156.95 | J66: 0 | K66: 0 | L66: 0.046117284 | M66: 208 | N66: 0.0095238095 | O66: 2.5485981e-08 | P66: 0.99999997 | Q66: 0.80343631 | R66: lower | S66: FALSE | U66: no | W66: standard | X66: ACT | Y66: 00-0041350
A67: 66 | B67: Brandon Aubrey | C67: DAL | D67: K | E67: 15.92 | F67: 89.1 | G67: =ROUND(100*((1-SETTINGS!$B$2)*J67+SETTINGS!$B$2*Q67),2) | H67: 127.8922 | I67: 10.69 | J67: 0.084 | K67: 35.394177 | L67: 168.51544 | M67: 5 | N67: 0.90697674 | O67: 0.17278652 | P67: 0.82721348 | Q67: 0.46022866 | R67: lower | S67: FALSE | U67: no | V67: 31.469503 | W67: low (kicker) | X67: ACT | Y67: 00-0037692
A68: 67 | B68: Kenneth Walker III | C68: KC | D68: RB | E68: 15.81 | F68: 83.45 | G68: =ROUND(100*((1-SETTINGS!$B$2)*J68+SETTINGS!$B$2*Q68),2) | H68: 175.02581 | I68: 18.03 | J68: 0.1417 | K68: 105.86623 | L68: 289.99371 | M68: 14 | N68: 0.93809524 | O68: 0.57975096 | P68: 0.42024904 | Q68: 0.22368538 | R68: higher | S68: FALSE | U68: no | V68: 25.865007 | W68: standard | X68: ACT | Y68: 00-0038134
A69: 68 | B69: Khalil Dinkins | C69: SF | D69: TE | E69: 15.7 | F69: 20.62 | G69: =ROUND(100*((1-SETTINGS!$B$2)*J69+SETTINGS!$B$2*Q69),2) | H69: 0.046117284 | I69: -124.88 | J69: 0 | K69: 0 | L69: -0.08029707 | M69: 194 | N69: 0.0076923077 | O69: 2.5485981e-08 | P69: 0.99999997 | Q69: 0.78476183 | R69: lower | S69: FALSE | U69: no | W69: standard | X69: ACT | Y69: 00-0041357
A70: 69 | B70: Louis Hansen | C70: HOU | D70: TE | E70: 15.7 | F70: 20.62 | G70: =ROUND(100*((1-SETTINGS!$B$2)*J70+SETTINGS!$B$2*Q70),2) | H70: 0.046117284 | I70: -124.88 | J70: 0 | K70: 0 | L70: -0.08029707 | M70: 194 | N70: 0.0076923077 | O70: 2.5485981e-08 | P70: 0.99999997 | Q70: 0.78476183 | R70: lower | S70: FALSE | U70: no | W70: standard | X70: ACT | Y70: 00-0041535
A71: 70 | B71: Jabari Small | C71: DET | D71: RB | E71: 15.6 | F71: 21.05 | G71: =ROUND(100*((1-SETTINGS!$B$2)*J71+SETTINGS!$B$2*Q71),2) | H71: 1.7114154 | I71: -155.28 | J71: 0 | K71: 0 | L71: 1.7114154 | M71: 207 | N71: 0.019047619 | O71: 0.023579595 | P71: 0.9764204 | Q71: 0.77985674 | R71: lower | S71: FALSE | U71: no | V71: 24.583668 | W71: standard | X71: ACT | Y71: 00-0039652
A72: 71 | B72: Ahmani Marshall | C72: CLE | D72: RB | E72: 15.22 | F72: 21.05 | G72: =ROUND(100*((1-SETTINGS!$B$2)*J72+SETTINGS!$B$2*Q72),2) | H72: 1.9123126 | I72: -155.08 | J72: 0 | K72: 0 | L72: 1.9123126 | M72: 206 | N72: 0.023809524 | O72: 0.042597985 | P72: 0.95740201 | Q72: 0.76083835 | R72: lower | S72: FALSE | U72: no | V72: 24.449509 | W72: standard | X72: ACT | Y72: 00-0040260
A73: 72 | B73: Anthony Tyus III | C73: CAR | D73: RB | E73: 15.16 | F73: 22.14 | G73: =ROUND(100*((1-SETTINGS!$B$2)*J73+SETTINGS!$B$2*Q73),2) | H73: 1.982408 | I73: -155.01 | J73: 0 | K73: 0 | L73: 1.982408 | M73: 203 | N73: 0.038095238 | O73: 0.045217286 | P73: 0.95478271 | Q73: 0.75821905 | R73: lower | S73: FALSE | U73: no | V73: 23.452911 | W73: standard | X73: ACT | Y73: 00-0040394
A74: 73 | B74: Dante Miller | C74: NYG | D74: RB | E74: 15.08 | F74: 22.44 | G74: =ROUND(100*((1-SETTINGS!$B$2)*J74+SETTINGS!$B$2*Q74),2) | H74: 2.0001108 | I74: -155 | J74: 0 | K74: 0 | L74: 2.0001108 | M74: 202 | N74: 0.042857143 | O74: 0.049414009 | P74: 0.95058599 | Q74: 0.75402233 | R74: lower | S74: FALSE | U74: no | V74: 27.302408 | W74: standard | X74: ACT | Y74: 00-0039230
A75: 74 | B75: Damien Alford | C75: NO | D75: WR | E75: 15.06 | F75: 20.83 | G75: =ROUND(100*((1-SETTINGS!$B$2)*J75+SETTINGS!$B$2*Q75),2) | H75: 0.061117284 | I75: -122.42 | J75: 0 | K75: 0 | L75: -0.017874415 | M75: 378 | N75: 0.010416667 | O75: 2.5485981e-08 | P75: 0.99999997 | Q75: 0.7528535 | R75: lower | S75: FALSE | U75: no | W75: standard | X75: ACT | Y75: 00-0040788
A76: 75 | B76: Jonathan Brady | C76: LV | D76: WR | E76: 15.06 | F76: 20.83 | G76: =ROUND(100*((1-SETTINGS!$B$2)*J76+SETTINGS!$B$2*Q76),2) | H76: 0.061117284 | I76: -122.42 | J76: 0 | K76: 0 | L76: -0.017874415 | M76: 378 | N76: 0.010416667 | O76: 2.5485981e-08 | P76: 0.99999997 | Q76: 0.7528535 | R76: lower | S76: FALSE | U76: no | W76: standard | X76: ACT | Y76: 00-0041022
A77: 76 | B77: Ben Patterson | C77: JAX | D77: WR | E77: 15.06 | F77: 20.83 | G77: =ROUND(100*((1-SETTINGS!$B$2)*J77+SETTINGS!$B$2*Q77),2) | H77: 0.061117284 | I77: -122.42 | J77: 0 | K77: 0 | L77: -0.017874415 | M77: 378 | N77: 0.010416667 | O77: 2.5485981e-08 | P77: 0.99999997 | Q77: 0.7528535 | R77: lower | S77: FALSE | U77: no | W77: standard | X77: ACT | Y77: 00-0041215
A78: 77 | B78: Gabriel Benyard | C78: BUF | D78: WR | E78: 15.06 | F78: 20.83 | G78: =ROUND(100*((1-SETTINGS!$B$2)*J78+SETTINGS!$B$2*Q78),2) | H78: 0.061117284 | I78: -122.42 | J78: 0 | K78: 0 | L78: -0.017874415 | M78: 378 | N78: 0.010416667 | O78: 2.5485981e-08 | P78: 0.99999997 | Q78: 0.7528535 | R78: lower | S78: FALSE | U78: no | W78: standard | X78: ACT | Y78: 00-0041222
A79: 78 | B79: Jalen Walthall | C79: NYJ | D79: WR | E79: 15.06 | F79: 20.83 | G79: =ROUND(100*((1-SETTINGS!$B$2)*J79+SETTINGS!$B$2*Q79),2) | H79: 0.061117284 | I79: -122.42 | J79: 0 | K79: 0 | L79: -0.017874415 | M79: 378 | N79: 0.010416667 | O79: 2.5485981e-08 | P79: 0.99999997 | Q79: 0.7528535 | R79: lower | S79: TRUE | T79: Reserve/Injured | U79: no | W79: standard | X79: ACT | Y79: 00-0041311
A80: 79 | B80: Luke Wysong | C80: MIN | D80: WR | E80: 15.06 | F80: 20.83 | G80: =ROUND(100*((1-SETTINGS!$B$2)*J80+SETTINGS!$B$2*Q80),2) | H80: 0.061117284 | I80: -122.42 | J80: 0 | K80: 0 | L80: -0.017874415 | M80: 378 | N80: 0.010416667 | O80: 2.5485981e-08 | P80: 0.99999997 | Q80: 0.7528535 | R80: lower | S80: FALSE | U80: no | W80: standard | X80: ACT | Y80: 00-0041356
A81: 80 | B81: Romello Brinson | C81: DAL | D81: WR | E81: 15.06 | F81: 20.83 | G81: =ROUND(100*((1-SETTINGS!$B$2)*J81+SETTINGS!$B$2*Q81),2) | H81: 0.061117284 | I81: -122.42 | J81: 0 | K81: 0 | L81: -0.017874415 | M81: 378 | N81: 0.010416667 | O81: 2.5485981e-08 | P81: 0.99999997 | Q81: 0.7528535 | R81: lower | S81: FALSE | U81: no | W81: standard | X81: ACT | Y81: 00-0041516
A82: 81 | B82: Tucker Kraft | C82: GB | D82: TE | E82: 15 | F82: 85.62 | G82: =ROUND(100*((1-SETTINGS!$B$2)*J82+SETTINGS!$B$2*Q82),2) | H82: 142.77334 | I82: 17.84 | J82: 0.1402 | K82: 99.02249 | L82: 215.65056 | M82: 7 | N82: 0.96923077 | O82: 0.59579733 | P82: 0.40420267 | Q82: 0.18896452 | R82: higher | S82: TRUE | T82: Questionable | U82: no | V82: 25.826677 | W82: standard | X82: ACT | Y82: 00-0038996
A83: 82 | B83: Colston Loveland | C83: CHI | D83: TE | E83: 14.98 | F83: 87.18 | G83: =ROUND(100*((1-SETTINGS!$B$2)*J83+SETTINGS!$B$2*Q83),2) | H83: 138.96957 | I83: 14.04 | J83: 0.1103 | K83: 95.218715 | L83: 211.84679 | M83: 9 | N83: 0.95897436 | O83: 0.47700521 | P83: 0.52299479 | Q83: 0.30775664 | R83: higher | S83: FALSE | U83: no | V83: 22.39608 | W83: standard | X83: ACT | Y83: 00-0040126
A84: 83 | B84: Frank Gore Jr. | C84: BUF | D84: RB | E84: 14.92 | F84: 24.19 | G84: =ROUND(100*((1-SETTINGS!$B$2)*J84+SETTINGS!$B$2*Q84),2) | H84: 2.119013 | I84: -154.88 | J84: 0 | K84: 0 | L84: 2.119013 | M84: 197 | N84: 0.066666667 | O84: 0.057262338 | P84: 0.94273766 | Q84: 0.746174 | R84: lower | S84: FALSE | U84: no | V84: 24.471413 | W84: standard | X84: ACT | Y84: 00-0039471
A85: 84 | B85: RJ Harvey | C85: DEN | D85: RB | E85: 14.83 | F85: 84.1 | G85: =ROUND(100*((1-SETTINGS!$B$2)*J85+SETTINGS!$B$2*Q85),2) | H85: 171.83337 | I85: 14.84 | J85: 0.1166 | K85: 102.67379 | L85: 286.80127 | M85: 15 | N85: 0.93333333 | O85: 0.52813255 | P85: 0.47186745 | Q85: 0.27530379 | R85: higher | S85: FALSE | U85: no | V85: 25.572052 | W85: standard | X85: ACT | Y85: 00-0040730
A86: 85 | B86: Cole Turner | C86: MIA | D86: TE | E86: 14.81 | F86: 42.91 | G86: =ROUND(100*((1-SETTINGS!$B$2)*J86+SETTINGS!$B$2*Q86),2) | H86: 3.1020489 | I86: -121.83 | J86: 0 | K86: 0.19158816 | L86: 2.9756345 | M86: 138 | N86: 0.2974359 | O86: 0.044088219 | P86: 0.95591178 | Q86: 0.74067363 | R86: lower | S86: FALSE | U86: no | V86: 26.461872 | W86: standard | X86: ACT | Y86: 00-0037078
A87: 86 | B87: Sean McKeon | C87: IND | D87: TE | E87: 14.77 | F87: 36.72 | G87: =ROUND(100*((1-SETTINGS!$B$2)*J87+SETTINGS!$B$2*Q87),2) | H87: 2.1306837 | I87: -122.8 | J87: 0 | K87: 0 | L87: 2.0042694 | M87: 153 | N87: 0.22051282 | O87: 0.046096717 | P87: 0.95390328 | Q87: 0.73866514 | R87: lower | S87: TRUE | T87: IR | U87: no | V87: 28.676838 | W87: standard | X87: ACT | Y87: 00-0036032
A88: 87 | B88: Carlos Washington | C88: MIA | D88: RB | E88: 14.77 | F88: 20.98 | G88: =ROUND(100*((1-SETTINGS!$B$2)*J88+SETTINGS!$B$2*Q88),2) | H88: 1.9589873 | I88: -155.04 | J88: 0 | K88: 0 | L88: 1.9589873 | M88: 205 | N88: 0.028571429 | O88: 0.065185588 | P88: 0.93481441 | Q88: 0.73825075 | R88: lower | S88: FALSE | U88: no | V88: 27.682978 | W88: standard | X88: ACT | Y88: 00-0038930
A89: 88 | B89: Lew Nichols III | C89: PIT | D89: RB | E89: 14.74 | F89: 29.72 | G89: =ROUND(100*((1-SETTINGS!$B$2)*J89+SETTINGS!$B$2*Q89),2) | H89: 4.8892909 | I89: -152.11 | J89: 0 | K89: 0 | L89: 4.8892909 | M89: 182 | N89: 0.13809524 | O89: 0.06638565 | P89: 0.93361435 | Q89: 0.73705069 | R89: lower | S89: FALSE | U89: no | V89: 25.043636 | W89: standard | X89: ACT | Y89: 00-0038409
A90: 89 | B90: Chris Collier | C90: LV | D90: RB | E90: 14.73 | F90: 24.75 | G90: =ROUND(100*((1-SETTINGS!$B$2)*J90+SETTINGS!$B$2*Q90),2) | H90: 2.1401455 | I90: -154.86 | J90: 0 | K90: 0 | L90: 2.1401455 | M90: 195 | N90: 0.076190476 | O90: 0.067113004 | P90: 0.932887 | Q90: 0.73632333 | R90: lower | S90: TRUE | T90: IR | U90: no | V90: 26.439968 | W90: standard | X90: ACT | Y90: 00-0039244
A91: 90 | B91: Jalen Virgil | C91: BUF | D91: WR | E91: 14.73 | F91: 21.34 | G91: =ROUND(100*((1-SETTINGS!$B$2)*J91+SETTINGS!$B$2*Q91),2) | H91: 1.1130127 | I91: -121.37 | J91: 0 | K91: 0 | L91: 1.034021 | M91: 377 | N91: 0.020833333 | O91: 0.016296691 | P91: 0.98370331 | Q91: 0.73655684 | R91: lower | S91: FALSE | U91: no | V91: 28.13747 | W91: standard | X91: ACT | Y91: 00-0037387
A92: 91 | B92: Israel Abanikanda | C92: DAL | D92: RB | E92: 14.72 | F92: 27.79 | G92: =ROUND(100*((1-SETTINGS!$B$2)*J92+SETTINGS!$B$2*Q92),2) | H92: 3.710085 | I92: -153.29 | J92: 0 | K92: 0 | L92: 3.710085 | M92: 187 | N92: 0.11428571 | O92: 0.067520777 | P92: 0.93247922 | Q92: 0.73591556 | R92: lower | S92: FALSE | U92: no | V92: 23.907404 | W92: standard | X92: ACT | Y92: 00-0038389
A93: 92 | B93: Lawrence Cager | C93: WAS | D93: TE | E93: 14.7 | F93: 34.59 | G93: =ROUND(100*((1-SETTINGS!$B$2)*J93+SETTINGS!$B$2*Q93),2) | H93: 2.0216294 | I93: -122.91 | J93: 0 | K93: 0 | L93: 1.895215 | M93: 158 | N93: 0.19487179 | O93: 0.049801546 | P93: 0.95019845 | Q93: 0.73496031 | R93: lower | S93: FALSE | U93: no | V93: 29.032766 | W93: standard | X93: ACT | Y93: 00-0036145
A94: 93 | B94: Gary Brightwell | C94: CIN | D94: RB | E94: 14.69 | F94: 32.33 | G94: =ROUND(100*((1-SETTINGS!$B$2)*J94+SETTINGS!$B$2*Q94),2) | H94: 6.2524651 | I94: -150.74 | J94: 0 | K94: 0.72534325 | L94: 6.2524651 | M94: 175 | N94: 0.17142857 | O94: 0.069019925 | P94: 0.93098008 | Q94: 0.73441641 | R94: lower | S94: FALSE | U94: no | V94: 28.507088 | W94: standard | X94: ACT | Y94: 00-0036569
A95: 94 | B95: Patrick Taylor | C95: SF | D95: RB | E95: 14.69 | F95: 27.38 | G95: =ROUND(100*((1-SETTINGS!$B$2)*J95+SETTINGS!$B$2*Q95),2) | H95: 3.4151286 | I95: -153.58 | J95: 0 | K95: 0 | L95: 3.4151286 | M95: 188 | N95: 0.10952381 | O95: 0.069092205 | P95: 0.93090779 | Q95: 0.73434413 | R95: lower | S95: FALSE | U95: no | V95: 28.342813 | W95: standard | X95: ACT | Y95: 00-0035973
A96: 95 | B96: Sincere McCormick | C96: SF | D96: RB | E96: 14.65 | F96: 26.2 | G96: =ROUND(100*((1-SETTINGS!$B$2)*J96+SETTINGS!$B$2*Q96),2) | H96: 2.386798 | I96: -154.61 | J96: 0 | K96: 0 | L96: 2.386798 | M96: 191 | N96: 0.095238095 | O96: 0.071166261 | P96: 0.92883374 | Q96: 0.73227008 | R96: lower | S96: FALSE | U96: no | V96: 25.974524 | W96: standard | X96: ACT | Y96: 00-0037509
A97: 96 | B97: Wil Lutz | C97: DEN | D97: K | E97: 14.57 | F97: 84.93 | G97: =ROUND(100*((1-SETTINGS!$B$2)*J97+SETTINGS!$B$2*Q97),2) | H97: 123.48417 | I97: 6.28 | J97: 0.0494 | K97: 30.986148 | L97: 164.10741 | M97: 8 | N97: 0.8372093 | O97: 0.10216082 | P97: 0.89783918 | Q97: 0.53085436 | R97: lower | S97: FALSE | U97: no | V97: 32.15398 | W97: low (kicker) | X97: ACT | Y97: 00-0032569
A98: 97 | B98: Max Hurleman | C98: PIT | D98: RB | E98: 14.56 | F98: 22.68 | G98: =ROUND(100*((1-SETTINGS!$B$2)*J98+SETTINGS!$B$2*Q98),2) | H98: 2.0377128 | I98: -154.96 | J98: 0 | K98: 0 | L98: 2.0377128 | M98: 200 | N98: 0.052380952 | O98: 0.075443538 | P98: 0.92455646 | Q98: 0.7279928 | R98: lower | S98: FALSE | U98: no | V98: 24.86841 | W98: standard | X98: ACT | Y98: 00-0040618
A99: 98 | B99: Kendric Pryor | C99: CIN | D99: WR | E99: 14.5 | F99: 23.82 | G99: =ROUND(100*((1-SETTINGS!$B$2)*J99+SETTINGS!$B$2*Q99),2) | H99: 1.9226629 | I99: -120.56 | J99: 0 | K99: 0 | L99: 1.8436712 | M99: 364 | N99: 0.0546875 | O99: 0.027808404 | P99: 0.9721916 | Q99: 0.72504513 | R99: lower | S99: FALSE | U99: no | V99: 28.652197 | W99: standard | X99: ACT | Y99: 00-0037422
A100: 99 | B100: Salvon Ahmed | C100: CHI | D100: RB | E100: 14.48 | F100: 25.65 | G100: =ROUND(100*((1-SETTINGS!$B$2)*J100+SETTINGS!$B$2*Q100),2) | H100: 2.2792333 | I100: -154.72 | J100: 0 | K100: 0 | L100: 2.2792333 | M100: 192 | N100: 0.09047619 | O100: 0.079530341 | P100: 0.92046966 | Q100: 0.723906 | R100: lower | S100: FALSE | U100: no | V100: 27.674765 | W100: standard | X100: ACT | Y100: 00-0036020
...

Sheet QB
A1: Rank | B1: Player | C1: Team | D1: Pos | E1: Overall Draft Score (replacement-adjusted) | F1: Position Draft Score (default weight) | G1: Custom-Weight Score (weight from SETTINGS) | H1: Projected 2026 Points | I1: Points Over Replacement | J1: Overall Value (points over replacement / max) | K1: Points P10 | L1: Points P90 | M1: Pos Points Rank | N1: Pos Points Percentile | O1: Missed-Time Injury Probability | P1: Healthy Probability | Q1: Healthy Probability vs Position Mean (+0.5) | R1: Injury Risk Band | S1: Current Injury Listing (screen date) | T1: Current Listing Status | U1: Rookie | V1: Age | W1: Points Model Confidence | X1: Roster Status (Aug 9) | Y1: Player ID
A2: 1 | B2: Josh Allen | C2: BUF | D2: QB | E2: 70.39 | F2: 91.32 | G2: =ROUND(100*((1-SETTINGS!$B$2)*N2+SETTINGS!$B$2*P2),2) | H2: 322.74206 | I2: 102.95 | J2: 0.809 | K2: 213.08296 | L2: 463.3179 | M2: 1 | N2: 1 | O2: 0.43420955 | P2: 0.56579045 | Q2: 0.28356424 | R2: higher | S2: FALSE | U2: no | V2: 30.281252 | W2: standard | X2: ACT | Y2: 00-0034857
A3: 2 | B3: Jared Goff | C3: DET | D3: QB | E3: 25.69 | F3: 90.84 | G3: =ROUND(100*((1-SETTINGS!$B$2)*N3+SETTINGS!$B$2*P3),2) | H3: 244.90236 | I3: 25.11 | J3: 0.1973 | K3: 135.24327 | L3: 385.4782 | M3: 8 | N3: 0.94117647 | O3: 0.22253456 | P3: 0.77746544 | Q3: 0.49523924 | R3: moderate | S3: FALSE | U3: no | V3: 31.882927 | W3: standard | X3: ACT | Y3: 00-0033106
A4: 3 | B4: Drake Maye | C4: NE | D4: QB | E4: 38.27 | F4: 90.36 | G4: =ROUND(100*((1-SETTINGS!$B$2)*N4+SETTINGS!$B$2*P4),2) | H4: 272.09196 | I4: 52.3 | J4: 0.411 | K4: 162.43286 | L4: 412.6678 | M4: 2 | N4: 0.99159664 | O4: 0.44824514 | P4: 0.55175486 | Q4: 0.26952865 | R4: higher | S4: FALSE | U4: no | V4: 24.005968 | W4: standard | X4: ACT | Y4: 00-0039851
A5: 4 | B5: Caleb Williams | C5: CHI | D5: QB | E5: 33.32 | F5: 89.49 | G5: =ROUND(100*((1-SETTINGS!$B$2)*N5+SETTINGS!$B$2*P5),2) | H5: 263.46877 | I5: 43.68 | J5: 0.3433 | K5: 153.80967 | L5: 404.04461 | M5: 4 | N5: 0.97478992 | O5: 0.42488997 | P5: 0.57511003 | Q5: 0.29288382 | R5: higher | S5: FALSE | U5: no | V5: 24.786272 | W5: standard | X5: ACT | Y5: 00-0039918
A6: 5 | B6: Jalen Hurts | C6: PHI | D6: QB | E6: 34.96 | F6: 89.23 | G6: =ROUND(100*((1-SETTINGS!$B$2)*N6+SETTINGS!$B$2*P6),2) | H6: 267.55492 | I6: 47.76 | J6: 0.3753 | K6: 157.89582 | L6: 408.13076 | M6: 3 | N6: 0.98319328 | O6: 0.47105394 | P6: 0.52894606 | Q6: 0.24671986 | R6: higher | S6: FALSE | U6: no | V6: 28.069023 | W6: standard | X6: ACT | Y6: 00-0036389
A7: 6 | B7: Bo Nix | C7: DEN | D7: QB | E7: 28.99 | F7: 88.94 | G7: =ROUND(100*((1-SETTINGS!$B$2)*N7+SETTINGS!$B$2*P7),2) | H7: 256.37092 | I7: 36.58 | J7: 0.2875 | K7: 146.71182 | L7: 396.94676 | M7: 5 | N7: 0.96638655 | O7: 0.41847222 | P7: 0.58152778 | Q7: 0.29930158 | R7: higher | S7: FALSE | U7: no | V7: 26.51663 | W7: standard | X7: ACT | Y7: 00-0039732
A8: 7 | B8: Justin Herbert | C8: LAC | D8: QB | E8: 24.27 | F8: 88.44 | G8: =ROUND(100*((1-SETTINGS!$B$2)*N8+SETTINGS!$B$2*P8),2) | H8: 248.61333 | I8: 28.82 | J8: 0.2265 | K8: 138.95423 | L8: 389.18917 | M8: 6 | N8: 0.95798319 | O8: 0.41010254 | P8: 0.58989746 | Q8: 0.30767125 | R8: higher | S8: FALSE | U8: no | V8: 28.47971 | W8: standard | X8: ACT | Y8: 00-0036355
A9: 8 | B9: Patrick Mahomes | C9: KC | D9: QB | E9: 17.19 | F9: 87.27 | G9: =ROUND(100*((1-SETTINGS!$B$2)*N9+SETTINGS!$B$2*P9),2) | H9: 235.99426 | I9: 16.2 | J9: 0.1273 | K9: 126.33516 | L9: 376.5701 | M9: 9 | N9: 0.93277311 | O9: 0.36752359 | P9: 0.63247641 | Q9: 0.35025021 | R9: higher | S9: TRUE | T9: Questionable | U9: no | V9: 30.957514 | W9: standard | X9: ACT | Y9: 00-0033873
A10: 9 | B10: Baker Mayfield | C10: TB | D10: QB | E10: 21.54 | F10: 86.99 | G10: =ROUND(100*((1-SETTINGS!$B$2)*N10+SETTINGS!$B$2*P10),2) | H10: 245.48501 | I10: 25.69 | J10: 0.2019 | K10: 135.82591 | L10: 386.06085 | M10: 7 | N10: 0.94957983 | O10: 0.44861377 | P10: 0.55138623 | Q10: 0.26916002 | R10: higher | S10: FALSE | U10: no | V10: 31.384628 | W10: standard | X10: ACT | Y10: 00-0034855
A11: 10 | B11: Matthew Stafford | C11: LA | D11: QB | E11: 8.71 | F11: 86.96 | G11: =ROUND(100*((1-SETTINGS!$B$2)*N11+SETTINGS!$B$2*P11),2) | H11: 219.79202 | I11: 0 | J11: 0 | K11: 110.13292 | L11: 360.36786 | M11: 12 | N11: 0.90756303 | O11: 0.28233285 | P11: 0.71766715 | Q11: 0.43544095 | R11: moderate | S11: FALSE | U11: no | V11: 38.566158 | W11: standard | X11: ACT | Y11: 00-0026498
A12: 11 | B12: Sam Darnold | C12: SEA | D12: QB | E12: 16.35 | F12: 86.6 | G12: =ROUND(100*((1-SETTINGS!$B$2)*N12+SETTINGS!$B$2*P12),2) | H12: 234.66665 | I12: 14.87 | J12: 0.1169 | K12: 125.00756 | L12: 375.2425 | M12: 10 | N12: 0.92436975 | O12: 0.36769669 | P12: 0.63230331 | Q12: 0.35007711 | R12: higher | S12: FALSE | U12: no | V12: 29.240847 | W12: standard | X12: ACT | Y12: 00-0034869
A13: 12 | B13: Trevor Lawrence | C13: JAX | D13: QB | E13: 8.76 | F13: 85.03 | G13: =ROUND(100*((1-SETTINGS!$B$2)*N13+SETTINGS!$B$2*P13),2) | H13: 224.00199 | I13: 4.21 | J13: 0.0331 | K13: 114.34289 | L13: 364.57783 | M13: 11 | N13: 0.91596639 | O13: 0.41239855 | P13: 0.58760145 | Q13: 0.30537525 | R13: higher | S13: FALSE | U13: no | V13: 26.905413 | W13: standard | X13: ACT | Y13: 00-0036971
A14: 13 | B14: Joe Burrow | C14: CIN | D14: QB | E14: 8.62 | F14: 83.51 | G14: =ROUND(100*((1-SETTINGS!$B$2)*N14+SETTINGS!$B$2*P14),2) | H14: 180.22304 | I14: -39.57 | J14: 0 | K14: 70.563941 | L14: 320.79888 | M14: 17 | N14: 0.86554622 | O14: 0.28680191 | P14: 0.71319809 | Q14: 0.43097188 | R14: moderate | S14: FALSE | U14: no | V14: 29.725456 | W14: standard | X14: ACT | Y14: 00-0036442
A15: 14 | B15: Jaxson Dart | C15: NYG | D15: QB | E15: 5.89 | F15: 83.46 | G15: =ROUND(100*((1-SETTINGS!$B$2)*N15+SETTINGS!$B$2*P15),2) | H15: 207.25922 | I15: -12.53 | J15: 0 | K15: 97.600127 | L15: 347.83506 | M15: 13 | N15: 0.89915966 | O15: 0.42344358 | P15: 0.57655642 | Q15: 0.29433021 | R15: higher | S15: FALSE | U15: no | V15: 23.305065 | W15: standard | X15: ACT | Y15: 00-0040691
A16: 15 | B16: Jordan Love | C16: GB | D16: QB | E16: 5.83 | F16: 82.06 | G16: =ROUND(100*((1-SETTINGS!$B$2)*N16+SETTINGS!$B$2*P16),2) | H16: 196.14107 | I16: -23.65 | J16: 0 | K16: 86.481977 | L16: 336.71691 | M16: 15 | N16: 0.88235294 | O16: 0.42616504 | P16: 0.57383496 | Q16: 0.29160875 | R16: higher | S16: FALSE | U16: no | V16: 27.830824 | W16: standard | X16: ACT | Y16: 00-0036264
A17: 16 | B17: Lamar Jackson | C17: BAL | D17: QB | E17: 5.06 | F17: 81.97 | G17: =ROUND(100*((1-SETTINGS!$B$2)*N17+SETTINGS!$B$2*P17),2) | H17: 204.22869 | I17: -15.56 | J17: 0 | K17: 94.56959 | L17: 344.80453 | M17: 14 | N17: 0.8907563 | O17: 0.46477309 | P17: 0.53522691 | Q17: 0.25300071 | R17: higher | S17: FALSE | U17: no | V17: 29.648794 | W17: standard | X17: ACT | Y17: 00-0034796
A18: 17 | B18: Cam Ward | C18: TEN | D18: QB | E18: 6.03 | F18: 81.59 | G18: =ROUND(100*((1-SETTINGS!$B$2)*N18+SETTINGS!$B$2*P18),2) | H18: 191.05727 | I18: -28.73 | J18: 0 | K18: 81.398176 | L18: 331.63311 | M18: 16 | N18: 0.87394958 | O18: 0.41605384 | P18: 0.58394616 | Q18: 0.30171995 | R18: higher | S18: FALSE | U18: no | V18: 24.271545 | W18: standard | X18: ACT | Y18: 00-0040676
A19: 18 | B19: Dak Prescott | C19: DAL | D19: QB | E19: 7.37 | F19: 80.91 | G19: =ROUND(100*((1-SETTINGS!$B$2)*N19+SETTINGS!$B$2*P19),2) | H19: 176.68635 | I19: -43.11 | J19: 0 | K19: 67.027257 | L19: 317.26219 | M19: 19 | N19: 0.8487395 | O19: 0.3492731 | P19: 0.6507269 | Q19: 0.3685007 | R19: moderate | S19: FALSE | U19: no | V19: 33.093082 | W19: standard | X19: ACT | Y19: 00-0033077
A20: 19 | B20: Tyler Shough | C20: NO | D20: QB | E20: 7.03 | F20: 79.9 | G20: =ROUND(100*((1-SETTINGS!$B$2)*N20+SETTINGS!$B$2*P20),2) | H20: 169.78443 | I20: -50.01 | J20: 0 | K20: 60.125335 | L20: 310.36027 | M20: 20 | N20: 0.84033613 | O20: 0.36619745 | P20: 0.63380255 | Q20: 0.35157634 | R20: higher | S20: FALSE | U20: no | V20: 26.927315 | W20: standard | X20: ACT | Y20: 00-0040743
A21: 20 | B21: Aaron Rodgers | C21: PIT | D21: QB | E21: 7.34 | F21: 79.54 | G21: =ROUND(100*((1-SETTINGS!$B$2)*N21+SETTINGS!$B$2*P21),2) | H21: 162.59147 | I21: -57.2 | J21: 0 | K21: 52.932375 | L21: 303.16731 | M21: 21 | N21: 0.83193277 | O21: 0.3508306 | P21: 0.6491694 | Q21: 0.3669432 | R21: higher | S21: FALSE | U21: no | V21: 42.74968 | W21: standard | X21: ACT | Y21: 00-0023459
... A30: 29 | B30: Bryce Young | C30: CAR | D30: QB | E30: 3.84 | F30: 75.36 | G30: =ROUND(100*((1-SETTINGS!$B$2)*N30+SETTINGS!$B$2*P30),2) | H30: 161.513 | I30: -58.28 | J30: 0 | K30: 51.853906 | L30: 302.08884 | M30: 22 | N30: 0.82352941 | O30: 0.52587438 | P30: 0.47412562 | Q30: 0.19189941 | R30: higher | S30: FALSE | U30: no | V30: 25.103868 | W30: standard | X30: ACT | Y30: 00-0039150
A31: 30 | B31: Tua Tagovailoa | C31: ATL | D31: QB | E31: 8.53 | F31: 74.68 | G31: =ROUND(100*((1-SETTINGS!$B$2)*N31+SETTINGS!$B$2*P31),2) | H31: 114.61954 | I31: -105.17 | J31: 0 | K31: 4.9604442 | L31: 255.19538 | M31: 30 | N31: 0.75630252 | O31: 0.29103142 | P31: 0.70896858 | Q31: 0.42674238 | R31: moderate | S31: TRUE | T31: Questionable | U31: no | V31: 28.501612 | W31: standard | X31: ACT | Y31: 00-0036212
A32: 31 | B32: Justin Fields | C32: KC | D32: QB | E32: 5.8 | F32: 73.3 | G32: =ROUND(100*((1-SETTINGS!$B$2)*N32+SETTINGS!$B$2*P32),2) | H32: 120.25003 | I32: -99.54 | J32: 0 | K32: 10.590934 | L32: 260.82587 | M32: 28 | N32: 0.77310924 | O32: 0.42757457 | P32: 0.57242543 | Q32: 0.29019923 | R32: higher | S32: FALSE | U32: no | V32: 27.494062 | W32: standard | X32: ACT | Y32: 00-0036945
A33: 32 | B33: Mac Jones | C33: SF | D33: QB | E33: 9.01 | F33: 72.47 | G33: =ROUND(100*((1-SETTINGS!$B$2)*N33+SETTINGS!$B$2*P33),2) | H33: 85.655328 | I33: -134.14 | J33: 0 | K33: 0 | L33: 226.23117 | M33: 34 | N33: 0.72268908 | O33: 0.26712335 | P33: 0.73287665 | Q33: 0.45065044 | R33: moderate | S33: FALSE | U33: no | V33: 27.989624 | W33: standard | X33: ACT | Y33: 00-0036972
A34: 33 | B34: Jayden Daniels | C34: WAS | D34: QB | E34: 7.22 | F34: 72.02 | G34: =ROUND(100*((1-SETTINGS!$B$2)*N34+SETTINGS!$B$2*P34),2) | H34: 93.543455 | I34: -126.25 | J34: 0 | K34: 0 | L34: 234.1193 | M34: 32 | N34: 0.7394958 | O34: 0.35692143 | P34: 0.64307857 | Q34: 0.36085237 | R34: higher | S34: FALSE | U34: no | V34: 25.70347 | W34: standard | X34: ACT | Y34: 00-0039910
A35: 34 | B35: Michael Penix Jr. | C35: ATL | D35: QB | E35: 8.33 | F35: 71.11 | G35: =ROUND(100*((1-SETTINGS!$B$2)*N35+SETTINGS!$B$2*P35),2) | H35: 82.425923 | I35: -137.37 | J35: 0 | K35: 0 | L35: 223.00176 | M35: 35 | N35: 0.71428571 | O35: 0.30147154 | P35: 0.69852846 | Q35: 0.41630226 | R35: moderate | S35: TRUE | T35: Questionable | U35: no | V35: 26.316763 | W35: standard | X35: ACT | Y35: 00-0039917
A36: 35 | B36: J.J. McCarthy | C36: MIN | D36: QB | E36: 6.64 | F36: 70.77 | G36: =ROUND(100*((1-SETTINGS!$B$2)*N36+SETTINGS!$B$2*P36),2) | H36: 89.648551 | I36: -130.14 | J36: 0 | K36: 0 | L36: 230.22439 | M36: 33 | N36: 0.73109244 | O36: 0.38596822 | P36: 0.61403178 | Q36: 0.33180557 | R36: higher | S36: FALSE | U36: no | V36: 23.614449 | W36: standard | X36: ACT | Y36: 00-0039923
A37: 36 | B37: Riley Leonard | C37: IND | D37: QB | E37: 10.56 | F37: 70.65 | G37: =ROUND(100*((1-SETTINGS!$B$2)*N37+SETTINGS!$B$2*P37),2) | H37: 68.060366 | I37: -151.73 | J37: 0 | K37: 0 | L37: 208.63621 | M37: 39 | N37: 0.68067227 | O37: 0.19001409 | P37: 0.80998591 | Q37: 0.5277597 | R37: lower | S37: FALSE | U37: no | V37: 23.967638 | W37: standard | X37: ACT | Y37: 00-0040206
A38: 37 | B38: Quinn Ewers | C38: MIA | D38: QB | E38: 9.1 | F38: 69.87 | G38: =ROUND(100*((1-SETTINGS!$B$2)*N38+SETTINGS!$B$2*P38),2) | H38: 71.707461 | I38: -148.08 | J38: 0 | K38: 0 | L38: 212.2833 | M38: 38 | N38: 0.68907563 | O38: 0.26297702 | P38: 0.73702298 | Q38: 0.45479677 | R38: moderate | S38: FALSE | U38: no | V38: 23.4666 | W38: standard | X38: ACT | Y38: 00-0040234
A39: 38 | B39: Marcus Mariota | C39: WAS | D39: QB | E39: 7.44 | F39: 69.55 | G39: =ROUND(100*((1-SETTINGS!$B$2)*N39+SETTINGS!$B$2*P39),2) | H39: 80.64105 | I39: -139.15 | J39: 0 | K39: 0 | L39: 221.21689 | M39: 36 | N39: 0.70588235 | O39: 0.34592804 | P39: 0.65407196 | Q39: 0.37184576 | R39: moderate | S39: FALSE | U39: no | V39: 32.838455 | W39: standard | X39: ACT | Y39: 00-0032268
A40: 39 | B40: Joe Flacco | C40: CIN | D40: QB | E40: 8.08 | F40: 69.52 | G40: =ROUND(100*((1-SETTINGS!$B$2)*N40+SETTINGS!$B$2*P40),2) | H40: 79.285153 | I40: -140.51 | J40: 0 | K40: 0 | L40: 219.86099 | M40: 37 | N40: 0.69747899 | O40: 0.31371272 | P40: 0.68628728 | Q40: 0.40406108 | R40: moderate | S40: FALSE | U40: no | V40: 41.624401 | W40: standard | X40: ACT | Y40: 00-0026158
A41: 40 | B41: Carson Wentz | C41: MIN | D41: QB | E41: 9.49 | F41: 68.92 | G41: =ROUND(100*((1-SETTINGS!$B$2)*N41+SETTINGS!$B$2*P41),2) | H41: 65.648848 | I41: -154.14 | J41: 0 | K41: 0 | L41: 206.22469 | M41: 40 | N41: 0.67226891 | O41: 0.24331258 | P41: 0.75668742 | Q41: 0.47446122 | R41: moderate | S41: FALSE | U41: no | V41: 33.67078 | W41: standard | X41: ACT | Y41: 00-0032950
A42: 41 | B42: Dillon Gabriel | C42: CLE | D42: QB | E42: 9.06 | F42: 67.82 | G42: =ROUND(100*((1-SETTINGS!$B$2)*N42+SETTINGS!$B$2*P42),2) | H42: 64.863561 | I42: -154.93 | J42: 0 | K42: 0 | L42: 205.4394 | M42: 41 | N42: 0.66386555 | O42: 0.26463087 | P42: 0.73536913 | Q42: 0.45314292 | R42: moderate | S42: FALSE | U42: no | V42: 25.676092 | W42: standard | X42: ACT | Y42: 00-0040704
A43: 42 | B43: Jameis Winston | C43: NYG | D43: QB | E43: 9.99 | F43: 66.72 | G43: =ROUND(100*((1-SETTINGS!$B$2)*N43+SETTINGS!$B$2*P43),2) | H43: 44.639282 | I43: -175.15 | J43: 0 | K43: 9.9978768 | L43: 89.01642 | M43: 44 | N43: 0.63865546 | O43: 0.21846044 | P43: 0.78153956 | Q43: 0.49931336 | R43: moderate | S43: FALSE | U43: no | V43: 32.652279 | W43: standard | X43: ACT | Y43: 00-0031503
A44: 43 | B44: Anthony Richardson | C44: IND | D44: QB | E44: 8.07 | F44: 66.16 | G44: =ROUND(100*((1-SETTINGS!$B$2)*N44+SETTINGS!$B$2*P44),2) | H44: 61.706992 | I44: -158.09 | J44: 0 | K44: 0 | L44: 202.28283 | M44: 42 | N44: 0.65546218 | O44: 0.31403754 | P44: 0.68596246 | Q44: 0.40373626 | R44: moderate | S44: FALSE | U44: no | V44: 24.279758 | W44: standard | X44: ACT | Y44: 00-0039164
A45: 44 | B45: Davis Mills | C45: HOU | D45: QB | E45: 10.09 | F45: 66.15 | G45: =ROUND(100*((1-SETTINGS!$B$2)*N45+SETTINGS!$B$2*P45),2) | H45: 44.548753 | I45: -175.24 | J45: 0 | K45: 9.9073478 | L45: 88.925891 | M45: 45 | N45: 0.6302521 | O45: 0.21351218 | P45: 0.78648782 | Q45: 0.50426162 | R45: moderate | S45: FALSE | U45: no | V45: 27.86368 | W45: standard | X45: ACT | Y45: 00-0036898
A46: 45 | B46: Spencer Rattler | C46: NO | D46: QB | E46: 8.72 | F46: 66.13 | G46: =ROUND(100*((1-SETTINGS!$B$2)*N46+SETTINGS!$B$2*P46),2) | H46: 56.840522 | I46: -162.95 | J46: 0 | K46: 0 | L46: 197.41636 | M46: 43 | N46: 0.64705882 | O46: 0.28159948 | P46: 0.71840052 | Q46: 0.43617431 | R46: moderate | S46: FALSE | U46: no | V46: 25.925241 | W46: standard | X46: ACT | Y46: 00-0039376
A47: 46 | B47: Tyrod Taylor | C47: GB | D47: QB | E47: 9.39 | F47: 64.78 | G47: =ROUND(100*((1-SETTINGS!$B$2)*N47+SETTINGS!$B$2*P47),2) | H47: 43.682119 | I47: -176.11 | J47: 0 | K47: 9.0407133 | L47: 88.059257 | M47: 46 | N47: 0.62184874 | O47: 0.24840789 | P47: 0.75159211 | Q47: 0.46936591 | R47: moderate | S47: FALSE | U47: no | V47: 37.079475 | W47: standard | X47: ACT | Y47: 00-0028118
... A56: 55 | B56: Mason Rudolph | C56: PIT | D56: QB | E56: 11.36 | F56: 60.03 | G56: =ROUND(100*((1-SETTINGS!$B$2)*N56+SETTINGS!$B$2*P56),2) | H56: 27.041444 | I56: -192.75 | J56: 0 | K56: 0 | L56: 71.418582 | M56: 56 | N56: 0.53781513 | O56: 0.14953916 | P56: 0.85046084 | Q56: 0.56823463 | R56: lower | S56: FALSE | U56: no | V56: 31.127264 | W56: standard | X56: ACT | Y56: 00-0034771
A57: 56 | B57: Jake Browning | C57: TB | D57: QB | E57: 9.84 | F57: 59.19 | G57: =ROUND(100*((1-SETTINGS!$B$2)*N57+SETTINGS!$B$2*P57),2) | H57: 28.670312 | I57: -191.12 | J57: 0 | K57: 0 | L57: 73.04745 | M57: 55 | N57: 0.54621849 | O57: 0.22562327 | P57: 0.77437673 | Q57: 0.49215052 | R57: moderate | S57: TRUE | T57: Questionable | U57: no | V57: 30.390768 | W57: standard | X57: ACT | Y57: 00-0035100
A58: 57 | B58: Joe Milton III | C58: DAL | D58: QB | E58: 10.65 | F58: 58.65 | G58: =ROUND(100*((1-SETTINGS!$B$2)*N58+SETTINGS!$B$2*P58),2) | H58: 22.759675 | I58: -197.03 | J58: 0 | K58: 0 | L58: 67.136813 | M58: 57 | N58: 0.52941176 | O58: 0.18527344 | P58: 0.81472656 | Q58: 0.53250036 | R58: lower | S58: FALSE | U58: no | V58: 26.48925 | W58: standard | X58: ACT | Y58: 00-0039398
A59: 58 | B59: Deshaun Watson | C59: CLE | D59: QB | E59: 11.77 | F59: 58.43 | G59: =ROUND(100*((1-SETTINGS!$B$2)*N59+SETTINGS!$B$2*P59),2) | H59: 20.022342 | I59: -199.77 | J59: 0 | K59: 0 | L59: 64.39948 | M59: 59 | N59: 0.51260504 | O59: 0.1291461 | P59: 0.8708539 | Q59: 0.5886277 | R59: lower | S59: FALSE | U59: no | V59: 30.965729 | W59: standard | X59: ACT | Y59: 00-0033537
A60: 59 | B60: Trey Lance | C60: LAC | D60: QB | E60: 10.29 | F60: 57.62 | G60: =ROUND(100*((1-SETTINGS!$B$2)*N60+SETTINGS!$B$2*P60),2) | H60: 21.888437 | I60: -197.9 | J60: 0 | K60: 0 | L60: 66.265576 | M60: 58 | N60: 0.5210084 | O60: 0.20311668 | P60: 0.79688332 | Q60: 0.51465711 | R60: moderate | S60: FALSE | U60: no | V60: 26.314024 | W60: standard | X60: ACT | Y60: 00-0037012
A61: 60 | B61: Drew Lock | C61: SEA | D61: QB | E61: 11.58 | F61: 57.56 | G61: =ROUND(100*((1-SETTINGS!$B$2)*N61+SETTINGS!$B$2*P61),2) | H61: 17.164568 | I61: -202.63 | J61: 0 | K61: 0 | L61: 61.541706 | M61: 60 | N61: 0.50420168 | O61: 0.13890931 | P61: 0.86109069 | Q61: 0.57886448 | R61: lower | S61: FALSE | U61: no | V61: 29.807594 | W61: standard | X61: ACT | Y61: 00-0035704
A62: 61 | B62: Gardner Minshew | C62: AZ | D62: QB | E62: 10.68 | F62: 55.99 | G62: =ROUND(100*((1-SETTINGS!$B$2)*N62+SETTINGS!$B$2*P62),2) | H62: 16.988505 | I62: -202.8 | J62: 0 | K62: 0 | L62: 61.365643 | M62: 61 | N62: 0.49579832 | O62: 0.18387905 | P62: 0.81612095 | Q62: 0.53389475 | R62: lower | S62: FALSE | U62: no | V62: 30.294941 | W62: standard | X62: ACT | Y62: 00-0035289
A63: 62 | B63: Tanner McKee | C63: PHI | D63: QB | E63: 11.34 | F63: 55.3 | G63: =ROUND(100*((1-SETTINGS!$B$2)*N63+SETTINGS!$B$2*P63),2) | H63: 14.752529 | I63: -205.04 | J63: 0 | K63: 0 | L63: 59.129667 | M63: 63 | N63: 0.4789916 | O63: 0.15083774 | P63: 0.84916226 | Q63: 0.56693605 | R63: lower | S63: FALSE | U63: no | V63: 26.34688 | W63: standard | X63: ACT | Y63: 00-0038400
A64: 63 | B64: Max Brosmer | C64: MIN | D64: QB | E64: 10.32 | F64: 54.95 | G64: =ROUND(100*((1-SETTINGS!$B$2)*N64+SETTINGS!$B$2*P64),2) | H64: 16.351773 | I64: -203.44 | J64: 0 | K64: 0 | L64: 60.728911 | M64: 62 | N64: 0.48739496 | O64: 0.20197008 | P64: 0.79802992 | Q64: 0.51580372 | R64: moderate | S64: FALSE | U64: no | V64: 25.42968 | W64: standard | X64: ACT | Y64: 00-0040494
A65: 64 | B65: Zach Wilson | C65: NO | D65: QB | E65: 12.01 | F65: 54.63 | G65: =ROUND(100*((1-SETTINGS!$B$2)*N65+SETTINGS!$B$2*P65),2) | H65: 13.568083 | I65: -206.22 | J65: 0 | K65: 0 | L65: 57.945221 | M65: 65 | N65: 0.46218487 | O65: 0.11734208 | P65: 0.88265792 | Q65: 0.60043171 | R65: lower | S65: FALSE | U65: no | V65: 27.080639 | W65: standard | X65: ACT | Y65: 00-0037013
A66: 65 | B66: Shane Buechele | C66: BUF | D66: QB | E66: 13.06 | F66: 54.34 | G66: =ROUND(100*((1-SETTINGS!$B$2)*N66+SETTINGS!$B$2*P66),2) | H66: 12.385684 | I66: -207.41 | J66: 0 | K66: 0 | L66: 56.762822 | M66: 67 | N66: 0.44537815 | O66: 0.06468782 | P66: 0.93531218 | Q66: 0.65308597 | R66: lower | S66: FALSE | U66: no | V66: 28.646721 | W66: standard | X66: ACT | Y66: 00-0036679
A67: 66 | B67: Aidan O'Connell | C67: LV | D67: QB | E67: 10.61 | F67: 53.9 | G67: =ROUND(100*((1-SETTINGS!$B$2)*N67+SETTINGS!$B$2*P67),2) | H67: 14.335096 | I67: -205.46 | J67: 0 | K67: 0 | L67: 58.712234 | M67: 64 | N67: 0.47058824 | O67: 0.18721088 | P67: 0.81278912 | Q67: 0.53056292 | R67: lower | S67: FALSE | U67: no | V67: 28.000574 | W67: standard | X67: ACT | Y67: 00-0038579
A68: 67 | B68: Chris Oladokun | C68: KC | D68: QB | E68: 11.8 | F68: 53.75 | G68: =ROUND(100*((1-SETTINGS!$B$2)*N68+SETTINGS!$B$2*P68),2) | H68: 12.805791 | I68: -206.99 | J68: 0 | K68: 0 | L68: 57.182929 | M68: 66 | N68: 0.45378151 | O68: 0.12766449 | P68: 0.87233551 | Q68: 0.5901093 | R68: lower | S68: FALSE | U68: no | V68: 28.994434 | W68: standard | X68: ACT | Y68: 00-0037324
A69: 68 | B69: Teddy Bridgewater | C69: DET | D69: QB | E69: 11.97 | F69: 52.57 | G69: =ROUND(100*((1-SETTINGS!$B$2)*N69+SETTINGS!$B$2*P69),2) | H69: 11.96351 | I69: -207.83 | J69: 0 | K69: 0 | L69: 56.340648 | M69: 68 | N69: 0.43697479 | O69: 0.11914986 | P69: 0.88085014 | Q69: 0.59862393 | R69: lower | S69: FALSE | U69: no | V69: 33.807674 | W69: standard | X69: ACT | Y69: 00-0031237
... A75: 74 | B75: Will Howard | C75: PIT | D75: QB | E75: 10.1 | F75: 47.34 | G75: =ROUND(100*((1-SETTINGS!$B$2)*N75+SETTINGS!$B$2*P75),2) | H75: 7.1613536 | I75: -212.63 | J75: 0 | K75: 0 | L75: 51.538492 | M75: 73 | N75: 0.39495798 | O75: 0.21282024 | P75: 0.78717976 | Q75: 0.50495355 | R75: moderate | S75: FALSE | U75: no | V75: 24.936857 | W75: standard | X75: ACT | Y75: 00-0040203
A76: 75 | B76: Skylar Thompson | C76: BAL | D76: QB | E76: 11.39 | F76: 45.94 | G76: =ROUND(100*((1-SETTINGS!$B$2)*N76+SETTINGS!$B$2*P76),2) | H76: 5.6163696 | I76: -214.18 | J76: 0 | K76: 0.71573984 | L76: 7.472416 | M76: 77 | N76: 0.36134454 | O76: 0.14841663 | P76: 0.85158337 | Q76: 0.56935717 | R76: lower | S76: TRUE | T76: IR | U76: no | V76: 29.243586 | W76: standard | X76: ACT | Y76: 00-0037327
A77: 76 | B77: Kurtis Rourke | C77: SF | D77: QB | E77: 9.79 | F77: 45.69 | G77: =ROUND(100*((1-SETTINGS!$B$2)*N77+SETTINGS!$B$2*P77),2) | H77: 6.4688972 | I77: -213.32 | J77: 0 | K77: 0 | L77: 50.846035 | M77: 75 | N77: 0.37815126 | O77: 0.22824191 | P77: 0.77175809 | Q77: 0.48953188 | R77: moderate | S77: TRUE | T77: Questionable | U77: no | V77: 25.851318 | W77: standard | X77: ACT | Y77: 00-0040589
A78: 77 | B78: Jarrett Stidham | C78: DEN | D78: QB | E78: 12.43 | F78: 45.64 | G78: =ROUND(100*((1-SETTINGS!$B$2)*N78+SETTINGS!$B$2*P78),2) | H78: 5.1896153 | I78: -214.6 | J78: 0 | K78: 0.28898555 | L78: 7.0456617 | M78: 79 | N78: 0.34453782 | O78: 0.096269852 | P78: 0.90373015 | Q78: 0.62150394 | R78: lower | S78: FALSE | U78: no | V78: 30.064957 | W78: standard | X78: ACT | Y78: 00-0035264
A79: 78 | B79: Kyle McCord | C79: GB | D79: QB | E79: 10.35 | F79: 45.58 | G79: =ROUND(100*((1-SETTINGS!$B$2)*N79+SETTINGS!$B$2*P79),2) | H79: 5.8128312 | I79: -213.98 | J79: 0 | K79: 0.91220145 | L79: 7.6688776 | M79: 76 | N79: 0.3697479 | O79: 0.20008077 | P79: 0.79991923 | Q79: 0.51769303 | R79: moderate | S79: FALSE | U79: no | V79: 23.95121 | W79: standard | X79: ACT | Y79: 00-0040014
A80: 79 | B80: Cam Miller | C80: MIA | D80: QB | E80: 10.45 | F80: 44.33 | G80: =ROUND(100*((1-SETTINGS!$B$2)*N80+SETTINGS!$B$2*P80),2) | H80: 5.2273683 | I80: -214.56 | J80: 0 | K80: 0.32673857 | L80: 7.0834148 | M80: 78 | N80: 0.35294118 | O80: 0.19538829 | P80: 0.80461171 | Q80: 0.5223855 | R80: lower | S80: FALSE | U80: no | V80: 25.205172 | W80: standard | X80: ACT | Y80: 00-0040222
A81: 80 | B81: Kyle Allen | C81: BUF | D81: QB | E81: 13.11 | F81: 44.3 | G81: =ROUND(100*((1-SETTINGS!$B$2)*N81+SETTINGS!$B$2*P81),2) | H81: 4.8245602 | I81: -214.97 | J81: 0 | K81: 0 | L81: 6.6806066 | M81: 82 | N81: 0.31932773 | O81: 0.062092144 | P81: 0.93790786 | Q81: 0.65568165 | R81: lower | S81: FALSE | U81: no | V81: 30.483856 | W81: standard | X81: ACT | Y81: 00-0034577
A82: 81 | B82: Kedon Slovis | C82: AZ | D82: QB | E82: 11.99 | F82: 43.86 | G82: =ROUND(100*((1-SETTINGS!$B$2)*N82+SETTINGS!$B$2*P82),2) | H82: 5.0526439 | I82: -214.74 | J82: 0 | K82: 0.15201415 | L82: 6.9086903 | M82: 81 | N82: 0.32773109 | O82: 0.11809444 | P82: 0.88190556 | Q82: 0.59967936 | R82: lower | S82: FALSE | U82: no | V82: 25.39135 | W82: standard | X82: ACT | Y82: 00-0039577
A83: 82 | B83: Tommy DeVito | C83: NE | D83: QB | E83: 12.82 | F83: 43.34 | G83: =ROUND(100*((1-SETTINGS!$B$2)*N83+SETTINGS!$B$2*P83),2) | H83: 4.4981991 | I83: -215.29 | J83: 0 | K83: 0 | L83: 6.3542455 | M83: 83 | N83: 0.31092437 | O83: 0.076627999 | P83: 0.923372 | Q83: 0.6411458 | R83: lower | S83: FALSE | U83: no | V83: 28.069023 | W83: standard | X83: ACT | Y83: 00-0038476
A84: 83 | B84: Sean Clifford | C84: CIN | D84: QB | E84: 13.43 | F84: 43.27 | G84: =ROUND(100*((1-SETTINGS!$B$2)*N84+SETTINGS!$B$2*P84),2) | H84: 4.4676277 | I84: -215.32 | J84: 0 | K84: 0 | L84: 6.3236742 | M84: 84 | N84: 0.30252101 | O84: 0.046380252 | P84: 0.95361975 | Q84: 0.67139354 | R84: lower | S84: FALSE | U84: no | V84: 28.134733 | W84: standard | X84: ACT | Y84: 00-0038391
A85: 84 | B85: Graham Mertz | C85: HOU | D85: QB | E85: 10.46 | F85: 42.99 | G85: =ROUND(100*((1-SETTINGS!$B$2)*N85+SETTINGS!$B$2*P85),2) | H85: 5.179803 | I85: -214.61 | J85: 0 | K85: 0.2791732 | L85: 7.0358494 | M85: 80 | N85: 0.33613445 | O85: 0.19487254 | P85: 0.80512746 | Q85: 0.52290126 | R85: lower | S85: TRUE | T85: Questionable | U85: no | V85: 25.736326 | W85: standard | X85: ACT | Y85: 00-0040211
A86: 85 | B86: Bailey Zappe | C86: NYJ | D86: QB | E86: 12.69 | F86: 41.87 | G86: =ROUND(100*((1-SETTINGS!$B$2)*N86+SETTINGS!$B$2*P86),2) | H86: 4.4469715 | I86: -215.35 | J86: 0 | K86: 0 | L86: 6.3030179 | M86: 85 | N86: 0.29411765 | O86: 0.083211566 | P86: 0.91678843 | Q86: 0.63456223 | R86: lower | S86: FALSE | U86: no | V86: 27.35169 | W86: standard | X86: ACT | Y86: 00-0038108
A87: 86 | B87: Will Grier | C87: CAR | D87: QB | E87: 13.03 | F87: 41.54 | G87: =ROUND(100*((1-SETTINGS!$B$2)*N87+SETTINGS!$B$2*P87),2) | H87: 4.401849 | I87: -215.39 | J87: 0 | K87: 0 | L87: 6.2578955 | M87: 86 | N87: 0.28571429 | O87: 0.066069278 | P87: 0.93393072 | Q87: 0.65170452 | R87: lower | S87: FALSE | U87: no | V87: 31.414745 | W87: standard | X87: ACT | Y87: 00-0035251
A88: 87 | B88: Stetson Bennett | C88: LA | D88: QB | E88: 12.82 | F88: 40.65 | G88: =ROUND(100*((1-SETTINGS!$B$2)*N88+SETTINGS!$B$2*P88),2) | H88: 4.3742323 | I88: -215.42 | J88: 0 | K88: 0 | L88: 6.2302788 | M88: 87 | N88: 0.27731092 | O88: 0.076643799 | P88: 0.9233562 | Q88: 0.64112999 | R88: lower | S88: FALSE | U88: no | V88: 28.843851 | W88: standard | X88: ACT | Y88: 00-0039107
A89: 88 | B89: Hendon Hooker | C89: TEN | D89: QB | E89: 13.12 | F89: 40.28 | G89: =ROUND(100*((1-SETTINGS!$B$2)*N89+SETTINGS!$B$2*P89),2) | H89: 4.3649468 | I89: -215.43 | J89: 0 | K89: 0 | L89: 6.2209933 | M89: 88 | N89: 0.26890756 | O89: 0.061656395 | P89: 0.93834361 | Q89: 0.6561174 | R89: lower | S89: FALSE | U89: no | V89: 28.633032 | W89: standard | X89: ACT | Y89: 00-0038550
A90: 89 | B90: Easton Stick | C90: IND | D90: QB | E90: 13.13 | F90: 38.94 | G90: =ROUND(100*((1-SETTINGS!$B$2)*N90+SETTINGS!$B$2*P90),2) | H90: 4.2722964 | I90: -215.52 | J90: 0 | K90: 0 | L90: 6.1283429 | M90: 90 | N90: 0.25210084 | O90: 0.061449144 | P90: 0.93855086 | Q90: 0.65632465 | R90: lower | S90: FALSE | U90: no | V90: 30.979418 | W90: standard | X90: ACT | Y90: 00-0035282
A91: 90 | B91: Sam Ehlinger | C91: DEN | D91: QB | E91: 12.38 | F91: 38.86 | G91: =ROUND(100*((1-SETTINGS!$B$2)*N91+SETTINGS!$B$2*P91),2) | H91: 4.345275 | I91: -215.45 | J91: 0 | K91: 0 | L91: 6.2013214 | M91: 89 | N91: 0.2605042 | O91: 0.098964556 | P91: 0.90103544 | Q91: 0.61880924 | R91: lower | S91: FALSE | U91: no | V91: 27.921175 | W91: standard | X91: ACT | Y91: 00-0036879
A92: 91 | B92: Trevor Siemian | C92: ATL | D92: QB | E92: 12.88 | F92: 38.02 | G92: =ROUND(100*((1-SETTINGS!$B$2)*N92+SETTINGS!$B$2*P92),2) | H92: 4.1135749 | I92: -215.68 | J92: 0 | K92: 0 | L92: 5.9696213 | M92: 91 | N92: 0.24369748 | O92: 0.073602352 | P92: 0.92639765 | Q92: 0.64417144 | R92: lower | S92: FALSE | U92: no | V92: 34.683807 | W92: standard | X92: ACT | Y92: 00-0032156
A93: 92 | B93: Adrian Martinez | C93: SF | D93: QB | E93: 12.45 | F93: 36.92 | G93: =ROUND(100*((1-SETTINGS!$B$2)*N93+SETTINGS!$B$2*P93),2) | H93: 3.4947417 | I93: -216.3 | J93: 0 | K93: 0 | L93: 5.3507882 | M93: 92 | N93: 0.23529412 | O93: 0.095283425 | P93: 0.90471658 | Q93: 0.62249037 | R93: lower | S93: FALSE | U93: no | V93: 26.650787 | W93: standard | X93: ACT | Y93: 00-0038658
A94: 93 | B94: Case Keenum | C94: CHI | D94: QB | E94: 13.44 | F94: 35.22 | G94: =ROUND(100*((1-SETTINGS!$B$2)*N94+SETTINGS!$B$2*P94),2) | H94: 2.4583779 | I94: -217.33 | J94: 0 | K94: 0 | L94: 4.3144243 | M94: 96 | N94: 0.20168067 | O94: 0.045819046 | P94: 0.95418095 | Q94: 0.67195475 | R94: lower | S94: FALSE | U94: no | V94: 38.53878 | W94: standard | X94: ACT | Y94: 00-0028986
A95: 94 | B95: Taylen Green | C95: CLE | D95: QB | E95: 10.84 | F95: 34.64 | G95: =ROUND(100*((1-SETTINGS!$B$2)*N95+SETTINGS!$B$2*P95),2) | H95: 3.2232475 | I95: -216.57 | J95: 0 | K95: 0 | L95: 5.079294 | M95: 93 | N95: 0.22689076 | O95: 0.17580595 | P95: 0.82419405 | Q95: 0.54196784 | R95: lower | S95: FALSE | U95: yes | V95: 23.871811 | W95: standard | X95: ACT | Y95: 00-0041092
A96: 95 | B96: Joe Fagnano | C96: BAL | D96: QB | E96: 11.44 | F96: 34.56 | G96: =ROUND(100*((1-SETTINGS!$B$2)*N96+SETTINGS!$B$2*P96),2) | H96: 2.7553766 | I96: -217.04 | J96: 0 | K96: 0 | L96: 4.611423 | M96: 94 | N96: 0.21848739 | O96: 0.14573175 | P96: 0.85426825 | Q96: 0.57204204 | R96: lower | S96: FALSE | U96: yes | V96: 25.421467 | W96: standard | X96: ACT | Y96: 00-0040981
A97: 96 | B97: Sam Hartman | C97: WAS | D97: QB | E97: 13.15 | F97: 34.26 | G97: =ROUND(100*((1-SETTINGS!$B$2)*N97+SETTINGS!$B$2*P97),2) | H97: 2.1491242 | I97: -217.64 | J97: 0 | K97: 0 | L97: 4.0051707 | M97: 97 | N97: 0.19327731 | O97: 0.060248321 | P97: 0.93975168 | Q97: 0.65752547 | R97: lower | S97: FALSE | U97: no | V97: 27.094328 | W97: standard | X97: ACT | Y97: 00-0039677
... A108: 107 | B108: Cade Klubnik | C108: NYJ | D108: QB | E108: 11.1 | F108: 25.49 | G108: =ROUND(100*((1-SETTINGS!$B$2)*N108+SETTINGS!$B$2*P108),2) | H108: 1.7807044 | I108: -218.01 | J108: 0 | K108: 0 | L108: 3.6367509 | M108: 107 | N108: 0.1092437 | O108: 0.16255166 | P108: 0.83744834 | Q108: 0.55522213 | R108: lower | S108: FALSE | U108: yes | V108: 22.894379 | W108: standard | X108: ACT | Y108: 00-0041056
A109: 108 | B109: Haynes King | C109: CAR | D109: QB | E109: 11.23 | F109: 24.94 | G109: =ROUND(100*((1-SETTINGS!$B$2)*N109+SETTINGS!$B$2*P109),2) | H109: 1.7737158 | I109: -218.02 | J109: 0 | K109: 0 | L109: 3.6297622 | M109: 108 | N109: 0.10084034 | O109: 0.15612232 | P109: 0.84387768 | Q109: 0.56165148 | R109: lower | S109: TRUE | T109: Questionable | U109: yes | V109: 25.643236 | W109: standard | X109: ACT | Y109: 00-0041149
A110: 109 | B110: Joey Aguilar | C110: JAX | D110: QB | E110: 11.19 | F110: 24.23 | G110: =ROUND(100*((1-SETTINGS!$B$2)*N110+SETTINGS!$B$2*P110),2) | H110: 1.7697389 | I110: -218.02 | J110: 0 | K110: 0 | L110: 3.6257853 | M110: 109 | N110: 0.092436975 | O110: 0.15835328 | P110: 0.84164672 | Q110: 0.55942051 | R110: lower | S110: FALSE | U110: yes | V110: 25.210648 | W110: standard | X110: ACT | Y110: 00-0041203
A111: 110 | B111: Kyron Drones | C111: GB | D111: QB | E111: 11.12 | F111: 23.49 | G111: =ROUND(100*((1-SETTINGS!$B$2)*N111+SETTINGS!$B$2*P111),2) | H111: 1.7154946 | I111: -218.08 | J111: 0 | K111: 0 | L111: 3.571541 | M111: 110 | N111: 0.084033613 | O111: 0.16186337 | P111: 0.83813663 | Q111: 0.55591042 | R111: lower | S111: FALSE | U111: yes | V111: 23.107935 | W111: standard | X111: ACT | Y111: 00-0040942
A112: 111 | B112: Athan Kaliakmanis | C112: WAS | D112: QB | E112: 11.12 | F112: 22.81 | G112: =ROUND(100*((1-SETTINGS!$B$2)*N112+SETTINGS!$B$2*P112),2) | H112: 1.6594883 | I112: -218.13 | J112: 0 | K112: 0 | L112: 3.5155347 | M112: 111 | N112: 0.075630252 | O112: 0.16197066 | P112: 0.83802934 | Q112: 0.55580314 | R112: lower | S112: FALSE | U112: yes | V112: 23.034012 | W112: standard | X112: ACT | Y112: 00-0041117
A113: 112 | B113: Cole Payton | C113: PHI | D113: QB | E113: 11.18 | F113: 22.2 | G113: =ROUND(100*((1-SETTINGS!$B$2)*N113+SETTINGS!$B$2*P113),2) | H113: 1.6591896 | I113: -218.13 | J113: 0 | K113: 0 | L113: 3.5152361 | M113: 112 | N113: 0.067226891 | O113: 0.15892673 | P113: 0.84107327 | Q113: 0.55884706 | R113: lower | S113: FALSE | U113: yes | V113: 23.849909 | W113: standard | X113: ACT | Y113: 00-0040891
A114: 113 | B114: Matthew Caldwell | C114: LA | D114: QB | E114: 11.13 | F114: 21.48 | G114: =ROUND(100*((1-SETTINGS!$B$2)*N114+SETTINGS!$B$2*P114),2) | H114: 1.6565796 | I114: -218.14 | J114: 0 | K114: 0 | L114: 3.512626 | M114: 113 | N114: 0.058823529 | O114: 0.16137035 | P114: 0.83862965 | Q114: 0.55640345 | R114: lower | S114: FALSE | U114: yes | V114: 23.277685 | W114: standard | X114: ACT | Y114: 00-0041414
A115: 114 | B115: Diego Pavia | C115: BAL | D115: QB | E115: 14.36 | F115: 21.01 | G115: =ROUND(100*((1-SETTINGS!$B$2)*N115+SETTINGS!$B$2*P115),2) | H115: 0.046117284 | I115: -219.75 | J115: 0 | K115: 0 | L115: 1.9021637 | M115: 118 | N115: 0.012605042 | O115: 2.5485981e-08 | P115: 0.99999997 | Q115: 0.71777377 | R115: lower | S115: FALSE | U115: no | W115: standard | X115: ACT | Y115: 00-0040985
A116: 115 | B116: Mark Gronowski | C116: MIA | D116: QB | E116: 14.36 | F116: 21.01 | G116: =ROUND(100*((1-SETTINGS!$B$2)*N116+SETTINGS!$B$2*P116),2) | H116: 0.046117284 | I116: -219.75 | J116: 0 | K116: 0 | L116: 1.9021637 | M116: 118 | N116: 0.012605042 | O116: 2.5485981e-08 | P116: 0.99999997 | Q116: 0.71777377 | R116: lower | S116: FALSE | U116: no | W116: standard | X116: ACT | Y116: 00-0041156
A117: 116 | B117: Carson Beck | C117: AZ | D117: QB | E117: 11.19 | F117: 20.87 | G117: =ROUND(100*((1-SETTINGS!$B$2)*N117+SETTINGS!$B$2*P117),2) | H117: 1.6482733 | I117: -218.14 | J117: 0 | K117: 0 | L117: 3.5043198 | M117: 114 | N117: 0.050420168 | O117: 0.15831335 | P117: 0.84168665 | Q117: 0.55946044 | R117: lower | S117: TRUE | T117: Questionable | U117: yes | V117: 24.783535 | W117: standard | X117: RES | Y117: 00-0041561
A118: 117 | B118: Jalon Daniels | C118: TB | D118: QB | E118: 11.32 | F118: 20.32 | G118: =ROUND(100*((1-SETTINGS!$B$2)*N118+SETTINGS!$B$2*P118),2) | H118: 1.6159632 | I118: -218.18 | J118: 0 | K118: 0 | L118: 3.4720096 | M118: 115 | N118: 0.042016807 | O118: 0.15188495 | P118: 0.84811505 | Q118: 0.56588884 | R118: lower | S118: FALSE | U118: yes | V118: 23.841694 | W118: standard | X118: ACT | Y118: 00-0041251
A119: 118 | B119: Jacob Clark | C119: LV | D119: QB | E119: 11.23 | F119: 19.57 | G119: =ROUND(100*((1-SETTINGS!$B$2)*N119+SETTINGS!$B$2*P119),2) | H119: 1.5471181 | I119: -218.24 | J119: 0 | K119: 0 | L119: 3.4031645 | M119: 116 | N119: 0.033613445 | O119: 0.15604767 | P119: 0.84395233 | Q119: 0.56172613 | R119: lower | S119: FALSE | U119: yes | V119: 25.832153 | W119: standard | X119: ACT | Y119: 00-0040996
A120: 119 | B120: Fernando Mendoza | C120: LV | D120: QB | E120: 11.12 | F120: 18.78 | G120: =ROUND(100*((1-SETTINGS!$B$2)*N120+SETTINGS!$B$2*P120),2) | H120: 1.506502 | I120: -218.29 | J120: 0 | K120: 0 | L120: 3.3625484 | M120: 117 | N120: 0.025210084 | O120: 0.16182279 | P120: 0.83817721 | Q120: 0.555951 | R120: lower | S120: FALSE | U120: yes | V120: 22.91902 | W120: standard | X120: RES | Y120: 00-0041562

Sheet RB
A1: Rank | B1: Player | C1: Team | D1: Pos | E1: Overall Draft Score (replacement-adjusted) | F1: Position Draft Score (default weight) | G1: Custom-Weight Score (weight from SETTINGS) | H1: Projected 2026 Points | I1: Points Over Replacement | J1: Overall Value (points over replacement / max) | K1: Points P10 | L1: Points P90 | M1: Pos Points Rank | N1: Pos Points Percentile | O1: Missed-Time Injury Probability | P1: Healthy Probability | Q1: Healthy Probability vs Position Mean (+0.5) | R1: Injury Risk Band | S1: Current Injury Listing (screen date) | T1: Current Listing Status | U1: Rookie | V1: Age | W1: Points Model Confidence | X1: Roster Status (Aug 9) | Y1: Player ID
A2: 1 | B2: Derrick Henry | C2: BAL | D2: RB | E2: 52.62 | F2: 89.34 | G2: =ROUND(100*((1-SETTINGS!$B$2)*N2+SETTINGS!$B$2*P2),2) | H2: 230.26795 | I2: 73.27 | J2: 0.5758 | K2: 161.10837 | L2: 345.23584 | M2: 4 | N2: 0.98571429 | O2: 0.47582579 | P2: 0.52417421 | Q2: 0.32761055 | R2: higher | S2: FALSE | U2: no | V2: 32.657753 | W2: standard | X2: ACT | Y2: 00-0032764
A3: 2 | B3: Bijan Robinson | C3: ATL | D3: RB | E3: 72.02 | F3: 88.24 | G3: =ROUND(100*((1-SETTINGS!$B$2)*N3+SETTINGS!$B$2*P3),2) | H3: 264.68583 | I3: 107.69 | J3: 0.8463 | K3: 195.52625 | L3: 379.65372 | M3: 1 | N3: 1 | O3: 0.58776347 | P3: 0.41223653 | Q3: 0.21567287 | R3: higher | S3: FALSE | U3: no | V3: 24.586405 | W3: standard | X3: ACT | Y3: 00-0038542
A4: 3 | B4: Jahmyr Gibbs | C4: DET | D4: RB | E4: 56.76 | F4: 87.83 | G4: =ROUND(100*((1-SETTINGS!$B$2)*N4+SETTINGS!$B$2*P4),2) | H4: 240.4644 | I4: 83.47 | J4: 0.656 | K4: 171.30482 | L4: 355.4323 | M4: 2 | N4: 0.9952381 | O4: 0.5893529 | P4: 0.4106471 | Q4: 0.21408344 | R4: higher | S4: TRUE | T4: Questionable | U4: no | V4: 24.452248 | W4: standard | X4: ACT | Y4: 00-0039139
A5: 4 | B5: Kyren Williams | C5: LA | D5: RB | E5: 31.7 | F5: 87.72 | G5: =ROUND(100*((1-SETTINGS!$B$2)*N5+SETTINGS!$B$2*P5),2) | H5: 197.75366 | I5: 40.76 | J5: 0.3203 | K5: 128.59408 | L5: 312.72156 | M5: 7 | N5: 0.97142857 | O5: 0.49950467 | P5: 0.50049533 | Q5: 0.30393166 | R5: higher | S5: FALSE | U5: no | V5: 26.015593 | W5: standard | X5: ACT | Y5: 00-0037840
A6: 5 | B6: Ashton Jeanty | C6: LV | D6: RB | E6: 46.99 | F6: 87.67 | G6: =ROUND(100*((1-SETTINGS!$B$2)*N6+SETTINGS!$B$2*P6),2) | H6: 223.37205 | I6: 66.38 | J6: 0.5217 | K6: 154.21247 | L6: 338.33995 | M6: 5 | N6: 0.98095238 | O6: 0.54054458 | P6: 0.45945542 | Q6: 0.26289176 | R6: higher | S6: FALSE | U6: no | V6: 22.749269 | W6: standard | X6: ACT | Y6: 00-0040122
A7: 6 | B7: De'Von Achane | C7: MIA | D7: RB | E7: 51.29 | F7: 87.47 | G7: =ROUND(100*((1-SETTINGS!$B$2)*N7+SETTINGS!$B$2*P7),2) | H7: 231.74679 | I7: 74.75 | J7: 0.5874 | K7: 162.58721 | L7: 346.71469 | M7: 3 | N7: 0.99047619 | O7: 0.58838759 | P7: 0.41161241 | Q7: 0.21504875 | R7: higher | S7: FALSE | U7: no | V7: 24.884836 | W7: standard | X7: ACT | Y7: 00-0039040
A8: 7 | B8: Chase Brown | C8: CIN | D8: RB | E8: 41.07 | F8: 87.19 | G8: =ROUND(100*((1-SETTINGS!$B$2)*N8+SETTINGS!$B$2*P8),2) | H8: 214.10578 | I8: 57.11 | J8: 0.4488 | K8: 144.9462 | L8: 329.07368 | M8: 6 | N8: 0.97619048 | O8: 0.54521446 | P8: 0.45478554 | Q8: 0.25822187 | R8: higher | S8: FALSE | U8: no | V8: 26.448181 | W8: standard | X8: ACT | Y8: 00-0038597
A9: 8 | B9: D'Andre Swift | C9: CHI | D9: RB | E9: 27.07 | F9: 86.1 | G9: =ROUND(100*((1-SETTINGS!$B$2)*N9+SETTINGS!$B$2*P9),2) | H9: 191.17046 | I9: 34.17 | J9: 0.2685 | K9: 122.01088 | L9: 306.13835 | M9: 10 | N9: 0.95714286 | O9: 0.52381258 | P9: 0.47618742 | Q9: 0.27962376 | R9: higher | S9: FALSE | U9: no | V9: 27.630957 | W9: standard | X9: ACT | Y9: 00-0036275
A10: 9 | B10: James Cook | C10: BUF | D10: RB | E10: 29.63 | F10: 85.62 | G10: =ROUND(100*((1-SETTINGS!$B$2)*N10+SETTINGS!$B$2*P10),2) | H10: 196.59144 | I10: 39.6 | J10: 0.3112 | K10: 127.43186 | L10: 311.55934 | M10: 9 | N10: 0.96190476 | O10: 0.566826 | P10: 0.433174 | Q10: 0.23661034 | R10: higher | S10: FALSE | U10: no | V10: 26.93553 | W10: standard | X10: ACT | Y10: 00-0037248
A11: 10 | B11: Breece Hall | C11: NYJ | D11: RB | E11: 29.06 | F11: 85.41 | G11: =ROUND(100*((1-SETTINGS!$B$2)*N11+SETTINGS!$B$2*P11),2) | H11: 196.62306 | I11: 39.63 | J11: 0.3114 | K11: 127.46348 | L11: 311.59095 | M11: 8 | N11: 0.96666667 | O11: 0.59615961 | P11: 0.40384039 | Q11: 0.20727672 | R11: higher | S11: FALSE | U11: no | V11: 25.254454 | W11: standard | X11: ACT | Y11: 00-0038120
A12: 11 | B12: TreVeyon Henderson | C12: NE | D12: RB | E12: 17.63 | F12: 84.94 | G12: =ROUND(100*((1-SETTINGS!$B$2)*N12+SETTINGS!$B$2*P12),2) | H12: 176.16169 | I12: 19.17 | J12: 0.1506 | K12: 107.00211 | L12: 291.12959 | M12: 13 | N12: 0.94285714 | O12: 0.52434617 | P12: 0.47565383 | Q12: 0.27909017 | R12: higher | S12: FALSE | U12: no | V12: 23.860859 | W12: standard | X12: ACT | Y12: 00-0040734
A13: 12 | B13: Christian McCaffrey | C13: SF | D13: RB | E13: 23.61 | F13: 84.47 | G13: =ROUND(100*((1-SETTINGS!$B$2)*N13+SETTINGS!$B$2*P13),2) | H13: 187.63536 | I13: 30.64 | J13: 0.2408 | K13: 118.47578 | L13: 302.60325 | M13: 11 | N13: 0.95238095 | O13: 0.58589425 | P13: 0.41410575 | Q13: 0.21754209 | R13: higher | S13: TRUE | T13: Questionable | U13: no | V13: 30.234707 | W13: standard | X13: ACT | Y13: 00-0033280
A14: 13 | B14: Saquon Barkley | C14: PHI | D14: RB | E14: 17.06 | F14: 84.3 | G14: =ROUND(100*((1-SETTINGS!$B$2)*N14+SETTINGS!$B$2*P14),2) | H14: 176.87906 | I14: 19.88 | J14: 0.1562 | K14: 107.71948 | L14: 291.84696 | M14: 12 | N14: 0.94761905 | O14: 0.57533157 | P14: 0.42466843 | Q14: 0.22810477 | R14: higher | S14: FALSE | U14: no | V14: 29.558445 | W14: standard | X14: ACT | Y14: 00-0034844
A15: 14 | B15: RJ Harvey | C15: DEN | D15: RB | E15: 14.83 | F15: 84.1 | G15: =ROUND(100*((1-SETTINGS!$B$2)*N15+SETTINGS!$B$2*P15),2) | H15: 171.83337 | I15: 14.84 | J15: 0.1166 | K15: 102.67379 | L15: 286.80127 | M15: 15 | N15: 0.93333333 | O15: 0.52813255 | P15: 0.47186745 | Q15: 0.27530379 | R15: higher | S15: FALSE | U15: no | V15: 25.572052 | W15: standard | X15: ACT | Y15: 00-0040730
A16: 15 | B16: Kenneth Walker III | C16: KC | D16: RB | E16: 15.81 | F16: 83.45 | G16: =ROUND(100*((1-SETTINGS!$B$2)*N16+SETTINGS!$B$2*P16),2) | H16: 175.02581 | I16: 18.03 | J16: 0.1417 | K16: 105.86623 | L16: 289.99371 | M16: 14 | N16: 0.93809524 | O16: 0.57975096 | P16: 0.42024904 | Q16: 0.22368538 | R16: higher | S16: FALSE | U16: no | V16: 25.865007 | W16: standard | X16: ACT | Y16: 00-0038134
A17: 16 | B17: Jaylen Warren | C17: PIT | D17: RB | E17: 13.92 | F17: 83.43 | G17: =ROUND(100*((1-SETTINGS!$B$2)*N17+SETTINGS!$B$2*P17),2) | H17: 170.84951 | I17: 13.85 | J17: 0.1088 | K17: 101.68993 | L17: 285.81741 | M17: 16 | N17: 0.92857143 | O17: 0.54264202 | P17: 0.45735798 | Q17: 0.26079432 | R17: higher | S17: FALSE | U17: no | V17: 27.833563 | W17: standard | X17: ACT | Y17: 00-0037228
A18: 17 | B18: Tony Pollard | C18: TEN | D18: RB | E18: 13.89 | F18: 83.22 | G18: =ROUND(100*((1-SETTINGS!$B$2)*N18+SETTINGS!$B$2*P18),2) | H18: 170.52083 | I18: 13.53 | J18: 0.1063 | K18: 101.36125 | L18: 285.48873 | M18: 17 | N18: 0.92380952 | O18: 0.53399148 | P18: 0.46600852 | Q18: 0.26944486 | R18: higher | S18: FALSE | U18: no | V18: 29.339411 | W18: standard | X18: ACT | Y18: 00-0035261
A19: 18 | B19: Tyrone Tracy Jr. | C19: NYG | D19: RB | E19: 8.86 | F19: 82.28 | G19: =ROUND(100*((1-SETTINGS!$B$2)*N19+SETTINGS!$B$2*P19),2) | H19: 162.20419 | I19: 5.21 | J19: 0.0409 | K19: 93.044604 | L19: 277.17208 | M19: 20 | N19: 0.90952381 | O19: 0.5238792 | P19: 0.4761208 | Q19: 0.27955714 | R19: higher | S19: FALSE | U19: no | V19: 26.773993 | W19: standard | X19: ACT | Y19: 00-0039384
A20: 19 | B20: Travis Etienne | C20: NO | D20: RB | E20: 11.97 | F20: 81.76 | G20: =ROUND(100*((1-SETTINGS!$B$2)*N20+SETTINGS!$B$2*P20),2) | H20: 169.18909 | I20: 12.19 | J20: 0.0958 | K20: 100.02951 | L20: 284.15699 | M20: 18 | N20: 0.91904762 | O20: 0.58812969 | P20: 0.41187031 | Q20: 0.21530665 | R20: higher | S20: FALSE | U20: no | V20: 27.598103 | W20: standard | X20: ACT | Y20: 00-0036973
A21: 20 | B21: Josh Jacobs | C21: GB | D21: RB | E21: 7.38 | F21: 81.65 | G21: =ROUND(100*((1-SETTINGS!$B$2)*N21+SETTINGS!$B$2*P21),2) | H21: 160.24005 | I21: 3.24 | J21: 0.0255 | K21: 91.080464 | L21: 275.20794 | M21: 21 | N21: 0.9047619 | O21: 0.53634448 | P21: 0.46365552 | Q21: 0.26709185 | R21: higher | S21: TRUE | T21: Questionable | U21: no | V21: 28.553633 | W21: standard | X21: ACT | Y21: 00-0035700
A22: 21 | B22: Bucky Irving | C22: TB | D22: RB | E22: 5.78 | F22: 81.09 | G22: =ROUND(100*((1-SETTINGS!$B$2)*N22+SETTINGS!$B$2*P22),2) | H22: 157.39499 | I22: 0.4 | J22: 0.0031 | K22: 88.235409 | L22: 272.36289 | M22: 23 | N22: 0.8952381 | O22: 0.52666092 | P22: 0.47333908 | Q22: 0.27677541 | R22: higher | S22: FALSE | U22: no | V22: 24.036085 | W22: standard | X22: ACT | Y22: 00-0039361
A23: 22 | B23: Jonathan Taylor | C23: IND | D23: RB | E23: 7.79 | F23: 81.04 | G23: =ROUND(100*((1-SETTINGS!$B$2)*N23+SETTINGS!$B$2*P23),2) | H23: 163.09199 | I23: 6.1 | J23: 0.0479 | K23: 93.932413 | L23: 278.05989 | M23: 19 | N23: 0.91428571 | O23: 0.60536284 | P23: 0.39463716 | Q23: 0.19807349 | R23: higher | S23: FALSE | U23: no | V23: 27.617268 | W23: standard | X23: ACT | Y23: 00-0036223
A24: 23 | B24: Rico Dowdle | C24: PIT | D24: RB | E24: 6.46 | F24: 80.7 | G24: =ROUND(100*((1-SETTINGS!$B$2)*N24+SETTINGS!$B$2*P24),2) | H24: 159.68369 | I24: 2.69 | J24: 0.0211 | K24: 90.52411 | L24: 274.65159 | M24: 22 | N24: 0.9 | O24: 0.56484874 | P24: 0.43515126 | Q24: 0.2385876 | R24: higher | S24: FALSE | U24: no | V24: 28.216869 | W24: standard | X24: ACT | Y24: 00-0036139
A25: 24 | B25: Woody Marks | C25: HOU | D25: RB | E25: 5.33 | F25: 80.12 | G25: =ROUND(100*((1-SETTINGS!$B$2)*N25+SETTINGS!$B$2*P25),2) | H25: 155.04385 | I25: -1.95 | J25: 0 | K25: 85.884265 | L25: 270.01174 | M25: 25 | N25: 0.88571429 | O25: 0.53674186 | P25: 0.46325814 | Q25: 0.26669448 | R25: higher | S25: FALSE | U25: no | V25: 25.673353 | W25: standard | X25: ACT | Y25: 00-0040583
A26: 25 | B26: Rachaad White | C26: WAS | D26: RB | E26: 7.23 | F26: 80.12 | G26: =ROUND(100*((1-SETTINGS!$B$2)*N26+SETTINGS!$B$2*P26),2) | H26: 126.17494 | I26: -30.82 | J26: 0 | K26: 57.01536 | L26: 241.14284 | M26: 30 | N26: 0.86190476 | O26: 0.44185351 | P26: 0.55814649 | Q26: 0.36158283 | R26: higher | S26: FALSE | U26: no | V26: 27.636433 | W26: standard | X26: ACT | Y26: 00-0037256
A27: 26 | B27: Kyle Monangai | C27: CHI | D27: RB | E27: 5.61 | F27: 79.64 | G27: =ROUND(100*((1-SETTINGS!$B$2)*N27+SETTINGS!$B$2*P27),2) | H27: 144.85013 | I27: -12.15 | J27: 0 | K27: 75.690551 | L27: 259.81803 | M27: 27 | N27: 0.87619048 | O27: 0.52278899 | P27: 0.47721101 | Q27: 0.28064735 | R27: higher | S27: FALSE | U27: no | V27: 24.238691 | W27: standard | X27: ACT | Y27: 00-0040236
A28: 27 | B28: Zach Charbonnet | C28: SEA | D28: RB | E28: 7.3 | F28: 79.42 | G28: =ROUND(100*((1-SETTINGS!$B$2)*N28+SETTINGS!$B$2*P28),2) | H28: 119.81819 | I28: -37.18 | J28: 0 | K28: 50.658613 | L28: 234.78609 | M28: 32 | N28: 0.85238095 | O28: 0.43839235 | P28: 0.56160765 | Q28: 0.36504399 | R28: higher | S28: TRUE | T28: Out | U28: no | V28: 25.645975 | W28: standard | X28: ACT | Y28: 00-0039165
A29: 28 | B29: Javonte Williams | C29: DAL | D29: RB | E29: 4.23 | F29: 79.4 | G29: =ROUND(100*((1-SETTINGS!$B$2)*N29+SETTINGS!$B$2*P29),2) | H29: 156.99572 | I29: 0 | J29: 0 | K29: 87.836136 | L29: 271.96361 | M29: 24 | N29: 0.89047619 | O29: 0.59214692 | P29: 0.40785308 | Q29: 0.21128941 | R29: higher | S29: FALSE | U29: no | V29: 26.352354 | W29: standard | X29: ACT | Y29: 00-0036997
A30: 29 | B30: Kenneth Gainwell | C30: TB | D30: RB | E30: 5.75 | F30: 79.4 | G30: =ROUND(100*((1-SETTINGS!$B$2)*N30+SETTINGS!$B$2*P30),2) | H30: 141.92959 | I30: -15.07 | J30: 0 | K30: 72.770004 | L30: 256.89748 | M30: 28 | N30: 0.87142857 | O30: 0.5159132 | P30: 0.4840868 | Q30: 0.28752314 | R30: higher | S30: FALSE | U30: no | V30: 27.469421 | W30: standard | X30: ACT | Y30: 00-0036919
A31: 30 | B31: Quinshon Judkins | C31: CLE | D31: RB | E31: 4.33 | F31: 78.74 | G31: =ROUND(100*((1-SETTINGS!$B$2)*N31+SETTINGS!$B$2*P31),2) | H31: 144.96214 | I31: -12.03 | J31: 0 | K31: 75.802555 | L31: 259.93003 | M31: 26 | N31: 0.88095238 | O31: 0.58678229 | P31: 0.41321771 | Q31: 0.21665405 | R31: higher | S31: FALSE | U31: no | V31: 22.842358 | W31: standard | X31: ACT | Y31: 00-0040784
A32: 31 | B32: Blake Corum | C32: LA | D32: RB | E32: 7.03 | F32: 78.39 | G32: =ROUND(100*((1-SETTINGS!$B$2)*N32+SETTINGS!$B$2*P32),2) | H32: 118.67241 | I32: -38.32 | J32: 0 | K32: 49.512824 | L32: 233.6403 | M32: 34 | N32: 0.84285714 | O32: 0.45178913 | P32: 0.54821087 | Q32: 0.35164721 | R32: higher | S32: FALSE | U32: no | V32: 25.766443 | W32: standard | X32: ACT | Y32: 00-0039738
A33: 32 | B33: Rhamondre Stevenson | C33: NE | D33: RB | E33: 5.04 | F33: 78.31 | G33: =ROUND(100*((1-SETTINGS!$B$2)*N33+SETTINGS!$B$2*P33),2) | H33: 128.98762 | I33: -28.01 | J33: 0 | K33: 59.828037 | L33: 243.95551 | M33: 29 | N33: 0.86666667 | O33: 0.55140531 | P33: 0.44859469 | Q33: 0.25203103 | R33: higher | S33: FALSE | U33: no | V33: 28.520777 | W33: standard | X33: ACT | Y33: 00-0036875
A34: 33 | B34: Jacory Croskey-Merritt | C34: WAS | D34: RB | E34: 6.53 | F34: 78.27 | G34: =ROUND(100*((1-SETTINGS!$B$2)*N34+SETTINGS!$B$2*P34),2) | H34: 118.84074 | I34: -38.15 | J34: 0 | K34: 49.681157 | L34: 233.80863 | M34: 33 | N34: 0.84761905 | O34: 0.4769794 | P34: 0.5230206 | Q34: 0.32645694 | R34: higher | S34: FALSE | U34: no | V34: 25.388611 | W34: standard | X34: ACT | Y34: 00-0040242
A35: 34 | B35: Omarion Hampton | C35: LAC | D35: RB | E35: 4.81 | F35: 77.31 | G35: =ROUND(100*((1-SETTINGS!$B$2)*N35+SETTINGS!$B$2*P35),2) | H35: 123.61245 | I35: -33.38 | J35: 0 | K35: 54.452864 | L35: 238.58034 | M35: 31 | N35: 0.85714286 | O35: 0.56291143 | P35: 0.43708857 | Q35: 0.24052491 | R35: higher | S35: FALSE | U35: no | V35: 23.463863 | W35: standard | X35: ACT | Y35: 00-0040666
A36: 35 | B36: Aaron Jones | C36: MIN | D36: RB | E36: 6.58 | F36: 77.18 | G36: =ROUND(100*((1-SETTINGS!$B$2)*N36+SETTINGS!$B$2*P36),2) | H36: 111.17895 | I36: -45.82 | J36: 0 | K36: 42.019372 | L36: 226.14685 | M36: 36 | N36: 0.83333333 | O36: 0.47455212 | P36: 0.52544788 | Q36: 0.32888422 | R36: higher | S36: FALSE | U36: no | V36: 31.74877 | W36: standard | X36: ACT | Y36: 00-0033293
A37: 36 | B37: Tyjae Spears | C37: TEN | D37: RB | E37: 6.61 | F37: 76.83 | G37: =ROUND(100*((1-SETTINGS!$B$2)*N37+SETTINGS!$B$2*P37),2) | H37: 110.98337 | I37: -46.01 | J37: 0 | K37: 41.823791 | L37: 225.95127 | M37: 37 | N37: 0.82857143 | O37: 0.47285341 | P37: 0.52714659 | Q37: 0.33058293 | R37: higher | S37: FALSE | U37: no | V37: 25.213387 | W37: standard | X37: ACT | Y37: 00-0039032
A38: 37 | B38: David Montgomery | C38: HOU | D38: RB | E38: 5.83 | F38: 76.81 | G38: =ROUND(100*((1-SETTINGS!$B$2)*N38+SETTINGS!$B$2*P38),2) | H38: 114.74878 | I38: -42.25 | J38: 0 | K38: 45.589197 | L38: 229.71667 | M38: 35 | N38: 0.83809524 | O38: 0.5118877 | P38: 0.4881123 | Q38: 0.29154864 | R38: higher | S38: FALSE | U38: no | V38: 29.235371 | W38: standard | X38: ACT | Y38: 00-0035685
A39: 38 | B39: Alvin Kamara | C39: NO | D39: RB | E39: 7.69 | F39: 76.76 | G39: =ROUND(100*((1-SETTINGS!$B$2)*N39+SETTINGS!$B$2*P39),2) | H39: 100.32774 | I39: -56.67 | J39: 0 | K39: 31.168158 | L39: 215.29564 | M39: 40 | N39: 0.81428571 | O39: 0.41893456 | P39: 0.58106544 | Q39: 0.38450178 | R39: higher | S39: FALSE | U39: no | V39: 31.105362 | W39: standard | X39: ACT | Y39: 00-0033906
A40: 39 | B40: Tyler Allgeier | C40: AZ | D40: RB | E40: 8.41 | F40: 76.72 | G40: =ROUND(100*((1-SETTINGS!$B$2)*N40+SETTINGS!$B$2*P40),2) | H40: 88.847803 | I40: -68.15 | J40: 0 | K40: 19.688222 | L40: 203.8157 | M40: 42 | N40: 0.8047619 | O40: 0.38302601 | P40: 0.61697399 | Q40: 0.42041033 | R40: higher | S40: FALSE | U40: no | V40: 26.379734 | W40: standard | X40: ACT | Y40: 00-0037263
A41: 40 | B41: James Conner | C41: AZ | D41: RB | E41: 9.52 | F41: 76.69 | G41: =ROUND(100*((1-SETTINGS!$B$2)*N41+SETTINGS!$B$2*P41),2) | H41: 79.161191 | I41: -77.83 | J41: 0 | K41: 10.001609 | L41: 194.12909 | M41: 45 | N41: 0.79047619 | O41: 0.32746081 | P41: 0.67253919 | Q41: 0.47597553 | R41: moderate | S41: TRUE | T41: Questionable | U41: no | V41: 31.327131 | W41: standard | X41: ACT | Y41: 00-0033553
A42: 41 | B42: Jordan Mason | C42: MIN | D42: RB | E42: 8.51 | F42: 76.44 | G42: =ROUND(100*((1-SETTINGS!$B$2)*N42+SETTINGS!$B$2*P42),2) | H42: 84.588826 | I42: -72.41 | J42: 0 | K42: 15.429244 | L42: 199.55672 | M42: 43 | N42: 0.8 | O42: 0.37784157 | P42: 0.62215843 | Q42: 0.42559477 | R42: higher | S42: FALSE | U42: no | V42: 27.27503 | W42: standard | X42: ACT | Y42: 00-0037525
A43: 42 | B43: Chuba Hubbard | C43: CAR | D43: RB | E43: 6.42 | F43: 76.25 | G43: =ROUND(100*((1-SETTINGS!$B$2)*N43+SETTINGS!$B$2*P43),2) | H43: 104.87034 | I43: -52.13 | J43: 0 | K43: 35.710759 | L43: 219.83824 | M43: 38 | N43: 0.82380952 | O43: 0.48250904 | P43: 0.51749096 | Q43: 0.3209273 | R43: higher | S43: TRUE | T43: Questionable | U43: no | V43: 27.225748 | W43: standard | X43: ACT | Y43: 00-0036555
A44: 43 | B44: Samaje Perine | C44: CIN | D44: RB | E44: 8.83 | F44: 75.62 | G44: =ROUND(100*((1-SETTINGS!$B$2)*N44+SETTINGS!$B$2*P44),2) | H44: 79.131387 | I44: -77.86 | J44: 0 | K44: 9.9718049 | L44: 194.09928 | M44: 46 | N44: 0.78571429 | O44: 0.36201366 | P44: 0.63798634 | Q44: 0.44142268 | R44: higher | S44: FALSE | U44: no | V44: 30.960253 | W44: standard | X44: ACT | Y44: 00-0033526
A45: 44 | B45: Kimani Vidal | C45: LAC | D45: RB | E45: 6.36 | F45: 75.05 | G45: =ROUND(100*((1-SETTINGS!$B$2)*N45+SETTINGS!$B$2*P45),2) | H45: 99.849973 | I45: -57.15 | J45: 0 | K45: 30.690392 | L45: 214.81787 | M45: 41 | N45: 0.80952381 | O45: 0.48536094 | P45: 0.51463906 | Q45: 0.3180754 | R45: higher | S45: FALSE | U45: no | V45: 25.01078 | W45: standard | X45: ACT | Y45: 00-0039391
A46: 45 | B46: J.K. Dobbins | C46: DEN | D46: RB | E46: 7.43 | F46: 74.98 | G46: =ROUND(100*((1-SETTINGS!$B$2)*N46+SETTINGS!$B$2*P46),2) | H46: 79.681027 | I46: -77.31 | J46: 0 | K46: 10.521445 | L46: 194.64892 | M46: 44 | N46: 0.7952381 | O46: 0.43210694 | P46: 0.56789306 | Q46: 0.3713294 | R46: higher | S46: TRUE | T46: Questionable | U46: no | V46: 27.707619 | W46: standard | X46: ACT | Y46: 00-0036158
A47: 46 | B47: Cam Skattebo | C47: NYG | D47: RB | E47: 5.41 | F47: 74.87 | G47: =ROUND(100*((1-SETTINGS!$B$2)*N47+SETTINGS!$B$2*P47),2) | H47: 103.04826 | I47: -53.95 | J47: 0 | K47: 33.888679 | L47: 218.01616 | M47: 39 | N47: 0.81904762 | O47: 0.53290271 | P47: 0.46709729 | Q47: 0.27053363 | R47: higher | S47: FALSE | U47: no | V47: 24.569977 | W47: standard | X47: ACT | Y47: 00-0040715
A48: 47 | B48: Devin Singletary | C48: NYG | D48: RB | E48: 7.88 | F48: 73.53 | G48: =ROUND(100*((1-SETTINGS!$B$2)*N48+SETTINGS!$B$2*P48),2) | H48: 70.814851 | I48: -86.18 | J48: 0 | K48: 1.6552696 | L48: 185.78275 | M48: 49 | N48: 0.77142857 | O48: 0.40941737 | P48: 0.59058263 | Q48: 0.39401897 | R48: higher | S48: FALSE | U48: no | V48: 28.994434 | W48: standard | X48: ACT | Y48: 00-0035250
A49: 48 | B49: Ray Davis | C49: BUF | D49: RB | E49: 6.84 | F49: 72.87 | G49: =ROUND(100*((1-SETTINGS!$B$2)*N49+SETTINGS!$B$2*P49),2) | H49: 72.77445 | I49: -84.22 | J49: 0 | K49: 3.6148683 | L49: 187.74235 | M49: 48 | N49: 0.77619048 | O49: 0.46149462 | P49: 0.53850538 | Q49: 0.34194172 | R49: higher | S49: FALSE | U49: no | V49: 26.782206 | W49: standard | X49: ACT | Y49: 00-0039875
A50: 49 | B50: Emanuel Wilson | C50: SEA | D50: RB | E50: 8.28 | F50: 72.78 | G50: =ROUND(100*((1-SETTINGS!$B$2)*N50+SETTINGS!$B$2*P50),2) | H50: 63.267027 | I50: -93.73 | J50: 0 | K50: 0 | L50: 178.23492 | M50: 52 | N50: 0.75714286 | O50: 0.3896499 | P50: 0.6103501 | Q50: 0.41378644 | R50: higher | S50: FALSE | U50: no | V50: 27.318836 | W50: standard | X50: ACT | Y50: 00-0038797
A51: 50 | B51: Audric Estimé | C51: NO | D51: RB | E51: 7.59 | F51: 72.48 | G51: =ROUND(100*((1-SETTINGS!$B$2)*N51+SETTINGS!$B$2*P51),2) | H51: 69.000869 | I51: -87.99 | J51: 0 | K51: 0 | L51: 183.96877 | M51: 51 | N51: 0.76190476 | O51: 0.42380684 | P51: 0.57619316 | Q51: 0.3796295 | R51: higher | S51: FALSE | U51: no | V51: 22.987467 | W51: standard | X51: ACT | Y51: 00-0039373
A52: 51 | B52: Dylan Sampson | C52: CLE | D52: RB | E52: 5.5 | F52: 71.91 | G52: =ROUND(100*((1-SETTINGS!$B$2)*N52+SETTINGS!$B$2*P52),2) | H52: 78.246664 | I52: -78.75 | J52: 0 | K52: 9.0870826 | L52: 193.21456 | M52: 47 | N52: 0.78095238 | O52: 0.52840375 | P52: 0.47159625 | Q52: 0.27503258 | R52: higher | S52: FALSE | U52: no | V52: 21.96349 | W52: standard | X52: ACT | Y52: 00-0040162
A53: 52 | B53: Ollie Gordon II | C53: MIA | D53: RB | E53: 7.85 | F53: 71.59 | G53: =ROUND(100*((1-SETTINGS!$B$2)*N53+SETTINGS!$B$2*P53),2) | H53: 61.871591 | I53: -95.12 | J53: 0 | K53: 0 | L53: 176.83949 | M53: 54 | N53: 0.74761905 | O53: 0.41081959 | P53: 0.58918041 | Q53: 0.39261675 | R53: higher | S53: FALSE | U53: no | V53: 22.628801 | W53: standard | X53: ACT | Y53: 00-0040198
A54: 53 | B54: Devin Neal | C54: NO | D54: RB | E54: 6.18 | F54: 71.44 | G54: =ROUND(100*((1-SETTINGS!$B$2)*N54+SETTINGS!$B$2*P54),2) | H54: 70.038721 | I54: -86.96 | J54: 0 | K54: 0.87913968 | L54: 185.00662 | M54: 50 | N54: 0.76666667 | O54: 0.49465468 | P54: 0.50534532 | Q54: 0.30878166 | R54: higher | S54: TRUE | T54: Questionable | U54: no | V54: 23.055916 | W54: standard | X54: ACT | Y54: 00-0040202
A55: 54 | B55: Isiah Pacheco | C55: DET | D55: RB | E55: 8.74 | F55: 71.34 | G55: =ROUND(100*((1-SETTINGS!$B$2)*N55+SETTINGS!$B$2*P55),2) | H55: 56.58781 | I55: -100.41 | J55: 0 | K55: 0 | L55: 171.55571 | M55: 57 | N55: 0.73333333 | O55: 0.3662784 | P55: 0.6337216 | Q55: 0.43715793 | R55: higher | S55: TRUE | T55: Questionable | U55: no | V55: 27.502275 | W55: standard | X55: ACT | Y55: 00-0037197
A56: 55 | B56: Isaiah Davis | C56: NYJ | D56: RB | E56: 6.41 | F56: 70.53 | G56: =ROUND(100*((1-SETTINGS!$B$2)*N56+SETTINGS!$B$2*P56),2) | H56: 62.382671 | I56: -94.61 | J56: 0 | K56: 0 | L56: 177.35057 | M56: 53 | N56: 0.75238095 | O56: 0.48294381 | P56: 0.51705619 | Q56: 0.32049253 | R56: higher | S56: TRUE | T56: Questionable | U56: no | V56: 24.526171 | W56: standard | X56: ACT | Y56: 00-0039798
A57: 56 | B57: Keaton Mitchell | C57: LAC | D57: RB | E57: 9 | F57: 70.46 | G57: =ROUND(100*((1-SETTINGS!$B$2)*N57+SETTINGS!$B$2*P57),2) | H57: 56.02913 | I57: -100.97 | J57: 0 | K57: 0 | L57: 170.99703 | M57: 60 | N57: 0.71904762 | O57: 0.35322926 | P57: 0.64677074 | Q57: 0.45020708 | R57: higher | S57: FALSE | U57: no | V57: 24.621998 | W57: standard | X57: ACT | Y57: 00-0038454
A58: 57 | B58: Michael Carter | C58: TEN | D58: RB | E58: 7.3 | F58: 70.28 | G58: =ROUND(100*((1-SETTINGS!$B$2)*N58+SETTINGS!$B$2*P58),2) | H58: 59.188469 | I58: -97.81 | J58: 0 | K58: 0 | L58: 174.15636 | M58: 56 | N58: 0.73809524 | O58: 0.43826811 | P58: 0.56173189 | Q58: 0.36516823 | R58: higher | S58: FALSE | U58: no | V58: 27.321573 | W58: standard | X58: ACT | Y58: 00-0036924
A59: 58 | B59: Bhayshul Tuten | C59: JAX | D59: RB | E59: 6.86 | F59: 70.22 | G59: =ROUND(100*((1-SETTINGS!$B$2)*N59+SETTINGS!$B$2*P59),2) | H59: 60.514308 | I59: -96.48 | J59: 0 | K59: 0 | L59: 175.4822 | M59: 55 | N59: 0.74285714 | O59: 0.46020048 | P59: 0.53979952 | Q59: 0.34323586 | R59: higher | S59: FALSE | U59: no | V59: 24.545336 | W59: standard | X59: ACT | Y59: 00-0040719
A60: 59 | B60: Brian Robinson | C60: ATL | D60: RB | E60: 9.71 | F60: 69.65 | G60: =ROUND(100*((1-SETTINGS!$B$2)*N60+SETTINGS!$B$2*P60),2) | H60: 51.287358 | I60: -105.71 | J60: 0 | K60: 0 | L60: 166.25525 | M60: 64 | N60: 0.7 | O60: 0.31770189 | P60: 0.68229811 | Q60: 0.48573445 | R60: moderate | S60: FALSE | U60: no | V60: 27.447517 | W60: standard | X60: ACT | Y60: 00-0037746
A61: 60 | B61: Ty Johnson | C61: BUF | D61: RB | E61: 6.95 | F61: 69.17 | G61: =ROUND(100*((1-SETTINGS!$B$2)*N61+SETTINGS!$B$2*P61),2) | H61: 56.279022 | I61: -100.72 | J61: 0 | K61: 0 | L61: 171.24692 | M61: 58 | N61: 0.72857143 | O61: 0.4559323 | P61: 0.5440677 | Q61: 0.34750404 | R61: higher | S61: TRUE | T61: Questionable | U61: no | V61: 28.956104 | W61: standard | X61: ACT | Y61: 00-0035537
A62: 61 | B62: Chris Rodriguez Jr. | C62: JAX | D62: RB | E62: 7.88 | F62: 68.96 | G62: =ROUND(100*((1-SETTINGS!$B$2)*N62+SETTINGS!$B$2*P62),2) | H62: 52.934438 | I62: -104.06 | J62: 0 | K62: 0 | L62: 167.90233 | M62: 61 | N62: 0.71428571 | O62: 0.40919975 | P62: 0.59080025 | Q62: 0.39423658 | R62: higher | S62: FALSE | U62: no | V62: 26.932791 | W62: standard | X62: ACT | Y62: 00-0038611
A63: 62 | B63: Trey Benson | C63: AZ | D63: RB | E63: 8.36 | F63: 68.68 | G63: =ROUND(100*((1-SETTINGS!$B$2)*N63+SETTINGS!$B$2*P63),2) | H63: 51.444234 | I63: -105.55 | J63: 0 | K63: 0 | L63: 166.41213 | M63: 63 | N63: 0.7047619 | O63: 0.38519716 | P63: 0.61480284 | Q63: 0.41823917 | R63: higher | S63: FALSE | U63: no | V63: 24.110008 | W63: standard | X63: ACT | Y63: 00-0039921
A64: 63 | B64: Jeremy McNichols | C64: WAS | D64: RB | E64: 7.9 | F64: 68.6 | G64: =ROUND(100*((1-SETTINGS!$B$2)*N64+SETTINGS!$B$2*P64),2) | H64: 52.560075 | I64: -104.44 | J64: 0 | K64: 0 | L64: 167.52797 | M64: 62 | N64: 0.70952381 | O64: 0.40828157 | P64: 0.59171843 | Q64: 0.39515477 | R64: higher | S64: TRUE | T64: Questionable | U64: no | V64: 30.683723 | W64: standard | X64: ACT | Y64: 00-0033955
A65: 64 | B65: Brashard Smith | C65: KC | D65: RB | E65: 6.4 | F65: 68.24 | G65: =ROUND(100*((1-SETTINGS!$B$2)*N65+SETTINGS!$B$2*P65),2) | H65: 56.031114 | I65: -100.96 | J65: 0 | K65: 0 | L65: 170.99901 | M65: 59 | N65: 0.72380952 | O65: 0.48342288 | P65: 0.51657712 | Q65: 0.32001346 | R65: higher | S65: FALSE | U65: no | V65: 23.392677 | W65: standard | X65: ACT | Y65: 00-0040078
A66: 65 | B66: Jerome Ford | C66: WAS | D66: RB | E66: 8.81 | F66: 67.98 | G66: =ROUND(100*((1-SETTINGS!$B$2)*N66+SETTINGS!$B$2*P66),2) | H66: 50.077578 | I66: -106.92 | J66: 0 | K66: 0 | L66: 165.04547 | M66: 66 | N66: 0.69047619 | O66: 0.3628845 | P66: 0.6371155 | Q66: 0.44055184 | R66: higher | S66: FALSE | U66: no | V66: 26.971123 | W66: standard | X66: ACT | Y66: 00-0037267
A67: 66 | B67: Tank Bigsby | C67: PHI | D67: RB | E67: 8.03 | F67: 67.58 | G67: =ROUND(100*((1-SETTINGS!$B$2)*N67+SETTINGS!$B$2*P67),2) | H67: 50.555892 | I67: -106.44 | J67: 0 | K67: 0 | L67: 165.52379 | M67: 65 | N67: 0.6952381 | O67: 0.40193884 | P67: 0.59806116 | Q67: 0.4014975 | R67: higher | S67: FALSE | U67: no | V67: 24.005968 | W67: standard | X67: ACT | Y67: 00-0038555
A68: 67 | B68: Sean Tucker | C68: TB | D68: RB | E68: 8.67 | F68: 67.46 | G68: =ROUND(100*((1-SETTINGS!$B$2)*N68+SETTINGS!$B$2*P68),2) | H68: 48.902885 | I68: -108.09 | J68: 0 | K68: 0 | L68: 163.87078 | M68: 67 | N68: 0.68571429 | O68: 0.36993953 | P68: 0.63006047 | Q68: 0.43349681 | R68: higher | S68: FALSE | U68: no | V68: 24.851982 | W68: standard | X68: ACT | Y68: 00-0038951
A69: 68 | B69: Emari Demercado | C69: KC | D69: RB | E69: 8.63 | F69: 67.04 | G69: =ROUND(100*((1-SETTINGS!$B$2)*N69+SETTINGS!$B$2*P69),2) | H69: 46.522322 | I69: -110.47 | J69: 0 | K69: 0 | L69: 161.49022 | M69: 68 | N69: 0.68095238 | O69: 0.37173676 | P69: 0.62826324 | Q69: 0.43169958 | R69: higher | S69: FALSE | U69: no | V69: 27.614531 | W69: standard | X69: ACT | Y69: 00-0038705
A70: 69 | B70: Ameer Abdullah | C70: JAX | D70: RB | E70: 10.51 | F70: 67.01 | G70: =ROUND(100*((1-SETTINGS!$B$2)*N70+SETTINGS!$B$2*P70),2) | H70: 40.168205 | I70: -116.83 | J70: 0 | K70: 12.030366 | L70: 68.496662 | M70: 73 | N70: 0.65714286 | O70: 0.27818356 | P70: 0.72181644 | Q70: 0.52525278 | R70: moderate | S70: FALSE | U70: no | V70: 33.219025 | W70: standard | X70: ACT | Y70: 00-0032104
A71: 70 | B71: Trevor Etienne | C71: CAR | D71: RB | E71: 8.87 | F71: 66.51 | G71: =ROUND(100*((1-SETTINGS!$B$2)*N71+SETTINGS!$B$2*P71),2) | H71: 45.502622 | I71: -111.49 | J71: 0 | K71: 0 | L71: 160.47052 | M71: 70 | N71: 0.67142857 | O71: 0.35996981 | P71: 0.64003019 | Q71: 0.44346653 | R71: higher | S71: FALSE | U71: no | V71: 22.146931 | W71: standard | X71: ACT | Y71: 00-0040644
A72: 71 | B72: Bam Knight | C72: AZ | D72: RB | E72: 8.36 | F72: 66.38 | G72: =ROUND(100*((1-SETTINGS!$B$2)*N72+SETTINGS!$B$2*P72),2) | H72: 45.707987 | I72: -111.29 | J72: 0 | K72: 0 | L72: 160.67588 | M72: 69 | N72: 0.67619048 | O72: 0.38566439 | P72: 0.61433561 | Q72: 0.41777195 | R72: higher | S72: FALSE | U72: no | V72: 25.39135 | W72: standard | X72: ACT | Y72: 00-0037157
A73: 72 | B73: Malik Davis | C73: DAL | D73: RB | E73: 10.68 | F73: 66.04 | G73: =ROUND(100*((1-SETTINGS!$B$2)*N73+SETTINGS!$B$2*P73),2) | H73: 37.299517 | I73: -119.7 | J73: 0 | K73: 9.1616775 | L73: 65.627973 | M73: 76 | N73: 0.64285714 | O73: 0.26955647 | P73: 0.73044353 | Q73: 0.53387987 | R73: moderate | S73: FALSE | U73: no | V73: 27.765116 | W73: standard | X73: ACT | Y73: 00-0037563
A74: 73 | B74: Tyler Badie | C74: DEN | D74: RB | E74: 8.65 | F74: 65.92 | G74: =ROUND(100*((1-SETTINGS!$B$2)*N74+SETTINGS!$B$2*P74),2) | H74: 42.414477 | I74: -114.58 | J74: 0 | K74: 0 | L74: 157.38237 | M74: 71 | N74: 0.66666667 | O74: 0.37087929 | P74: 0.62912071 | Q74: 0.43255705 | R74: higher | S74: FALSE | U74: no | V74: 27.565248 | W74: standard | X74: ACT | Y74: 00-0037085
A75: 74 | B75: Kyle Juszczyk | C75: SF | D75: RB | E75: 9.67 | F75: 65.79 | G75: =ROUND(100*((1-SETTINGS!$B$2)*N75+SETTINGS!$B$2*P75),2) | H75: 39.888838 | I75: -117.11 | J75: 0 | K75: 11.750999 | L75: 68.217294 | M75: 74 | N75: 0.65238095 | O75: 0.32016674 | P75: 0.67983326 | Q75: 0.4832696 | R75: moderate | S75: TRUE | T75: Questionable | U75: no | V75: 35.360069 | W75: standard | X75: ACT | Y75: 00-0029892
A76: 75 | B76: Jaydon Blue | C76: DAL | D76: RB | E76: 10.47 | F76: 65.06 | G76: =ROUND(100*((1-SETTINGS!$B$2)*N76+SETTINGS!$B$2*P76),2) | H76: 35.695825 | I76: -121.3 | J76: 0 | K76: 7.5579856 | L76: 64.024281 | M76: 78 | N76: 0.63333333 | O76: 0.28011547 | P76: 0.71988453 | Q76: 0.52332087 | R76: moderate | S76: FALSE | U76: no | V76: 22.647966 | W76: standard | X76: ACT | Y76: 00-0040586
A77: 76 | B77: Justice Hill | C77: BAL | D77: RB | E77: 7.9 | F77: 64.78 | G77: =ROUND(100*((1-SETTINGS!$B$2)*N77+SETTINGS!$B$2*P77),2) | H77: 42.253387 | I77: -114.74 | J77: 0 | K77: 0 | L77: 157.22128 | M77: 72 | N77: 0.66190476 | O77: 0.40865256 | P77: 0.59134744 | Q77: 0.39478378 | R77: higher | S77: FALSE | U77: no | V77: 28.797306 | W77: standard | X77: ACT | Y77: 00-0034975
A78: 77 | B78: Jawhar Jordan | C78: HOU | D78: RB | E78: 9.94 | F78: 64.16 | G78: =ROUND(100*((1-SETTINGS!$B$2)*N78+SETTINGS!$B$2*P78),2) | H78: 32.546408 | I78: -124.45 | J78: 0 | K78: 4.4085685 | L78: 60.874864 | M78: 79 | N78: 0.62857143 | O78: 0.30619288 | P78: 0.69380712 | Q78: 0.49724346 | R78: moderate | S78: TRUE | T78: Questionable | U78: no | V78: 27.03957 | W78: standard | X78: ACT | Y78: 00-0039405
A79: 78 | B79: Jaylen Wright | C79: MIA | D79: RB | E79: 8.03 | F79: 63.77 | G79: =ROUND(100*((1-SETTINGS!$B$2)*N79+SETTINGS!$B$2*P79),2) | H79: 39.829358 | I79: -117.17 | J79: 0 | K79: 11.691518 | L79: 68.157814 | M79: 75 | N79: 0.64761905 | O79: 0.40197718 | P79: 0.59802282 | Q79: 0.40145916 | R79: higher | S79: FALSE | U79: no | V79: 23.420057 | W79: standard | X79: ACT | Y79: 00-0039874
A80: 79 | B80: DJ Giddens | C80: IND | D80: RB | E80: 10.98 | F80: 63.68 | G80: =ROUND(100*((1-SETTINGS!$B$2)*N80+SETTINGS!$B$2*P80),2) | H80: 25.033877 | I80: -131.96 | J80: 0 | K80: 0 | L80: 53.362333 | M80: 83 | N80: 0.60952381 | O80: 0.2542998 | P80: 0.7457002 | Q80: 0.54913654 | R80: moderate | S80: TRUE | T80: Questionable | U80: no | V80: 23.017584 | W80: standard | X80: ACT | Y80: 00-0040179
A81: 80 | B81: Hunter Luepke | C81: DAL | D81: RB | E81: 9.58 | F81: 63.42 | G81: =ROUND(100*((1-SETTINGS!$B$2)*N81+SETTINGS!$B$2*P81),2) | H81: 28.857965 | I81: -128.14 | J81: 0 | K81: 0.72012586 | L81: 57.186422 | M81: 80 | N81: 0.62380952 | O81: 0.32443679 | P81: 0.67556321 | Q81: 0.47899955 | R81: moderate | S81: FALSE | U81: no | V81: 26.508415 | W81: standard | X81: ACT | Y81: 00-0038738
A82: 81 | B82: Kendre Miller | C82: NO | D82: RB | E82: 9.87 | F82: 63.33 | G82: =ROUND(100*((1-SETTINGS!$B$2)*N82+SETTINGS!$B$2*P82),2) | H82: 27.7189 | I82: -129.28 | J82: 0 | K82: 0 | L82: 56.047356 | M82: 81 | N82: 0.61904762 | O82: 0.30978517 | P82: 0.69021483 | Q82: 0.49365117 | R82: moderate | S82: TRUE | T82: Questionable | U82: no | V82: 24.225 | W82: standard | X82: ACT | Y82: 00-0038551
A83: 82 | B83: Jaleel McLaughlin | C83: DEN | D83: RB | E83: 9.98 | F83: 63.05 | G83: =ROUND(100*((1-SETTINGS!$B$2)*N83+SETTINGS!$B$2*P83),2) | H83: 27.233833 | I83: -129.76 | J83: 0 | K83: 0 | L83: 55.562289 | M83: 82 | N83: 0.61428571 | O83: 0.30445999 | P83: 0.69554001 | Q83: 0.49897635 | R83: moderate | S83: FALSE | U83: no | V83: 25.966311 | W83: standard | X83: ACT | Y83: 00-0038794
A84: 83 | B84: LeQuint Allen Jr. | C84: JAX | D84: RB | E84: 7.69 | F84: 62.67 | G84: =ROUND(100*((1-SETTINGS!$B$2)*N84+SETTINGS!$B$2*P84),2) | H84: 36.500884 | I84: -120.49 | J84: 0 | K84: 8.3630448 | L84: 64.82934 | M84: 77 | N84: 0.63809524 | O84: 0.41900846 | P84: 0.58099154 | Q84: 0.38442788 | R84: higher | S84: FALSE | U84: no | V84: 22.073006 | W84: standard | X84: ACT | Y84: 00-0040238
A85: 84 | B85: Kaleb Johnson | C85: PIT | D85: RB | E85: 9.99 | F85: 61.92 | G85: =ROUND(100*((1-SETTINGS!$B$2)*N85+SETTINGS!$B$2*P85),2) | H85: 24.539227 | I85: -132.46 | J85: 0 | K85: 0 | L85: 52.867683 | M85: 85 | N85: 0.6 | O85: 0.30389914 | P85: 0.69610086 | Q85: 0.4995372 | R85: moderate | S85: FALSE | U85: no | V85: 23.05044 | W85: standard | X85: ACT | Y85: 00-0040142
A86: 85 | B86: Jeremiyah Love | C86: AZ | D86: RB | E86: 10.9 | F86: 60.92 | G86: =ROUND(100*((1-SETTINGS!$B$2)*N86+SETTINGS!$B$2*P86),2) | H86: 20.574482 | I86: -136.42 | J86: 0 | K86: 0 | L86: 48.902939 | M86: 90 | N86: 0.57619048 | O86: 0.25861714 | P86: 0.74138286 | Q86: 0.5448192 | R86: moderate | S86: TRUE | T86: Questionable | U86: yes | V86: 21.254372 | W86: standard | X86: ACT | Y86: 00-0041027
A87: 86 | B87: Jonah Coleman | C87: DEN | D87: RB | E87: 11.16 | F87: 60.8 | G87: =ROUND(100*((1-SETTINGS!$B$2)*N87+SETTINGS!$B$2*P87),2) | H87: 20.559399 | I87: -136.44 | J87: 0 | K87: 0 | L87: 48.887856 | M87: 91 | N87: 0.57142857 | O87: 0.24559631 | P87: 0.75440369 | Q87: 0.55784003 | R87: moderate | S87: FALSE | U87: yes | V87: 23.034012 | W87: standard | X87: ACT | Y87: 00-0041496
A88: 87 | B88: Tahj Brooks | C88: CIN | D88: RB | E88: 9.64 | F88: 60.43 | G88: =ROUND(100*((1-SETTINGS!$B$2)*N88+SETTINGS!$B$2*P88),2) | H88: 20.893189 | I88: -136.1 | J88: 0 | K88: 0 | L88: 49.221645 | M88: 88 | N88: 0.58571429 | O88: 0.32122663 | P88: 0.67877337 | Q88: 0.4822097 | R88: moderate | S88: FALSE | U88: no | V88: 24.304401 | W88: standard | X88: ACT | Y88: 00-0040208
A89: 88 | B89: George Holani | C89: SEA | D89: RB | E89: 9.7 | F89: 60.11 | G89: =ROUND(100*((1-SETTINGS!$B$2)*N89+SETTINGS!$B$2*P89),2) | H89: 20.699762 | I89: -136.3 | J89: 0 | K89: 0 | L89: 49.028218 | M89: 89 | N89: 0.58095238 | O89: 0.31825382 | P89: 0.68174618 | Q89: 0.48518252 | R89: moderate | S89: FALSE | U89: no | V89: 26.711021 | W89: standard | X89: ACT | Y89: 00-0039299
A90: 89 | B90: Terrell Jennings | C90: NE | D90: RB | E90: 11.26 | F90: 59.76 | G90: =ROUND(100*((1-SETTINGS!$B$2)*N90+SETTINGS!$B$2*P90),2) | H90: 19.276949 | I90: -137.72 | J90: 0 | K90: 0 | L90: 47.605405 | M90: 94 | N90: 0.55714286 | O90: 0.24034151 | P90: 0.75965849 | Q90: 0.56309482 | R90: moderate | S90: TRUE | T90: IR | U90: no | V90: 25.659664 | W90: standard | X90: ACT | Y90: 00-0039757
A91: 90 | B91: Raheim Sanders | C91: CLE | D91: RB | E91: 10.84 | F91: 59.72 | G91: =ROUND(100*((1-SETTINGS!$B$2)*N91+SETTINGS!$B$2*P91),2) | H91: 19.656904 | I91: -137.34 | J91: 0 | K91: 0 | L91: 47.98536 | M91: 93 | N91: 0.56190476 | O91: 0.26159666 | P91: 0.73840334 | Q91: 0.54183968 | R91: moderate | S91: FALSE | U91: no | V91: 24.233215 | W91: standard | X91: ACT | Y91: 00-0040466
A92: 91 | B92: Rasheen Ali | C92: BAL | D92: RB | E92: 7.33 | F92: 59.64 | G92: =ROUND(100*((1-SETTINGS!$B$2)*N92+SETTINGS!$B$2*P92),2) | H92: 24.79277 | I92: -132.2 | J92: 0 | K92: 0 | L92: 53.121226 | M92: 84 | N92: 0.6047619 | O92: 0.43680936 | P92: 0.56319064 | Q92: 0.36662697 | R92: higher | S92: FALSE | U92: no | V92: 25.539196 | W92: standard | X92: ACT | Y92: 00-0039796
A93: 92 | B93: Zavier Scott | C93: MIN | D93: RB | E93: 8.45 | F93: 59.62 | G93: =ROUND(100*((1-SETTINGS!$B$2)*N93+SETTINGS!$B$2*P93),2) | H93: 21.496501 | I93: -135.5 | J93: 0 | K93: 0 | L93: 49.824957 | M93: 87 | N93: 0.59047619 | O93: 0.38087924 | P93: 0.61912076 | Q93: 0.4225571 | R93: higher | S93: FALSE | U93: no | V93: 27.127182 | W93: standard | X93: ACT | Y93: 00-0038440
A94: 93 | B94: Will Shipley | C94: PHI | D94: RB | E94: 7.84 | F94: 59.39 | G94: =ROUND(100*((1-SETTINGS!$B$2)*N94+SETTINGS!$B$2*P94),2) | H94: 23.381167 | I94: -133.61 | J94: 0 | K94: 0 | L94: 51.709623 | M94: 86 | N94: 0.5952381 | O94: 0.41163313 | P94: 0.58836687 | Q94: 0.39180321 | R94: higher | S94: FALSE | U94: no | V94: 24.008707 | W94: standard | X94: ACT | Y94: 00-0039746
A95: 94 | B95: Jaret Patterson | C95: LAC | D95: RB | E95: 11.41 | F95: 59.15 | G95: =ROUND(100*((1-SETTINGS!$B$2)*N95+SETTINGS!$B$2*P95),2) | H95: 18.588094 | I95: -138.41 | J95: 0 | K95: 0 | L95: 46.91655 | M95: 96 | N95: 0.54761905 | O95: 0.23288933 | P95: 0.76711067 | Q95: 0.570547 | R95: moderate | S95: FALSE | U95: no | V95: 26.691854 | W95: standard | X95: ACT | Y95: 00-0036755
A96: 95 | B96: Velus Jones Jr. | C96: SEA | D96: RB | E96: 12.42 | F96: 59.02 | G96: =ROUND(100*((1-SETTINGS!$B$2)*N96+SETTINGS!$B$2*P96),2) | H96: 16.007939 | I96: -140.99 | J96: 0 | K96: 0 | L96: 44.336395 | M96: 99 | N96: 0.53333333 | O96: 0.18242535 | P96: 0.81757465 | Q96: 0.62101099 | R96: lower | S96: FALSE | U96: no | V96: 29.309294 | W96: standard | X96: ACT | Y96: 00-0037745
A97: 96 | B97: Braelon Allen | C97: NYJ | D97: RB | E97: 9.27 | F97: 58.53 | G97: =ROUND(100*((1-SETTINGS!$B$2)*N97+SETTINGS!$B$2*P97),2) | H97: 19.840443 | I97: -137.16 | J97: 0 | K97: 0 | L97: 48.168899 | M97: 92 | N97: 0.56666667 | O97: 0.34006976 | P97: 0.65993024 | Q97: 0.46336658 | R97: moderate | S97: FALSE | U97: no | V97: 22.615112 | W97: standard | X97: ACT | Y97: 00-0039794
A98: 97 | B98: Isaac Guerendo | C98: SF | D98: RB | E98: 10.59 | F98: 57.95 | G98: =ROUND(100*((1-SETTINGS!$B$2)*N98+SETTINGS!$B$2*P98),2) | H98: 18.381381 | I98: -138.61 | J98: 0 | K98: 0 | L98: 46.709837 | M98: 97 | N98: 0.54285714 | O98: 0.27380551 | P98: 0.72619449 | Q98: 0.52963083 | R98: moderate | S98: TRUE | T98: Out | U98: no | V98: 26.17713 | W98: standard | X98: ACT | Y98: 00-0039363
A99: 98 | B99: Jonathon Brooks | C99: CAR | D99: RB | E99: 10.71 | F99: 57.68 | G99: =ROUND(100*((1-SETTINGS!$B$2)*N99+SETTINGS!$B$2*P99),2) | H99: 17.162382 | I99: -139.83 | J99: 0 | K99: 0 | L99: 45.490838 | M99: 98 | N99: 0.53809524 | O99: 0.26815227 | P99: 0.73184773 | Q99: 0.53528407 | R99: moderate | S99: FALSE | U99: no | V99: 23.116148 | W99: standard | X99: ACT | Y99: 00-0039344
A100: 99 | B100: Noah Whittington | C100: HOU | D100: RB | E100: 11.19 | F100: 57.03 | G100: =ROUND(100*((1-SETTINGS!$B$2)*N100+SETTINGS!$B$2*P100),2) | H100: 15.770826 | I100: -141.22 | J100: 0 | K100: 0 | L100: 44.099282 | M100: 101 | N100: 0.52380952 | O100: 0.24386395 | P100: 0.75613605 | Q100: 0.55957239 | R100: moderate | S100: FALSE | U100: yes | V100: 24.717825 | W100: standard | X100: ACT | Y100: 00-0041312
...

Sheet WR
A1: Rank | B1: Player | C1: Team | D1: Pos | E1: Overall Draft Score (replacement-adjusted) | F1: Position Draft Score (default weight) | G1: Custom-Weight Score (weight from SETTINGS) | H1: Projected 2026 Points | I1: Points Over Replacement | J1: Overall Value (points over replacement / max) | K1: Points P10 | L1: Points P90 | M1: Pos Points Rank | N1: Pos Points Percentile | O1: Missed-Time Injury Probability | P1: Healthy Probability | Q1: Healthy Probability vs Position Mean (+0.5) | R1: Injury Risk Band | S1: Current Injury Listing (screen date) | T1: Current Listing Status | U1: Rookie | V1: Age | W1: Points Model Confidence | X1: Roster Status (Aug 9) | Y1: Player ID
A2: 1 | B2: Ja'Marr Chase | C2: CIN | D2: WR | E2: 65.83 | F2: 91.81 | G2: =ROUND(100*((1-SETTINGS!$B$2)*N2+SETTINGS!$B$2*P2),2) | H2: 215.27921 | I2: 92.79 | J2: 0.7292 | K2: 147.48739 | L2: 297.55999 | M2: 4 | N2: 0.9921875 | O2: 0.37819061 | P2: 0.62180939 | Q2: 0.37466292 | R2: higher | S2: FALSE | U2: no | V2: 26.502939 | W2: standard | X2: ACT | Y2: 00-0036900
A3: 2 | B3: George Pickens | C3: DAL | D3: WR | E3: 63.88 | F3: 91.25 | G3: =ROUND(100*((1-SETTINGS!$B$2)*N3+SETTINGS!$B$2*P3),2) | H3: 212.40207 | I3: 89.92 | J3: 0.7066 | K3: 144.61025 | L3: 294.68285 | M3: 6 | N3: 0.98697917 | O3: 0.38547724 | P3: 0.61452276 | Q3: 0.36737629 | R3: higher | S3: FALSE | U3: no | V3: 25.49539 | W3: standard | X3: ACT | Y3: 00-0037247
A4: 3 | B4: Amon-Ra St. Brown | C4: DET | D4: WR | E4: 75.19 | F4: 91.13 | G4: =ROUND(100*((1-SETTINGS!$B$2)*N4+SETTINGS!$B$2*P4),2) | H4: 231.91781 | I4: 109.43 | J4: 0.86 | K4: 164.12599 | L4: 314.19859 | M4: 2 | N4: 0.99739583 | O4: 0.43314403 | P4: 0.56685597 | Q4: 0.3197095 | R4: higher | S4: FALSE | U4: no | V4: 26.856131 | W4: standard | X4: ACT | Y4: 00-0036963
A5: 4 | B5: Justin Jefferson | C5: MIN | D5: WR | E5: 63.83 | F5: 91.03 | G5: =ROUND(100*((1-SETTINGS!$B$2)*N5+SETTINGS!$B$2*P5),2) | H5: 213.00414 | I5: 90.52 | J5: 0.7114 | K5: 145.21232 | L5: 295.28492 | M5: 5 | N5: 0.98958333 | O5: 0.4070599 | P5: 0.5929401 | Q5: 0.34579363 | R5: higher | S5: FALSE | U5: no | V5: 27.212057 | W5: standard | X5: ACT | Y5: 00-0036322
A6: 5 | B6: Jaxon Smith-Njigba | C6: SEA | D6: WR | E6: 85.74 | F6: 90.68 | G6: =ROUND(100*((1-SETTINGS!$B$2)*N6+SETTINGS!$B$2*P6),2) | H6: 249.73827 | I6: 127.25 | J6: 1 | K6: 181.94645 | L6: 332.01905 | M6: 1 | N6: 1 | O6: 0.46595868 | P6: 0.53404132 | Q6: 0.28689485 | R6: higher | S6: FALSE | U6: no | V6: 24.545336 | W6: standard | X6: ACT | Y6: 00-0038543
A7: 6 | B7: Puka Nacua | C7: LA | D7: WR | E7: 74.24 | F7: 90.38 | G7: =ROUND(100*((1-SETTINGS!$B$2)*N7+SETTINGS!$B$2*P7),2) | H7: 231.26732 | I7: 108.78 | J7: 0.8549 | K7: 163.4755 | L7: 313.5481 | M7: 3 | N7: 0.99479167 | O7: 0.46033059 | P7: 0.53966941 | Q7: 0.29252294 | R7: higher | S7: TRUE | T7: Questionable | U7: no | V7: 25.25993 | W7: standard | X7: ACT | Y7: 00-0039075
A8: 7 | B8: Chris Olave | C8: NO | D8: WR | E8: 42.78 | F8: 89.86 | G8: =ROUND(100*((1-SETTINGS!$B$2)*N8+SETTINGS!$B$2*P8),2) | H8: 178.73788 | I8: 56.25 | J8: 0.442 | K8: 110.94606 | L8: 261.01867 | M8: 13 | N8: 0.96875 | O8: 0.38199551 | P8: 0.61800449 | Q8: 0.37085802 | R8: higher | S8: FALSE | U8: no | V8: 26.179867 | W8: standard | X8: ACT | Y8: 00-0037239
A9: 8 | B9: Zay Flowers | C9: BAL | D9: WR | E9: 59.1 | F9: 89.65 | G9: =ROUND(100*((1-SETTINGS!$B$2)*N9+SETTINGS!$B$2*P9),2) | H9: 206.67381 | I9: 84.19 | J9: 0.6616 | K9: 138.88199 | L9: 288.95459 | M9: 8 | N9: 0.98177083 | O9: 0.44443044 | P9: 0.55556956 | Q9: 0.30842309 | R9: higher | S9: FALSE | U9: no | V9: 25.971786 | W9: standard | X9: ACT | Y9: 00-0039064
A10: 9 | B10: CeeDee Lamb | C10: DAL | D10: WR | E10: 58.45 | F10: 89.03 | G10: =ROUND(100*((1-SETTINGS!$B$2)*N10+SETTINGS!$B$2*P10),2) | H10: 206.9714 | I10: 84.49 | J10: 0.664 | K10: 139.17958 | L10: 289.25218 | M10: 7 | N10: 0.984375 | O10: 0.48621738 | P10: 0.51378262 | Q10: 0.26663615 | R10: higher | S10: FALSE | U10: no | V10: 27.400974 | W10: standard | X10: ACT | Y10: 00-0036358
A11: 10 | B11: Jameson Williams | C11: DET | D11: WR | E11: 54.7 | F11: 88.93 | G11: =ROUND(100*((1-SETTINGS!$B$2)*N11+SETTINGS!$B$2*P11),2) | H11: 200.4812 | I11: 78 | J11: 0.613 | K11: 132.68938 | L11: 282.76198 | M11: 9 | N11: 0.97916667 | O11: 0.47008001 | P11: 0.52991999 | Q11: 0.28277352 | R11: higher | S11: FALSE | U11: no | V11: 25.435156 | W11: standard | X11: ACT | Y11: 00-0037240
A12: 11 | B12: Nico Collins | C12: HOU | D12: WR | E12: 40.99 | F12: 87.95 | G12: =ROUND(100*((1-SETTINGS!$B$2)*N12+SETTINGS!$B$2*P12),2) | H12: 179.27048 | I12: 56.78 | J12: 0.4462 | K12: 111.47866 | L12: 261.55126 | M12: 12 | N12: 0.97135417 | O12: 0.48793958 | P12: 0.51206042 | Q12: 0.26491395 | R12: higher | S12: FALSE | U12: no | V12: 27.455732 | W12: standard | X12: ACT | Y12: 00-0036554
A13: 12 | B13: Jaylen Waddle | C13: DEN | D13: WR | E13: 40.4 | F13: 87.71 | G13: =ROUND(100*((1-SETTINGS!$B$2)*N13+SETTINGS!$B$2*P13),2) | H13: 178.02173 | I13: 55.54 | J13: 0.4365 | K13: 110.22991 | L13: 260.30251 | M13: 14 | N13: 0.96614583 | O13: 0.47908948 | P13: 0.52091052 | Q13: 0.27376405 | R13: higher | S13: TRUE | T13: Questionable | U13: no | V13: 27.767853 | W13: standard | X13: ACT | Y13: 00-0036613
A14: 13 | B14: Drake London | C14: ATL | D14: WR | E14: 52.09 | F14: 87.69 | G14: =ROUND(100*((1-SETTINGS!$B$2)*N14+SETTINGS!$B$2*P14),2) | H14: 197.9819 | I14: 75.5 | J14: 0.5933 | K14: 130.19008 | L14: 280.26269 | M14: 10 | N14: 0.9765625 | O14: 0.52163641 | P14: 0.47836359 | Q14: 0.23121712 | R14: higher | S14: FALSE | U14: no | V14: 25.106607 | W14: standard | X14: ACT | Y14: 00-0037238
A15: 14 | B15: A.J. Brown | C15: NE | D15: WR | E15: 39.58 | F15: 87.66 | G15: =ROUND(100*((1-SETTINGS!$B$2)*N15+SETTINGS!$B$2*P15),2) | H15: 176.48154 | I15: 54 | J15: 0.4244 | K15: 108.68972 | L15: 258.76232 | M15: 15 | N15: 0.96354167 | O15: 0.47129817 | P15: 0.52870183 | Q15: 0.28155536 | R15: higher | S15: FALSE | U15: no | V15: 29.1724 | W15: standard | X15: ACT | Y15: 00-0035676
A16: 15 | B16: DeVonta Smith | C16: PHI | D16: WR | E16: 38.66 | F16: 87.49 | G16: =ROUND(100*((1-SETTINGS!$B$2)*N16+SETTINGS!$B$2*P16),2) | H16: 174.96752 | I16: 52.48 | J16: 0.4124 | K16: 107.1757 | L16: 257.2483 | M16: 16 | N16: 0.9609375 | O16: 0.46928457 | P16: 0.53071543 | Q16: 0.28356896 | R16: higher | S16: TRUE | T16: Questionable | U16: no | V16: 27.79797 | W16: standard | X16: ACT | Y16: 00-0036912
A17: 16 | B17: Tetairoa McMillan | C17: CAR | D17: WR | E17: 43.19 | F17: 87.24 | G17: =ROUND(100*((1-SETTINGS!$B$2)*N17+SETTINGS!$B$2*P17),2) | H17: 184.2247 | I17: 61.74 | J17: 0.4852 | K17: 116.43288 | L17: 266.50548 | M17: 11 | N17: 0.97395833 | O17: 0.53396651 | P17: 0.46603349 | Q17: 0.21888702 | R17: higher | S17: FALSE | U17: no | V17: 23.409105 | W17: standard | X17: ACT | Y17: 00-0040124
A18: 17 | B18: Wan'Dale Robinson | C18: TEN | D18: WR | E18: 36.18 | F18: 86.88 | G18: =ROUND(100*((1-SETTINGS!$B$2)*N18+SETTINGS!$B$2*P18),2) | H18: 171.65199 | I18: 49.17 | J18: 0.3864 | K18: 103.86017 | L18: 253.93278 | M18: 17 | N18: 0.95833333 | O18: 0.48954781 | P18: 0.51045219 | Q18: 0.26330572 | R18: higher | S18: FALSE | U18: no | V18: 25.654188 | W18: standard | X18: ACT | Y18: 00-0038117
A19: 18 | B19: Davante Adams | C19: LA | D19: WR | E19: 31.12 | F19: 86.65 | G19: =ROUND(100*((1-SETTINGS!$B$2)*N19+SETTINGS!$B$2*P19),2) | H19: 162.3029 | I19: 39.82 | J19: 0.3129 | K19: 94.511082 | L19: 244.58368 | M19: 22 | N19: 0.9453125 | O19: 0.44855853 | P19: 0.55144147 | Q19: 0.30429499 | R19: higher | S19: FALSE | U19: no | V19: 33.687206 | W19: standard | X19: ACT | Y19: 00-0031381
A20: 19 | B20: Khalil Shakir | C20: BUF | D20: WR | E20: 21.08 | F20: 86.32 | G20: =ROUND(100*((1-SETTINGS!$B$2)*N20+SETTINGS!$B$2*P20),2) | H20: 144.87719 | I20: 22.39 | J20: 0.176 | K20: 77.085368 | L20: 227.15797 | M20: 28 | N20: 0.9296875 | O20: 0.4026671 | P20: 0.5973329 | Q20: 0.35018643 | R20: higher | S20: FALSE | U20: no | V20: 26.576864 | W20: standard | X20: ACT | Y20: 00-0037261
A21: 20 | B21: Michael Pittman | C21: PIT | D21: WR | E21: 31.07 | F21: 86.22 | G21: =ROUND(100*((1-SETTINGS!$B$2)*N21+SETTINGS!$B$2*P21),2) | H21: 163.57812 | I21: 41.09 | J21: 0.3229 | K21: 95.786296 | L21: 245.8589 | M21: 20 | N21: 0.95052083 | O21: 0.49104256 | P21: 0.50895744 | Q21: 0.26181097 | R21: higher | S21: TRUE | T21: Questionable | U21: no | V21: 28.906822 | W21: standard | X21: ACT | Y21: 00-0036252
A22: 21 | B22: Courtland Sutton | C22: DEN | D22: WR | E22: 30.5 | F22: 86.09 | G22: =ROUND(100*((1-SETTINGS!$B$2)*N22+SETTINGS!$B$2*P22),2) | H22: 162.54173 | I22: 40.06 | J22: 0.3148 | K22: 94.749911 | L22: 244.82251 | M22: 21 | N22: 0.94791667 | O22: 0.48727471 | P22: 0.51272529 | Q22: 0.26557882 | R22: higher | S22: FALSE | U22: no | V22: 30.894543 | W22: standard | X22: ACT | Y22: 00-0034348
A23: 22 | B23: Michael Wilson | C23: AZ | D23: WR | E23: 31.45 | F23: 85.88 | G23: =ROUND(100*((1-SETTINGS!$B$2)*N23+SETTINGS!$B$2*P23),2) | H23: 165.04877 | I23: 42.56 | J23: 0.3345 | K23: 97.25695 | L23: 247.32955 | M23: 19 | N23: 0.953125 | O23: 0.51845499 | P23: 0.48154501 | Q23: 0.23439854 | R23: higher | S23: FALSE | U23: no | V23: 26.522104 | W23: standard | X23: ACT | Y23: 00-0038559
A24: 23 | B24: Emeka Egbuka | C24: TB | D24: WR | E24: 33.62 | F24: 85.8 | G24: =ROUND(100*((1-SETTINGS!$B$2)*N24+SETTINGS!$B$2*P24),2) | H24: 168.97355 | I24: 46.49 | J24: 0.3653 | K24: 101.18173 | L24: 251.25433 | M24: 18 | N24: 0.95572917 | O24: 0.53296324 | P24: 0.46703676 | Q24: 0.21989029 | R24: higher | S24: TRUE | T24: Questionable | U24: no | V24: 23.882763 | W24: standard | X24: ACT | Y24: 00-0040129
A25: 24 | B25: Alec Pierce | C25: IND | D25: WR | E25: 20.79 | F25: 85.73 | G25: =ROUND(100*((1-SETTINGS!$B$2)*N25+SETTINGS!$B$2*P25),2) | H25: 145.68725 | I25: 23.2 | J25: 0.1823 | K25: 77.895427 | L25: 227.96803 | M25: 27 | N25: 0.93229167 | O25: 0.4426161 | P25: 0.5573839 | Q25: 0.31023743 | R25: higher | S25: TRUE | T25: Out | U25: no | V25: 26.333189 | W25: standard | X25: ACT | Y25: 00-0037664
A26: 25 | B26: Tee Higgins | C26: CIN | D26: WR | E26: 25.73 | F26: 85.16 | G26: =ROUND(100*((1-SETTINGS!$B$2)*N26+SETTINGS!$B$2*P26),2) | H26: 155.11223 | I26: 32.63 | J26: 0.2564 | K26: 87.32041 | L26: 237.39301 | M26: 25 | N26: 0.9375 | O26: 0.4920269 | P26: 0.5079731 | Q26: 0.26082663 | R26: higher | S26: FALSE | U26: no | V26: 27.620007 | W26: standard | X26: ACT | Y26: 00-0036410
A27: 26 | B27: Jakobi Meyers | C27: JAX | D27: WR | E27: 27.88 | F27: 84.95 | G27: =ROUND(100*((1-SETTINGS!$B$2)*N27+SETTINGS!$B$2*P27),2) | H27: 159.52831 | I27: 37.04 | J27: 0.2911 | K27: 91.736488 | L27: 241.80909 | M27: 23 | N27: 0.94270833 | O27: 0.52349037 | P27: 0.47650963 | Q27: 0.22936316 | R27: higher | S27: FALSE | U27: no | V27: 29.810331 | W27: standard | X27: ACT | Y27: 00-0034960
A28: 27 | B28: DJ Moore | C28: BUF | D28: WR | E28: 19.26 | F28: 84.85 | G28: =ROUND(100*((1-SETTINGS!$B$2)*N28+SETTINGS!$B$2*P28),2) | H28: 143.98793 | I28: 21.5 | J28: 0.169 | K28: 76.196107 | L28: 226.26871 | M28: 29 | N28: 0.92708333 | O28: 0.46595062 | P28: 0.53404938 | Q28: 0.28690291 | R28: higher | S28: FALSE | U28: no | V28: 29.383219 | W28: standard | X28: ACT | Y28: 00-0034827
A29: 28 | B29: DK Metcalf | C29: PIT | D29: WR | E29: 25.34 | F29: 84.49 | G29: =ROUND(100*((1-SETTINGS!$B$2)*N29+SETTINGS!$B$2*P29),2) | H29: 155.88554 | I29: 33.4 | J29: 0.2625 | K29: 88.093722 | L29: 238.16632 | M29: 24 | N29: 0.94010417 | O29: 0.53604805 | P29: 0.46395195 | Q29: 0.21680548 | R29: higher | S29: TRUE | T29: Questionable | U29: no | V29: 28.715168 | W29: standard | X29: ACT | Y29: 00-0035640
A30: 29 | B30: Brian Thomas Jr. | C30: JAX | D30: WR | E30: 13.05 | F30: 84.3 | G30: =ROUND(100*((1-SETTINGS!$B$2)*N30+SETTINGS!$B$2*P30),2) | H30: 134.66058 | I30: 12.18 | J30: 0.0957 | K30: 66.868761 | L30: 216.94136 | M30: 30 | N30: 0.92447917 | O30: 0.48292553 | P30: 0.51707447 | Q30: 0.269928 | R30: higher | S30: FALSE | U30: no | V30: 23.899191 | W30: standard | X30: ACT | Y30: 00-0039893
A31: 30 | B31: Troy Franklin | C31: DEN | D31: WR | E31: 12.48 | F31: 84.17 | G31: =ROUND(100*((1-SETTINGS!$B$2)*N31+SETTINGS!$B$2*P31),2) | H31: 133.61142 | I31: 11.13 | J31: 0.0875 | K31: 65.819596 | L31: 215.8922 | M31: 31 | N31: 0.921875 | O31: 0.47883094 | P31: 0.52116906 | Q31: 0.27402259 | R31: higher | S31: FALSE | U31: no | V31: 23.567904 | W31: standard | X31: ACT | Y31: 00-0039868
A32: 31 | B32: Ladd McConkey | C32: LAC | D32: WR | E32: 22.74 | F32: 84.16 | G32: =ROUND(100*((1-SETTINGS!$B$2)*N32+SETTINGS!$B$2*P32),2) | H32: 151.61636 | I32: 29.13 | J32: 0.2289 | K32: 83.824541 | L32: 233.89714 | M32: 26 | N32: 0.93489583 | O32: 0.53147609 | P32: 0.46852391 | Q32: 0.22137744 | R32: higher | S32: FALSE | U32: no | V32: 24.805437 | W32: standard | X32: ACT | Y32: 00-0039915
A33: 32 | B33: Luther Burden III | C33: CHI | D33: WR | E33: 8.54 | F33: 84.11 | G33: =ROUND(100*((1-SETTINGS!$B$2)*N33+SETTINGS!$B$2*P33),2) | H33: 126.7982 | I33: 4.31 | J33: 0.0339 | K33: 59.00638 | L33: 209.07898 | M33: 33 | N33: 0.91666667 | O33: 0.46122235 | P33: 0.53877765 | Q33: 0.29163118 | R33: higher | S33: TRUE | T33: Questionable | U33: no | V33: 22.721889 | W33: standard | X33: ACT | Y33: 00-0040735
A34: 33 | B34: Xavier Worthy | C34: KC | D34: WR | E34: 6.84 | F34: 83.96 | G34: =ROUND(100*((1-SETTINGS!$B$2)*N34+SETTINGS!$B$2*P34),2) | H34: 123.66165 | I34: 1.18 | J34: 0.0093 | K34: 55.86983 | L34: 205.94243 | M34: 35 | N34: 0.91145833 | O34: 0.44805948 | P34: 0.55194052 | Q34: 0.30479405 | R34: higher | S34: TRUE | T34: Questionable | U34: no | V34: 23.348871 | W34: standard | X34: ACT | Y34: 00-0039894
A35: 34 | B35: Romeo Doubs | C35: NE | D35: WR | E35: 5.72 | F35: 83.37 | G35: =ROUND(100*((1-SETTINGS!$B$2)*N35+SETTINGS!$B$2*P35),2) | H35: 122.48557 | I35: 0 | J35: 0 | K35: 54.693755 | L35: 204.76636 | M35: 36 | N35: 0.90885417 | O35: 0.46670226 | P35: 0.53329774 | Q35: 0.28615127 | R35: higher | S35: FALSE | U35: no | V35: 26.38521 | W35: standard | X35: ACT | Y35: 00-0037816
A36: 35 | B36: Jerry Jeudy | C36: CLE | D36: WR | E36: 6.75 | F36: 83.15 | G36: =ROUND(100*((1-SETTINGS!$B$2)*N36+SETTINGS!$B$2*P36),2) | H36: 111.60798 | I36: -10.88 | J36: 0 | K36: 43.81616 | L36: 193.88876 | M36: 42 | N36: 0.89322917 | O36: 0.41542488 | P36: 0.58457512 | Q36: 0.33742865 | R36: higher | S36: FALSE | U36: no | V36: 27.357166 | W36: standard | X36: ACT | Y36: 00-0036407
A37: 36 | B37: Chimere Dike | C37: TEN | D37: WR | E37: 6.95 | F37: 83.14 | G37: =ROUND(100*((1-SETTINGS!$B$2)*N37+SETTINGS!$B$2*P37),2) | H37: 107.45227 | I37: -15.03 | J37: 0 | K37: 39.660452 | L37: 189.73305 | M37: 43 | N37: 0.890625 | O37: 0.40546037 | P37: 0.59453963 | Q37: 0.34739316 | R37: higher | S37: FALSE | U37: no | V37: 24.715086 | W37: standard | X37: ACT | Y37: 00-0040705
A38: 37 | B38: Parker Washington | C38: JAX | D38: WR | E38: 9.52 | F38: 82.9 | G38: =ROUND(100*((1-SETTINGS!$B$2)*N38+SETTINGS!$B$2*P38),2) | H38: 130.59207 | I38: 8.11 | J38: 0.0637 | K38: 62.800251 | L38: 212.87285 | M38: 32 | N38: 0.91927083 | O38: 0.53184727 | P38: 0.46815273 | Q38: 0.22100626 | R38: higher | S38: FALSE | U38: no | V38: 24.449509 | W38: standard | X38: ACT | Y38: 00-0038606
A39: 38 | B39: Jordan Addison | C39: MIN | D39: WR | E39: 5.84 | F39: 82.87 | G39: =ROUND(100*((1-SETTINGS!$B$2)*N39+SETTINGS!$B$2*P39),2) | H39: 121.09536 | I39: -1.39 | J39: 0 | K39: 53.303544 | L39: 203.37614 | M39: 39 | N39: 0.90104167 | O39: 0.46066537 | P39: 0.53933463 | Q39: 0.29218816 | R39: higher | S39: TRUE | T39: Questionable | U39: no | V39: 24.594618 | W39: standard | X39: ACT | Y39: 00-0038994
A40: 39 | B40: Josh Downs | C40: IND | D40: WR | E40: 6.26 | F40: 82.87 | G40: =ROUND(100*((1-SETTINGS!$B$2)*N40+SETTINGS!$B$2*P40),2) | H40: 116.4892 | I40: -6 | J40: 0 | K40: 48.697382 | L40: 198.76998 | M40: 41 | N40: 0.89583333 | O40: 0.44004037 | P40: 0.55995963 | Q40: 0.31281316 | R40: higher | S40: TRUE | T40: Questionable | U40: no | V40: 25.054586 | W40: standard | X40: ACT | Y40: 00-0038997
A41: 40 | B41: Tre Tucker | C41: LV | D41: WR | E41: 5.17 | F41: 82.62 | G41: =ROUND(100*((1-SETTINGS!$B$2)*N41+SETTINGS!$B$2*P41),2) | H41: 122.39998 | I41: -0.09 | J41: 0 | K41: 54.608164 | L41: 204.68077 | M41: 37 | N41: 0.90625 | O41: 0.49417886 | P41: 0.50582114 | Q41: 0.25867467 | R41: higher | S41: FALSE | U41: no | V41: 25.484438 | W41: standard | X41: ACT | Y41: 00-0038563
A42: 41 | B42: Rome Odunze | C42: CHI | D42: WR | E42: 5.9 | F42: 82.31 | G42: =ROUND(100*((1-SETTINGS!$B$2)*N42+SETTINGS!$B$2*P42),2) | H42: 125.12179 | I42: 2.64 | J42: 0.0207 | K42: 57.329975 | L42: 207.40258 | M42: 34 | N42: 0.9140625 | O42: 0.54058636 | P42: 0.45941364 | Q42: 0.21226717 | R42: higher | S42: FALSE | U42: no | V42: 24.246904 | W42: standard | X42: ACT | Y42: 00-0039919
A43: 42 | B43: Rashee Rice | C43: KC | D43: WR | E43: 5.45 | F43: 82.27 | G43: =ROUND(100*((1-SETTINGS!$B$2)*N43+SETTINGS!$B$2*P43),2) | H43: 116.89046 | I43: -5.6 | J43: 0 | K43: 49.098644 | L43: 199.17125 | M43: 40 | N43: 0.8984375 | O43: 0.48034671 | P43: 0.51965329 | Q43: 0.27250682 | R43: higher | S43: FALSE | U43: no | V43: 26.360569 | W43: standard | X43: ACT | Y43: 00-0039067
A44: 43 | B44: Adonai Mitchell | C44: NYJ | D44: WR | E44: 7.59 | F44: 82.12 | G44: =ROUND(100*((1-SETTINGS!$B$2)*N44+SETTINGS!$B$2*P44),2) | H44: 94.164909 | I44: -28.32 | J44: 0 | K44: 26.37309 | L44: 176.44569 | M44: 51 | N44: 0.86979167 | O44: 0.37341186 | P44: 0.62658814 | Q44: 0.37944167 | R44: higher | S44: FALSE | U44: no | V44: 23.899191 | W44: standard | X44: ACT | Y44: 00-0039890
A45: 44 | B45: Rashid Shaheed | C45: SEA | D45: WR | E45: 7.16 | F45: 81.89 | G45: =ROUND(100*((1-SETTINGS!$B$2)*N45+SETTINGS!$B$2*P45),2) | H45: 94.659941 | I45: -27.83 | J45: 0 | K45: 26.868122 | L45: 176.94072 | M45: 50 | N45: 0.87239583 | O45: 0.39507826 | P45: 0.60492174 | Q45: 0.35777527 | R45: higher | S45: FALSE | U45: no | V45: 28.003313 | W45: standard | X45: ACT | Y45: 00-0037545
A46: 45 | B46: Jauan Jennings | C46: MIN | D46: WR | E46: 5.78 | F46: 81.56 | G46: =ROUND(100*((1-SETTINGS!$B$2)*N46+SETTINGS!$B$2*P46),2) | H46: 105.23649 | I46: -17.25 | J46: 0 | K46: 37.444673 | L46: 187.51727 | M46: 45 | N46: 0.88541667 | O46: 0.46389412 | P46: 0.53610588 | Q46: 0.28895941 | R46: higher | S46: FALSE | U46: no | V46: 29.14502 | W46: standard | X46: ACT | Y46: 00-0036259
A47: 46 | B47: Quentin Johnston | C47: LAC | D47: WR | E47: 4.23 | F47: 81.47 | G47: =ROUND(100*((1-SETTINGS!$B$2)*N47+SETTINGS!$B$2*P47),2) | H47: 121.53766 | I47: -0.95 | J47: 0 | K47: 53.74584 | L47: 203.81844 | M47: 38 | N47: 0.90364583 | O47: 0.54114946 | P47: 0.45885054 | Q47: 0.21170407 | R47: higher | S47: FALSE | U47: no | V47: 24.986139 | W47: standard | X47: ACT | Y47: 00-0038544
A48: 47 | B48: Jayden Higgins | C48: HOU | D48: WR | E48: 6.26 | F48: 81.41 | G48: =ROUND(100*((1-SETTINGS!$B$2)*N48+SETTINGS!$B$2*P48),2) | H48: 99.726518 | I48: -22.76 | J48: 0 | K48: 31.934699 | L48: 182.0073 | M48: 48 | N48: 0.87760417 | O48: 0.43968504 | P48: 0.56031496 | Q48: 0.31316849 | R48: higher | S48: FALSE | U48: no | V48: 23.713013 | W48: standard | X48: ACT | Y48: 00-0040130
A49: 48 | B49: Elic Ayomanor | C49: TEN | D49: WR | E49: 6.77 | F49: 80.46 | G49: =ROUND(100*((1-SETTINGS!$B$2)*N49+SETTINGS!$B$2*P49),2) | H49: 88.95969 | I49: -33.53 | J49: 0 | K49: 21.16787 | L49: 171.24047 | M49: 55 | N49: 0.859375 | O49: 0.41456848 | P49: 0.58543152 | Q49: 0.33828505 | R49: higher | S49: FALSE | U49: no | V49: 23.247568 | W49: standard | X49: ACT | Y49: 00-0040170
A50: 49 | B50: Malik Nabers | C50: NYG | D50: WR | E50: 4.31 | F50: 80.29 | G50: =ROUND(100*((1-SETTINGS!$B$2)*N50+SETTINGS!$B$2*P50),2) | H50: 106.42416 | I50: -16.06 | J50: 0 | K50: 38.632338 | L50: 188.70494 | M50: 44 | N50: 0.88802083 | O50: 0.53746725 | P50: 0.46253275 | Q50: 0.21538628 | R50: higher | S50: TRUE | T50: Questionable | U50: no | V50: 23.096983 | W50: standard | X50: ACT | Y50: 00-0039337
A51: 50 | B51: Ryan Flournoy | C51: DAL | D51: WR | E51: 5.31 | F51: 80.26 | G51: =ROUND(100*((1-SETTINGS!$B$2)*N51+SETTINGS!$B$2*P51),2) | H51: 95.481043 | I51: -27 | J51: 0 | K51: 27.689223 | L51: 177.76182 | M51: 49 | N51: 0.875 | O51: 0.4871615 | P51: 0.5128385 | Q51: 0.26569203 | R51: higher | S51: FALSE | U51: no | V51: 26.847916 | W51: standard | X51: ACT | Y51: 00-0039410
A52: 51 | B52: Odell Beckham Jr. | C52: NYG | D52: WR | E52: 12.91 | F52: 80.15 | G52: =ROUND(100*((1-SETTINGS!$B$2)*N52+SETTINGS!$B$2*P52),2) | H52: 63.634167 | I52: -58.85 | J52: 0 | K52: 0 | L52: 145.91495 | M52: 86 | N52: 0.77864583 | O52: 0.10711534 | P52: 0.89288466 | Q52: 0.64573819 | R52: lower | S52: FALSE | U52: no | V52: 33.821365 | W52: standard | X52: ACT | Y52: 00-0031235
A53: 52 | B53: Jayden Reed | C53: GB | D53: WR | E53: 6.56 | F53: 80.05 | G53: =ROUND(100*((1-SETTINGS!$B$2)*N53+SETTINGS!$B$2*P53),2) | H53: 88.469145 | I53: -34.02 | J53: 0 | K53: 20.677325 | L53: 170.74993 | M53: 56 | N53: 0.85677083 | O53: 0.42466922 | P53: 0.57533078 | Q53: 0.32818431 | R53: higher | S53: FALSE | U53: no | V53: 26.344141 | W53: standard | X53: ACT | Y53: 00-0039146
A54: 53 | B54: Dontayvion Wicks | C54: PHI | D54: WR | E54: 7.37 | F54: 80.02 | G54: =ROUND(100*((1-SETTINGS!$B$2)*N54+SETTINGS!$B$2*P54),2) | H54: 84.34818 | I54: -38.14 | J54: 0 | K54: 16.55636 | L54: 166.62896 | M54: 60 | N54: 0.84635417 | O54: 0.38445912 | P54: 0.61554088 | Q54: 0.36839441 | R54: higher | S54: FALSE | U54: no | V54: 25.210648 | W54: standard | X54: ACT | Y54: 00-0038393
A55: 54 | B55: Cooper Kupp | C55: SEA | D55: WR | E55: 6.86 | F55: 79.93 | G55: =ROUND(100*((1-SETTINGS!$B$2)*N55+SETTINGS!$B$2*P55),2) | H55: 86.603046 | I55: -35.88 | J55: 0 | K55: 18.811226 | L55: 168.88383 | M55: 58 | N55: 0.8515625 | O55: 0.4097187 | P55: 0.5902813 | Q55: 0.34313483 | R55: higher | S55: FALSE | U55: no | V55: 33.213551 | W55: standard | X55: ACT | Y55: 00-0033908
A56: 55 | B56: Jalen Coker | C56: CAR | D56: WR | E56: 6.98 | F56: 79.84 | G56: =ROUND(100*((1-SETTINGS!$B$2)*N56+SETTINGS!$B$2*P56),2) | H56: 84.956689 | I56: -37.53 | J56: 0 | K56: 17.164869 | L56: 167.23747 | M56: 59 | N56: 0.84895833 | O56: 0.40360446 | P56: 0.59639554 | Q56: 0.34924907 | R56: higher | S56: FALSE | U56: no | V56: 24.838293 | W56: standard | X56: ACT | Y56: 00-0039491
A57: 56 | B57: Garrett Wilson | C57: NYJ | D57: WR | E57: 4.24 | F57: 79.6 | G57: =ROUND(100*((1-SETTINGS!$B$2)*N57+SETTINGS!$B$2*P57),2) | H57: 101.81845 | I57: -20.67 | J57: 0 | K57: 34.026629 | L57: 184.09923 | M57: 47 | N57: 0.88020833 | O57: 0.54085287 | P57: 0.45914713 | Q57: 0.21200066 | R57: higher | S57: FALSE | U57: no | V57: 26.11142 | W57: standard | X57: ACT | Y57: 00-0037740
A58: 57 | B58: Tre Harris | C58: LAC | D58: WR | E58: 5.66 | F58: 79.56 | G58: =ROUND(100*((1-SETTINGS!$B$2)*N58+SETTINGS!$B$2*P58),2) | H58: 89.146946 | I58: -33.34 | J58: 0 | K58: 21.355127 | L58: 171.42773 | M58: 54 | N58: 0.86197917 | O58: 0.4699429 | P58: 0.5300571 | Q58: 0.28291063 | R58: higher | S58: FALSE | U58: no | V58: 24.507006 | W58: standard | X58: ACT | Y58: 00-0040727
A59: 58 | B59: DeMario Douglas | C59: NE | D59: WR | E59: 5.17 | F59: 79.49 | G59: =ROUND(100*((1-SETTINGS!$B$2)*N59+SETTINGS!$B$2*P59),2) | H59: 91.005339 | I59: -31.48 | J59: 0 | K59: 23.213519 | L59: 173.28612 | M59: 52 | N59: 0.8671875 | O59: 0.49421005 | P59: 0.50578995 | Q59: 0.25864348 | R59: higher | S59: FALSE | U59: no | V59: 25.73085 | W59: standard | X59: ACT | Y59: 00-0038621
A60: 59 | B60: Marvin Mims Jr. | C60: DEN | D60: WR | E60: 7.2 | F60: 79.44 | G60: =ROUND(100*((1-SETTINGS!$B$2)*N60+SETTINGS!$B$2*P60),2) | H60: 81.624733 | I60: -40.86 | J60: 0 | K60: 13.832913 | L60: 163.90551 | M60: 62 | N60: 0.84114583 | O60: 0.39279054 | P60: 0.60720946 | Q60: 0.36006299 | R60: higher | S60: TRUE | T60: Questionable | U60: no | V60: 24.454985 | W60: standard | X60: ACT | Y60: 00-0038976
A61: 60 | B61: Terry McLaurin | C61: WAS | D61: WR | E61: 5.89 | F61: 79.17 | G61: =ROUND(100*((1-SETTINGS!$B$2)*N61+SETTINGS!$B$2*P61),2) | H61: 88.202598 | I61: -34.28 | J61: 0 | K61: 20.410778 | L61: 170.48338 | M61: 57 | N61: 0.85416667 | O61: 0.4582958 | P61: 0.5417042 | Q61: 0.29455773 | R61: higher | S61: FALSE | U61: no | V61: 30.96299 | W61: standard | X61: ACT | Y61: 00-0035659
A62: 61 | B62: Mike Evans | C62: SF | D62: WR | E62: 7.17 | F62: 78.99 | G62: =ROUND(100*((1-SETTINGS!$B$2)*N62+SETTINGS!$B$2*P62),2) | H62: 78.947153 | I62: -43.54 | J62: 0 | K62: 11.155334 | L62: 161.22794 | M62: 64 | N62: 0.8359375 | O62: 0.39446323 | P62: 0.60553677 | Q62: 0.3583903 | R62: higher | S62: TRUE | T62: Questionable | U62: no | V62: 33.030109 | W62: standard | X62: ACT | Y62: 00-0031408
A63: 62 | B63: Christian Watson | C63: GB | D63: WR | E63: 4.79 | F63: 78.9 | G63: =ROUND(100*((1-SETTINGS!$B$2)*N63+SETTINGS!$B$2*P63),2) | H63: 90.047864 | I63: -32.44 | J63: 0 | K63: 22.256045 | L63: 172.32865 | M63: 53 | N63: 0.86458333 | O63: 0.51330005 | P63: 0.48669995 | Q63: 0.23955348 | R63: higher | S63: FALSE | U63: no | V63: 27.307884 | W63: standard | X63: ACT | Y63: 00-0038124
A64: 63 | B64: Calvin Ridley | C64: TEN | D64: WR | E64: 7.56 | F64: 78.75 | G64: =ROUND(100*((1-SETTINGS!$B$2)*N64+SETTINGS!$B$2*P64),2) | H64: 78.361288 | I64: -44.12 | J64: 0 | K64: 10.569468 | L64: 160.64207 | M64: 67 | N64: 0.828125 | O64: 0.37499869 | P64: 0.62500131 | Q64: 0.37785484 | R64: higher | S64: FALSE | U64: no | V64: 31.699488 | W64: standard | X64: ACT | Y64: 00-0034837
A65: 64 | B65: Malik Washington | C65: MIA | D65: WR | E65: 6.02 | F65: 78.46 | G65: =ROUND(100*((1-SETTINGS!$B$2)*N65+SETTINGS!$B$2*P65),2) | H65: 82.745353 | I65: -39.74 | J65: 0 | K65: 14.953533 | L65: 165.02613 | M65: 61 | N65: 0.84375 | O65: 0.45196017 | P65: 0.54803983 | Q65: 0.30089336 | R65: higher | S65: FALSE | U65: no | V65: 25.865007 | W65: standard | X65: ACT | Y65: 00-0039880
A66: 65 | B66: Ricky Pearsall | C66: SF | D66: WR | E66: 6.82 | F66: 78.43 | G66: =ROUND(100*((1-SETTINGS!$B$2)*N66+SETTINGS!$B$2*P66),2) | H66: 78.723969 | I66: -43.76 | J66: 0 | K66: 10.93215 | L66: 161.00475 | M66: 65 | N66: 0.83333333 | O66: 0.41189961 | P66: 0.58810039 | Q66: 0.34095392 | R66: higher | S66: TRUE | T66: IR | U66: no | V66: 25.977262 | W66: standard | X66: ACT | Y66: 00-0039916
A67: 66 | B67: Marvin Harrison Jr. | C67: AZ | D67: WR | E67: 2.77 | F67: 78.34 | G67: =ROUND(100*((1-SETTINGS!$B$2)*N67+SETTINGS!$B$2*P67),2) | H67: 104.15799 | I67: -18.33 | J67: 0 | K67: 36.366166 | L67: 186.43877 | M67: 46 | N67: 0.8828125 | O67: 0.61439411 | P67: 0.38560589 | Q67: 0.13845942 | R67: higher | S67: FALSE | U67: no | V67: 24.057989 | W67: standard | X67: ACT | Y67: 00-0039849
A68: 67 | B68: Kayshon Boutte | C68: NE | D68: WR | E68: 6.23 | F68: 78.26 | G68: =ROUND(100*((1-SETTINGS!$B$2)*N68+SETTINGS!$B$2*P68),2) | H68: 80.444759 | I68: -42.04 | J68: 0 | K68: 12.652939 | L68: 162.72554 | M68: 63 | N68: 0.83854167 | O68: 0.44138358 | P68: 0.55861642 | Q68: 0.31146995 | R68: higher | S68: FALSE | U68: no | V68: 24.320827 | W68: standard | X68: ACT | Y68: 00-0038608
A69: 68 | B69: Pat Bryant | C69: DEN | D69: WR | E69: 5.83 | F69: 77.23 | G69: =ROUND(100*((1-SETTINGS!$B$2)*N69+SETTINGS!$B$2*P69),2) | H69: 78.649999 | I69: -43.84 | J69: 0 | K69: 10.858179 | L69: 160.93078 | M69: 66 | N69: 0.83072917 | O69: 0.46139347 | P69: 0.53860653 | Q69: 0.29146006 | R69: higher | S69: FALSE | U69: no | V69: 23.726702 | W69: standard | X69: ACT | Y69: 00-0040134
A70: 69 | B70: Darnell Mooney | C70: NYG | D70: WR | E70: 6.88 | F70: 77.04 | G70: =ROUND(100*((1-SETTINGS!$B$2)*N70+SETTINGS!$B$2*P70),2) | H70: 73.405742 | I70: -49.08 | J70: 0 | K70: 5.6139226 | L70: 155.68652 | M70: 72 | N70: 0.81510417 | O70: 0.40862149 | P70: 0.59137851 | Q70: 0.34423204 | R70: higher | S70: FALSE | U70: no | V70: 28.841112 | W70: standard | X70: ACT | Y70: 00-0036309
A71: 70 | B71: Xavier Hutchinson | C71: HOU | D71: WR | E71: 6.47 | F71: 77.03 | G71: =ROUND(100*((1-SETTINGS!$B$2)*N71+SETTINGS!$B$2*P71),2) | H71: 74.281341 | I71: -48.2 | J71: 0 | K71: 6.4895215 | L71: 156.56212 | M71: 70 | N71: 0.8203125 | O71: 0.42950004 | P71: 0.57049996 | Q71: 0.32335349 | R71: higher | S71: FALSE | U71: no | V71: 26.251053 | W71: standard | X71: ACT | Y71: 00-0038618
A72: 71 | B72: KaVontae Turpin | C72: DAL | D72: WR | E72: 7.65 | F72: 76.97 | G72: =ROUND(100*((1-SETTINGS!$B$2)*N72+SETTINGS!$B$2*P72),2) | H72: 71.164476 | I72: -51.32 | J72: 0 | K72: 3.3726565 | L72: 153.44526 | M72: 76 | N72: 0.8046875 | O72: 0.37040974 | P72: 0.62959026 | Q72: 0.38244379 | R72: higher | S72: FALSE | U72: no | V72: 30.081385 | W72: standard | X72: ACT | Y72: 00-0037801
A73: 72 | B73: Calvin Austin III | C73: NYG | D73: WR | E73: 6.8 | F73: 76.53 | G73: =ROUND(100*((1-SETTINGS!$B$2)*N73+SETTINGS!$B$2*P73),2) | H73: 72.698048 | I73: -49.79 | J73: 0 | K73: 4.9062284 | L73: 154.97883 | M73: 74 | N73: 0.80989583 | O73: 0.41293139 | P73: 0.58706861 | Q73: 0.33992214 | R73: higher | S73: FALSE | U73: no | V73: 27.442041 | W73: standard | X73: ACT | Y73: 00-0037837
A74: 73 | B74: Chris Godwin Jr. | C74: TB | D74: WR | E74: 5.59 | F74: 75.95 | G74: =ROUND(100*((1-SETTINGS!$B$2)*N74+SETTINGS!$B$2*P74),2) | H74: 73.684155 | I74: -48.8 | J74: 0 | K74: 5.8923358 | L74: 155.96494 | M74: 71 | N74: 0.81770833 | O74: 0.47327401 | P74: 0.52672599 | Q74: 0.27957952 | R74: higher | S74: FALSE | U74: no | V74: 30.511236 | W74: standard | X74: ACT | Y74: 00-0033921
A75: 74 | B75: Olamide Zaccheaus | C75: ATL | D75: WR | E75: 8.93 | F75: 75.54 | G75: =ROUND(100*((1-SETTINGS!$B$2)*N75+SETTINGS!$B$2*P75),2) | H75: 57.935046 | I75: -64.55 | J75: 0 | K75: 0 | L75: 140.21583 | M75: 89 | N75: 0.77083333 | O75: 0.30647468 | P75: 0.69352532 | Q75: 0.44637884 | R75: moderate | S75: FALSE | U75: no | V75: 29.109426 | W75: standard | X75: ACT | Y75: 00-0035208
A76: 75 | B76: Andrei Iosivas | C76: CIN | D76: WR | E76: 4.72 | F76: 75.5 | G76: =ROUND(100*((1-SETTINGS!$B$2)*N76+SETTINGS!$B$2*P76),2) | H76: 75.168091 | I76: -47.32 | J76: 0 | K76: 7.3762715 | L76: 157.44887 | M76: 69 | N76: 0.82291667 | O76: 0.51667825 | P76: 0.48332175 | Q76: 0.23617528 | R76: higher | S76: FALSE | U76: no | V76: 26.880772 | W76: standard | X76: ACT | Y76: 00-0038619
A77: 76 | B77: Isaiah Bond | C77: CLE | D77: WR | E77: 6.81 | F77: 75.5 | G77: =ROUND(100*((1-SETTINGS!$B$2)*N77+SETTINGS!$B$2*P77),2) | H77: 69.162128 | I77: -53.32 | J77: 0 | K77: 1.3703087 | L77: 151.44291 | M77: 79 | N77: 0.796875 | O77: 0.41241002 | P77: 0.58758998 | Q77: 0.34044351 | R77: higher | S77: FALSE | U77: no | V77: 22.464527 | W77: standard | X77: ACT | Y77: 00-0040782
A78: 77 | B78: Xavier Legette | C78: CAR | D78: WR | E78: 6.53 | F78: 75.43 | G78: =ROUND(100*((1-SETTINGS!$B$2)*N78+SETTINGS!$B$2*P78),2) | H78: 69.543116 | I78: -52.94 | J78: 0 | K78: 1.7512966 | L78: 151.8239 | M78: 78 | N78: 0.79947917 | O78: 0.42632197 | P78: 0.57367803 | Q78: 0.32653156 | R78: higher | S78: FALSE | U78: no | V78: 25.588478 | W78: standard | X78: ACT | Y78: 00-0039342
... A90: 89 | B90: Jaylin Lane | C90: WAS | D90: WR | E90: 6.32 | F90: 73.34 | G90: =ROUND(100*((1-SETTINGS!$B$2)*N90+SETTINGS!$B$2*P90),2) | H90: 60.324569 | I90: -62.16 | J90: 0 | K90: 0 | L90: 142.60535 | M90: 87 | N90: 0.77604167 | O90: 0.4371006 | P90: 0.5628994 | Q90: 0.31575293 | R90: higher | S90: FALSE | U90: no | V90: 24.337255 | W90: standard | X90: ACT | Y90: 00-0040164
A91: 90 | B91: Tez Johnson | C91: TB | D91: WR | E91: 5.89 | F91: 73.33 | G91: =ROUND(100*((1-SETTINGS!$B$2)*N91+SETTINGS!$B$2*P91),2) | H91: 64.579933 | I91: -57.91 | J91: 0 | K91: 0 | L91: 146.86071 | M91: 85 | N91: 0.78125 | O91: 0.45836655 | P91: 0.54163345 | Q91: 0.29448698 | R91: higher | S91: TRUE | T91: Questionable | U91: no | V91: 24.29071 | W91: standard | X91: ACT | Y91: 00-0040237
A92: 91 | B92: Devaughn Vele | C92: NO | D92: WR | E92: 6.34 | F92: 73.15 | G92: =ROUND(100*((1-SETTINGS!$B$2)*N92+SETTINGS!$B$2*P92),2) | H92: 58.981435 | I92: -63.5 | J92: 0 | K92: 0 | L92: 141.26222 | M92: 88 | N92: 0.7734375 | O92: 0.43605837 | P92: 0.56394163 | Q92: 0.31679516 | R92: higher | S92: FALSE | U92: no | V92: 28.720644 | W92: standard | X92: ACT | Y92: 00-0039424
A93: 92 | B93: John Metchie III | C93: CAR | D93: WR | E93: 6.58 | F93: 72.98 | G93: =ROUND(100*((1-SETTINGS!$B$2)*N93+SETTINGS!$B$2*P93),2) | H93: 55.565048 | I93: -66.92 | J93: 0 | K93: 0 | L93: 137.84583 | M93: 90 | N93: 0.76822917 | O93: 0.423918 | P93: 0.576082 | Q93: 0.32893553 | R93: higher | S93: FALSE | U93: no | V93: 26.122372 | W93: standard | X93: ACT | Y93: 00-0037614
A94: 93 | B94: Josh Palmer | C94: BUF | D94: WR | E94: 7.18 | F94: 72.75 | G94: =ROUND(100*((1-SETTINGS!$B$2)*N94+SETTINGS!$B$2*P94),2) | H94: 54.095705 | I94: -68.39 | J94: 0 | K94: 0 | L94: 136.37649 | M94: 94 | N94: 0.7578125 | O94: 0.39381576 | P94: 0.60618424 | Q94: 0.35903777 | R94: higher | S94: FALSE | U94: no | V94: 26.943743 | W94: standard | X94: ACT | Y94: 00-0036988
A95: 94 | B95: Jalen Tolbert | C95: MIA | D95: WR | E95: 8.6 | F95: 72.71 | G95: =ROUND(100*((1-SETTINGS!$B$2)*N95+SETTINGS!$B$2*P95),2) | H95: 49.48744 | I95: -73 | J95: 0 | K95: 0 | L95: 131.76822 | M95: 101 | N95: 0.73958333 | O95: 0.32273114 | P95: 0.67726886 | Q95: 0.43012239 | R95: moderate | S95: FALSE | U95: no | V95: 27.51049 | W95: standard | X95: ACT | Y95: 00-0037666
A96: 95 | B96: Kendrick Bourne | C96: AZ | D96: WR | E96: 7.16 | F96: 72.52 | G96: =ROUND(100*((1-SETTINGS!$B$2)*N96+SETTINGS!$B$2*P96),2) | H96: 53.243332 | I96: -69.24 | J96: 0 | K96: 0 | L96: 135.52411 | M96: 95 | N96: 0.75520833 | O96: 0.3946453 | P96: 0.6053547 | Q96: 0.35820823 | R96: higher | S96: FALSE | U96: no | V96: 31.077982 | W96: standard | X96: ACT | Y96: 00-0033307
A97: 96 | B97: Tyquan Thornton | C97: KC | D97: WR | E97: 7.26 | F97: 72.41 | G97: =ROUND(100*((1-SETTINGS!$B$2)*N97+SETTINGS!$B$2*P97),2) | H97: 52.956364 | I97: -69.53 | J97: 0 | K97: 0 | L97: 135.23715 | M97: 96 | N97: 0.75260417 | O97: 0.38988749 | P97: 0.61011251 | Q97: 0.36296604 | R97: higher | S97: FALSE | U97: no | V97: 26.067612 | W97: standard | X97: ACT | Y97: 00-0038104
A98: 97 | B98: Greg Dortch | C98: DET | D98: WR | E98: 8.24 | F98: 72.14 | G98: =ROUND(100*((1-SETTINGS!$B$2)*N98+SETTINGS!$B$2*P98),2) | H98: 48.332615 | I98: -74.15 | J98: 0 | K98: 0 | L98: 130.6134 | M98: 102 | N98: 0.73697917 | O98: 0.34066728 | P98: 0.65933272 | Q98: 0.41218625 | R98: moderate | S98: FALSE | U98: no | V98: 28.260675 | W98: standard | X98: ACT | Y98: 00-0035500
A99: 98 | B99: Rashod Bateman | C99: BAL | D99: WR | E99: 7.77 | F99: 72.09 | G99: =ROUND(100*((1-SETTINGS!$B$2)*N99+SETTINGS!$B$2*P99),2) | H99: 49.649238 | I99: -72.84 | J99: 0 | K99: 0 | L99: 131.93002 | M99: 100 | N99: 0.7421875 | O99: 0.36410696 | P99: 0.63589304 | Q99: 0.38874657 | R99: higher | S99: FALSE | U99: no | V99: 26.757565 | W99: standard | X99: ACT | Y99: 00-0036550
A100: 99 | B100: Xavier Smith | C100: LA | D100: WR | E100: 8.4 | F100: 72.09 | G100: =ROUND(100*((1-SETTINGS!$B$2)*N100+SETTINGS!$B$2*P100),2) | H100: 47.712037 | I100: -74.77 | J100: 0 | K100: 0 | L100: 129.99282 | M100: 103 | N100: 0.734375 | O100: 0.33300899 | P100: 0.66699101 | Q100: 0.41984454 | R100: moderate | S100: FALSE | U100: no | V100: 28.945152 | W100: standard | X100: ACT | Y100: 00-0038359
A101: 100 | B101: Van Jefferson | C101: WAS | D101: WR | E101: 7.06 | F101: 72.01 | G101: =ROUND(100*((1-SETTINGS!$B$2)*N101+SETTINGS!$B$2*P101),2) | H101: 51.115257 | I101: -71.37 | J101: 0 | K101: 0 | L101: 133.39604 | M101: 97 | N101: 0.75 | O101: 0.39972345 | P101: 0.60027655 | Q101: 0.35313008 | R101: higher | S101: FALSE | U101: no | V101: 30.10055 | W101: standard | X101: ACT | Y101: 00-0036415
A102: 101 | B102: Tank Dell | C102: HOU | D102: WR | E102: 8.26 | F102: 71.75 | G102: =ROUND(100*((1-SETTINGS!$B$2)*N102+SETTINGS!$B$2*P102),2) | H102: 47.60331 | I102: -74.88 | J102: 0 | K102: 0 | L102: 129.88409 | M102: 104 | N102: 0.73177083 | O102: 0.3396493 | P102: 0.6603507 | Q102: 0.41320423 | R102: moderate | S102: TRUE | T102: Questionable | U102: no | V102: 26.84244 | W102: standard | X102: ACT | Y102: 00-0038977
A103: 102 | B103: Demarcus Robinson | C103: SF | D103: WR | E103: 8.98 | F103: 71.63 | G103: =ROUND(100*((1-SETTINGS!$B$2)*N103+SETTINGS!$B$2*P103),2) | H103: 44.140884 | I103: -78.34 | J103: 0 | K103: 0 | L103: 126.42167 | M103: 108 | N103: 0.72135417 | O103: 0.30373608 | P103: 0.69626392 | Q103: 0.44911745 | R103: moderate | S103: FALSE | U103: no | V103: 31.945898 | W103: standard | X103: ACT | Y103: 00-0032775
A104: 103 | B104: Marquise Brown | C104: PHI | D104: WR | E104: 5.83 | F104: 71.61 | G104: =ROUND(100*((1-SETTINGS!$B$2)*N104+SETTINGS!$B$2*P104),2) | H104: 54.321479 | I104: -68.16 | J104: 0 | K104: 0 | L104: 136.60226 | M104: 93 | N104: 0.76041667 | O104: 0.46131563 | P104: 0.53868437 | Q104: 0.2915379 | R104: higher | S104: FALSE | U104: no | V104: 29.243586 | W104: standard | X104: ACT | Y104: 00-0035662
A105: 104 | B105: Kyle Williams | C105: NE | D105: WR | E105: 5.38 | F105: 71.36 | G105: =ROUND(100*((1-SETTINGS!$B$2)*N105+SETTINGS!$B$2*P105),2) | H105: 54.423258 | I105: -68.06 | J105: 0 | K105: 0 | L105: 136.70404 | M105: 92 | N105: 0.76302083 | O105: 0.48398599 | P105: 0.51601401 | Q105: 0.26886754 | R105: higher | S105: FALSE | U105: no | V105: 23.800625 | W105: standard | X105: ACT | Y105: 00-0040131
A106: 105 | B106: Kalif Raymond | C106: CHI | D106: WR | E106: 9.04 | F106: 71.27 | G106: =ROUND(100*((1-SETTINGS!$B$2)*N106+SETTINGS!$B$2*P106),2) | H106: 43.107791 | I106: -79.38 | J106: 0 | K106: 0 | L106: 125.38857 | M106: 110 | N106: 0.71614583 | O106: 0.30106547 | P106: 0.69893453 | Q106: 0.45178806 | R106: moderate | S106: FALSE | U106: no | V106: 32.066368 | W106: standard | X106: ACT | Y106: 00-0032464
A107: 106 | B107: Christian Kirk | C107: SF | D107: WR | E107: 8.35 | F107: 71.21 | G107: =ROUND(100*((1-SETTINGS!$B$2)*N107+SETTINGS!$B$2*P107),2) | H107: 44.693752 | I107: -77.79 | J107: 0 | K107: 0 | L107: 126.97453 | M107: 107 | N107: 0.72395833 | O107: 0.3354732 | P107: 0.6645268 | Q107: 0.41738033 | R107: moderate | S107: TRUE | T107: Questionable | U107: no | V107: 29.78569 | W107: standard | X107: ACT | Y107: 00-0034775
A108: 107 | B108: Lil'Jordan Humphrey | C108: DEN | D108: WR | E108: 9.57 | F108: 70.56 | G108: =ROUND(100*((1-SETTINGS!$B$2)*N108+SETTINGS!$B$2*P108),2) | H108: 39.701487 | I108: -82.78 | J108: 0 | K108: 0 | L108: 121.98227 | M108: 116 | N108: 0.70052083 | O108: 0.27430453 | P108: 0.72569547 | Q108: 0.478549 | R108: moderate | S108: FALSE | U108: no | V108: 28.370192 | W108: standard | X108: ACT | Y108: 00-0035406
A109: 108 | B109: Elijah Moore | C109: PHI | D109: WR | E109: 9.9 | F109: 70.46 | G109: =ROUND(100*((1-SETTINGS!$B$2)*N109+SETTINGS!$B$2*P109),2) | H109: 37.633469 | I109: -84.85 | J109: 0 | K109: 0 | L109: 119.91425 | M109: 118 | N109: 0.6953125 | O109: 0.25802939 | P109: 0.74197061 | Q109: 0.49482414 | R109: moderate | S109: FALSE | U109: no | V109: 26.431755 | W109: standard | X109: ACT | Y109: 00-0036980
A110: 109 | B110: Cedric Tillman | C110: CLE | D110: WR | E110: 5.5 | F110: 70.23 | G110: =ROUND(100*((1-SETTINGS!$B$2)*N110+SETTINGS!$B$2*P110),2) | H110: 50.741808 | I110: -71.74 | J110: 0 | K110: 0 | L110: 133.02259 | M110: 98 | N110: 0.74739583 | O110: 0.47807683 | P110: 0.52192317 | Q110: 0.2747767 | R110: higher | S110: TRUE | T110: Questionable | U110: no | V110: 26.368782 | W110: standard | X110: ACT | Y110: 00-0038979
A111: 110 | B111: David Sills | C111: TB | D111: WR | E111: 8.66 | F111: 69.85 | G111: =ROUND(100*((1-SETTINGS!$B$2)*N111+SETTINGS!$B$2*P111),2) | H111: 39.877635 | I111: -82.61 | J111: 0 | K111: 0 | L111: 122.15842 | M111: 115 | N111: 0.703125 | O111: 0.31985461 | P111: 0.68014539 | Q111: 0.43299892 | R111: moderate | S111: FALSE | U111: no | V111: 31.261423 | W111: standard | X111: ACT | Y111: 00-0035359
...

Sheet TE
A1: Rank | B1: Player | C1: Team | D1: Pos | E1: Overall Draft Score (replacement-adjusted) | F1: Position Draft Score (default weight) | G1: Custom-Weight Score (weight from SETTINGS) | H1: Projected 2026 Points | I1: Points Over Replacement | J1: Overall Value (points over replacement / max) | K1: Points P10 | L1: Points P90 | M1: Pos Points Rank | N1: Pos Points Percentile | O1: Missed-Time Injury Probability | P1: Healthy Probability | Q1: Healthy Probability vs Position Mean (+0.5) | R1: Injury Risk Band | S1: Current Injury Listing (screen date) | T1: Current Listing Status | U1: Rookie | V1: Age | W1: Points Model Confidence | X1: Roster Status (Aug 9) | Y1: Player ID
A2: 1 | B2: Travis Kelce | C2: KC | D2: TE | E2: 32.04 | F2: 91.02 | G2: =ROUND(100*((1-SETTINGS!$B$2)*N2+SETTINGS!$B$2*P2),2) | H2: 162.60426 | I2: 37.68 | J2: 0.2961 | K2: 118.85341 | L2: 235.48148 | M2: 5 | N2: 0.97948718 | O2: 0.36695746 | P2: 0.63304254 | Q2: 0.41780439 | R2: higher | S2: FALSE | U2: no | V2: 36.906986 | W2: standard | X2: ACT | Y2: 00-0030506
A3: 2 | B3: Trey McBride | C3: AZ | D3: TE | E3: 70.59 | F3: 90.75 | G3: =ROUND(100*((1-SETTINGS!$B$2)*N3+SETTINGS!$B$2*P3),2) | H3: 226.95633 | I3: 102.03 | J3: 0.8018 | K3: 183.20548 | L3: 299.83355 | M3: 1 | N3: 1 | O3: 0.46235352 | P3: 0.53764648 | Q3: 0.32240833 | R3: higher | S3: FALSE | U3: no | V3: 26.77673 | W3: standard | X3: ACT | Y3: 00-0037744
A4: 3 | B4: Harold Fannin Jr. | C4: CLE | D4: TE | E4: 33.07 | F4: 89.22 | G4: =ROUND(100*((1-SETTINGS!$B$2)*N4+SETTINGS!$B$2*P4),2) | H4: 168.4083 | I4: 43.48 | J4: 0.3417 | K4: 124.65745 | L4: 241.28552 | M4: 3 | N4: 0.98974359 | O4: 0.49803494 | P4: 0.50196506 | Q4: 0.28672691 | R4: higher | S4: FALSE | U4: no | V4: 22.116814 | W4: standard | X4: ACT | Y4: 00-0040663
A5: 4 | B5: Kyle Pitts | C5: ATL | D5: TE | E5: 33 | F5: 89.2 | G5: =ROUND(100*((1-SETTINGS!$B$2)*N5+SETTINGS!$B$2*P5),2) | H5: 168.98125 | I5: 44.05 | J5: 0.3462 | K5: 125.23039 | L5: 241.85847 | M5: 2 | N5: 0.99487179 | O5: 0.51970839 | P5: 0.48029161 | Q5: 0.26505346 | R5: higher | S5: FALSE | U5: no | V5: 25.903337 | W5: standard | X5: ACT | Y5: 00-0036970
A6: 5 | B6: Tyler Warren | C6: IND | D6: TE | E6: 28.93 | F6: 88.31 | G6: =ROUND(100*((1-SETTINGS!$B$2)*N6+SETTINGS!$B$2*P6),2) | H6: 162.62031 | I6: 37.69 | J6: 0.2962 | K6: 118.86946 | L6: 235.49753 | M6: 4 | N6: 0.98461538 | O6: 0.52284604 | P6: 0.47715396 | Q6: 0.26191581 | R6: higher | S6: FALSE | U6: no | V6: 24.274284 | W6: standard | X6: ACT | Y6: 00-0040128
A7: 6 | B7: Colston Loveland | C7: CHI | D7: TE | E7: 14.98 | F7: 87.18 | G7: =ROUND(100*((1-SETTINGS!$B$2)*N7+SETTINGS!$B$2*P7),2) | H7: 138.96957 | I7: 14.04 | J7: 0.1103 | K7: 95.218715 | L7: 211.84679 | M7: 9 | N7: 0.95897436 | O7: 0.47700521 | P7: 0.52299479 | Q7: 0.30775664 | R7: higher | S7: FALSE | U7: no | V7: 22.39608 | W7: standard | X7: ACT | Y7: 00-0040126
A8: 7 | B8: Brock Bowers | C8: LV | D8: TE | E8: 17.88 | F8: 86.58 | G8: =ROUND(100*((1-SETTINGS!$B$2)*N8+SETTINGS!$B$2*P8),2) | H8: 146.4786 | I8: 21.55 | J8: 0.1694 | K8: 102.72775 | L8: 219.35582 | M8: 6 | N8: 0.97435897 | O8: 0.56835443 | P8: 0.43164557 | Q8: 0.21640742 | R8: higher | S8: FALSE | U8: no | V8: 23.718489 | W8: standard | X8: ACT | Y8: 00-0039338
A9: 8 | B9: Hunter Henry | C9: NE | D9: TE | E9: 11.03 | F9: 86.52 | G9: =ROUND(100*((1-SETTINGS!$B$2)*N9+SETTINGS!$B$2*P9),2) | H9: 132.43126 | I9: 7.5 | J9: 0.0589 | K9: 88.680404 | L9: 205.30848 | M9: 11 | N9: 0.94871795 | O9: 0.46901521 | P9: 0.53098479 | Q9: 0.31574664 | R9: higher | S9: FALSE | U9: no | V9: 31.735081 | W9: standard | X9: ACT | Y9: 00-0033090
A10: 9 | B10: George Kittle | C10: SF | D10: TE | E10: 10.02 | F10: 85.67 | G10: =ROUND(100*((1-SETTINGS!$B$2)*N10+SETTINGS!$B$2*P10),2) | H10: 132.81833 | I10: 7.89 | J10: 0.062 | K10: 89.067474 | L10: 205.69555 | M10: 10 | N10: 0.95384615 | O10: 0.53166694 | P10: 0.46833306 | Q10: 0.25309491 | R10: higher | S10: TRUE | T10: Out | U10: no | V10: 32.895954 | W10: standard | X10: ACT | Y10: 00-0033288
A11: 10 | B11: Tucker Kraft | C11: GB | D11: TE | E11: 15 | F11: 85.62 | G11: =ROUND(100*((1-SETTINGS!$B$2)*N11+SETTINGS!$B$2*P11),2) | H11: 142.77334 | I11: 17.84 | J11: 0.1402 | K11: 99.02249 | L11: 215.65056 | M11: 7 | N11: 0.96923077 | O11: 0.59579733 | P11: 0.40420267 | Q11: 0.18896452 | R11: higher | S11: TRUE | T11: Questionable | U11: no | V11: 25.826677 | W11: standard | X11: ACT | Y11: 00-0038996
A12: 11 | B12: Sam LaPorta | C12: DET | D12: TE | E12: 13.32 | F12: 85.17 | G12: =ROUND(100*((1-SETTINGS!$B$2)*N12+SETTINGS!$B$2*P12),2) | H12: 140.18927 | I12: 15.26 | J12: 0.1199 | K12: 96.438423 | L12: 213.06649 | M12: 8 | N12: 0.96410256 | O12: 0.59811736 | P12: 0.40188264 | Q12: 0.18664449 | R12: higher | S12: FALSE | U12: no | V12: 25.635023 | W12: standard | X12: ACT | Y12: 00-0039065
A13: 12 | B13: Dalton Schultz | C13: HOU | D13: TE | E13: 5.77 | F13: 85.15 | G13: =ROUND(100*((1-SETTINGS!$B$2)*N13+SETTINGS!$B$2*P13),2) | H13: 119.779 | I13: -5.15 | J13: 0 | K13: 76.028149 | L13: 192.65622 | M13: 13 | N13: 0.93846154 | O13: 0.49624791 | P13: 0.50375209 | Q13: 0.28851395 | R13: higher | S13: FALSE | U13: no | V13: 30.141619 | W13: standard | X13: ACT | Y13: 00-0034383
A14: 13 | B14: Juwan Johnson | C14: NO | D14: TE | E14: 5.27 | F14: 85.07 | G14: =ROUND(100*((1-SETTINGS!$B$2)*N14+SETTINGS!$B$2*P14),2) | H14: 124.92868 | I14: 0 | J14: 0 | K14: 81.177831 | L14: 197.8059 | M14: 12 | N14: 0.94358974 | O14: 0.52101397 | P14: 0.47898603 | Q14: 0.26374788 | R14: higher | S14: FALSE | U14: no | V14: 29.966393 | W14: standard | X14: ACT | Y14: 00-0036040
A15: 14 | B15: Chig Okonkwo | C15: WAS | D15: TE | E15: 7.13 | F15: 84.87 | G15: =ROUND(100*((1-SETTINGS!$B$2)*N15+SETTINGS!$B$2*P15),2) | H15: 108.57592 | I15: -16.35 | J15: 0 | K15: 64.825073 | L15: 181.45314 | M15: 17 | N15: 0.91794872 | O15: 0.42846828 | P15: 0.57153172 | Q15: 0.35629357 | R15: higher | S15: FALSE | U15: no | V15: 26.982073 | W15: standard | X15: ACT | Y15: 00-0037809
A16: 15 | B16: Oronde Gadsden II | C16: LAC | D16: TE | E16: 5.7 | F16: 84.67 | G16: =ROUND(100*((1-SETTINGS!$B$2)*N16+SETTINGS!$B$2*P16),2) | H16: 116.52509 | I16: -8.4 | J16: 0 | K16: 72.77424 | L16: 189.40231 | M16: 14 | N16: 0.93333333 | O16: 0.49970305 | P16: 0.50029695 | Q16: 0.2850588 | R16: higher | S16: FALSE | U16: no | V16: 23.187334 | W16: standard | X16: ACT | Y16: 00-0040189
A17: 16 | B17: Jake Ferguson | C17: DAL | D17: TE | E17: 5.54 | F17: 84.11 | G17: =ROUND(100*((1-SETTINGS!$B$2)*N17+SETTINGS!$B$2*P17),2) | H17: 111.93507 | I17: -12.99 | J17: 0 | K17: 68.184221 | L17: 184.81229 | M17: 15 | N17: 0.92820513 | O17: 0.50753765 | P17: 0.49246235 | Q17: 0.2772242 | R17: higher | S17: FALSE | U17: no | V17: 27.620007 | W17: standard | X17: ACT | Y17: 00-0038041
A18: 17 | B18: AJ Barner | C18: SEA | D18: TE | E18: 5.55 | F18: 83.7 | G18: =ROUND(100*((1-SETTINGS!$B$2)*N18+SETTINGS!$B$2*P18),2) | H18: 110.71646 | I18: -14.21 | J18: 0 | K18: 66.96561 | L18: 183.59368 | M18: 16 | N18: 0.92307692 | O18: 0.507384 | P18: 0.492616 | Q18: 0.27737786 | R18: higher | S18: FALSE | U18: no | V18: 24.331779 | W18: standard | X18: ACT | Y18: 00-0039793
A19: 18 | B19: Cade Otton | C19: TB | D19: TE | E19: 6.51 | F19: 83.43 | G19: =ROUND(100*((1-SETTINGS!$B$2)*N19+SETTINGS!$B$2*P19),2) | H19: 104.74664 | I19: -20.18 | J19: 0 | K19: 60.995793 | L19: 177.62386 | M19: 19 | N19: 0.90769231 | O19: 0.45920332 | P19: 0.54079668 | Q19: 0.32555853 | R19: higher | S19: FALSE | U19: no | V19: 27.381807 | W19: standard | X19: ACT | Y19: 00-0038129
A20: 19 | B20: Dallas Goedert | C20: PHI | D20: TE | E20: 5.33 | F20: 81.84 | G20: =ROUND(100*((1-SETTINGS!$B$2)*N20+SETTINGS!$B$2*P20),2) | H20: 96.001055 | I20: -28.93 | J20: 0 | K20: 52.250203 | L20: 168.87827 | M20: 20 | N20: 0.9025641 | O20: 0.51805684 | P20: 0.48194316 | Q20: 0.26670501 | R20: higher | S20: FALSE | U20: no | V20: 31.661156 | W20: standard | X20: ACT | Y20: 00-0034351
A21: 20 | B21: Dalton Kincaid | C21: BUF | D21: TE | E21: 5.46 | F21: 81.56 | G21: =ROUND(100*((1-SETTINGS!$B$2)*N21+SETTINGS!$B$2*P21),2) | H21: 91.376603 | I21: -33.55 | J21: 0 | K21: 47.625751 | L21: 164.25382 | M21: 21 | N21: 0.8974359 | O21: 0.51169606 | P21: 0.48830394 | Q21: 0.27306579 | R21: higher | S21: FALSE | U21: no | V21: 26.872557 | W21: standard | X21: ACT | Y21: 00-0038933
A22: 21 | B22: Mark Andrews | C22: BAL | D22: TE | E22: 7.38 | F22: 81.43 | G22: =ROUND(100*((1-SETTINGS!$B$2)*N22+SETTINGS!$B$2*P22),2) | H22: 79.065572 | I22: -45.86 | J22: 0 | K22: 35.31472 | L22: 151.94279 | M22: 26 | N22: 0.87179487 | O22: 0.41564221 | P22: 0.58435779 | Q22: 0.36911965 | R22: higher | S22: FALSE | U22: no | V22: 30.987631 | W22: standard | X22: ACT | Y22: 00-0034753
A23: 22 | B23: Brenton Strange | C23: JAX | D23: TE | E23: 4.03 | F23: 81.37 | G23: =ROUND(100*((1-SETTINGS!$B$2)*N23+SETTINGS!$B$2*P23),2) | H23: 108.33146 | I23: -16.6 | J23: 0 | K23: 64.580609 | L23: 181.20868 | M23: 18 | N23: 0.91282051 | O23: 0.58301964 | P23: 0.41698036 | Q23: 0.20174221 | R23: higher | S23: FALSE | U23: no | V23: 25.678829 | W23: standard | X23: ACT | Y23: 00-0038935
... A42: 41 | B42: Noah Fant | C42: NO | D42: TE | E42: 6.75 | F42: 74.64 | G42: =ROUND(100*((1-SETTINGS!$B$2)*N42+SETTINGS!$B$2*P42),2) | H42: 53.911756 | I42: -71.02 | J42: 0 | K42: 10.160904 | L42: 126.78898 | M42: 41 | N42: 0.79487179 | O42: 0.44734918 | P42: 0.55265082 | Q42: 0.33741268 | R42: higher | S42: FALSE | U42: no | V42: 28.780878 | W42: standard | X42: ACT | Y42: 00-0035644
A43: 42 | B43: Luke Musgrave | C43: GB | D43: TE | E43: 7.52 | F43: 74.19 | G43: =ROUND(100*((1-SETTINGS!$B$2)*N43+SETTINGS!$B$2*P43),2) | H43: 49.162885 | I43: -75.77 | J43: 0 | K43: 5.4120338 | L43: 122.04011 | M43: 44 | N43: 0.77948718 | O43: 0.40859316 | P43: 0.59140684 | Q43: 0.3761687 | R43: higher | S43: TRUE | T43: Out | U43: no | V43: 25.996428 | W43: standard | X43: ACT | Y43: 00-0039144
A44: 43 | B44: Dawson Knox | C44: BUF | D44: TE | E44: 5.29 | F44: 73.59 | G44: =ROUND(100*((1-SETTINGS!$B$2)*N44+SETTINGS!$B$2*P44),2) | H44: 56.836983 | I44: -68.09 | J44: 0 | K44: 13.086131 | L44: 129.7142 | M44: 40 | N44: 0.8 | O44: 0.52025319 | P44: 0.47974681 | Q44: 0.26450867 | R44: higher | S44: FALSE | U44: no | V44: 29.796642 | W44: standard | X44: ACT | Y44: 00-0035689
A45: 44 | B45: Noah Gray | C45: KC | D45: TE | E45: 8.46 | F45: 73.48 | G45: =ROUND(100*((1-SETTINGS!$B$2)*N45+SETTINGS!$B$2*P45),2) | H45: 45.097643 | I45: -79.83 | J45: 0 | K45: 1.3467915 | L45: 117.97486 | M45: 48 | N45: 0.75897436 | O45: 0.36193652 | P45: 0.63806348 | Q45: 0.42282533 | R45: higher | S45: FALSE | U45: no | V45: 27.34074 | W45: standard | X45: ACT | Y45: 00-0036637
A46: 45 | B46: Mitchell Evans | C46: CAR | D46: TE | E46: 6.07 | F46: 73.14 | G46: =ROUND(100*((1-SETTINGS!$B$2)*N46+SETTINGS!$B$2*P46),2) | H46: 50.764568 | I46: -74.16 | J46: 0 | K46: 7.0137163 | L46: 123.64179 | M46: 43 | N46: 0.78461538 | O46: 0.48130885 | P46: 0.51869115 | Q46: 0.303453 | R46: higher | S46: FALSE | U46: no | V46: 23.291374 | W46: standard | X46: ACT | Y46: 00-0040187
A47: 46 | B47: Davis Allen | C47: LA | D47: TE | E47: 6.68 | F47: 72.93 | G47: =ROUND(100*((1-SETTINGS!$B$2)*N47+SETTINGS!$B$2*P47),2) | H47: 48.363007 | I47: -76.57 | J47: 0 | K47: 4.6121554 | L47: 121.24023 | M47: 45 | N47: 0.77435897 | O47: 0.45080569 | P47: 0.54919431 | Q47: 0.33395617 | R47: higher | S47: TRUE | T47: Questionable | U47: no | V47: 25.574789 | W47: standard | X47: ACT | Y47: 00-0039074
A48: 47 | B48: Daniel Bellinger | C48: TEN | D48: TE | E48: 6.78 | F48: 72.62 | G48: =ROUND(100*((1-SETTINGS!$B$2)*N48+SETTINGS!$B$2*P48),2) | H48: 46.446662 | I48: -78.48 | J48: 0 | K48: 2.6958108 | L48: 119.32388 | M48: 46 | N48: 0.76923077 | O48: 0.44567677 | P48: 0.55432323 | Q48: 0.33908508 | R48: higher | S48: FALSE | U48: no | V48: 25.941669 | W48: standard | X48: ACT | Y48: 00-0038115
A49: 48 | B49: Adam Trautman | C49: DEN | D49: TE | E49: 7.8 | F49: 72 | G49: =ROUND(100*((1-SETTINGS!$B$2)*N49+SETTINGS!$B$2*P49),2) | H49: 44.385915 | I49: -80.54 | J49: 0 | K49: 0.6350629 | L49: 117.26313 | M49: 50 | N49: 0.74871795 | O49: 0.39480569 | P49: 0.60519431 | Q49: 0.38995617 | R49: higher | S49: FALSE | U49: no | V49: 29.569395 | W49: standard | X49: ACT | Y49: 00-0036422
A50: 49 | B50: Tanner Hudson | C50: CIN | D50: TE | E50: 11.06 | F50: 71.98 | G50: =ROUND(100*((1-SETTINGS!$B$2)*N50+SETTINGS!$B$2*P50),2) | H50: 31.066601 | I50: -93.86 | J50: 0 | K50: 0 | L50: 103.94382 | M50: 58 | N50: 0.70769231 | O50: 0.23190033 | P50: 0.76809967 | Q50: 0.55286152 | R50: moderate | S50: FALSE | U50: no | V50: 31.803528 | W50: standard | X50: ACT | Y50: 00-0034613
A51: 50 | B51: Austin Hooper | C51: ATL | D51: TE | E51: 8.39 | F51: 71.77 | G51: =ROUND(100*((1-SETTINGS!$B$2)*N51+SETTINGS!$B$2*P51),2) | H51: 42.566744 | I51: -82.36 | J51: 0 | K51: 0 | L51: 115.44396 | M51: 52 | N51: 0.73846154 | O51: 0.36528175 | P51: 0.63471825 | Q51: 0.4194801 | R51: higher | S51: FALSE | U51: no | V51: 31.841858 | W51: standard | X51: ACT | Y51: 00-0032392
A52: 51 | B52: Jackson Hawes | C52: BUF | D52: TE | E52: 5.79 | F52: 71.22 | G52: =ROUND(100*((1-SETTINGS!$B$2)*N52+SETTINGS!$B$2*P52),2) | H52: 46.344431 | I52: -78.58 | J52: 0 | K52: 2.5935791 | L52: 119.22165 | M52: 47 | N52: 0.76410256 | O52: 0.49543798 | P52: 0.50456202 | Q52: 0.28932387 | R52: higher | S52: FALSE | U52: no | V52: 25.736326 | W52: standard | X52: ACT | Y52: 00-0040194
A53: 52 | B53: Tommy Tremble | C53: CAR | D53: TE | E53: 6.58 | F53: 71.19 | G53: =ROUND(100*((1-SETTINGS!$B$2)*N53+SETTINGS!$B$2*P53),2) | H53: 44.980501 | I53: -79.95 | J53: 0 | K53: 1.2296496 | L53: 117.85772 | M53: 49 | N53: 0.75384615 | O53: 0.45593983 | P53: 0.54406017 | Q53: 0.32882202 | R53: higher | S53: FALSE | U53: no | V53: 26.248314 | W53: standard | X53: ACT | Y53: 00-0037005
A54: 53 | B54: Charlie Kolar | C54: LAC | D54: TE | E54: 8.89 | F54: 70.63 | G54: =ROUND(100*((1-SETTINGS!$B$2)*N54+SETTINGS!$B$2*P54),2) | H54: 36.867011 | I54: -88.06 | J54: 0 | K54: 0 | L54: 109.74423 | M54: 56 | N54: 0.71794872 | O54: 0.34030716 | P54: 0.65969284 | Q54: 0.44445469 | R54: moderate | S54: FALSE | U54: no | V54: 27.557034 | W54: standard | X54: ACT | Y54: 00-0038046
A55: 54 | B55: Josh Oliver | C55: MIN | D55: TE | E55: 8.28 | F55: 70.43 | G55: =ROUND(100*((1-SETTINGS!$B$2)*N55+SETTINGS!$B$2*P55),2) | H55: 37.803242 | I55: -87.13 | J55: 0 | K55: 0 | L55: 110.68046 | M55: 55 | N55: 0.72307692 | O55: 0.37085268 | P55: 0.62914732 | Q55: 0.41390918 | R55: higher | S55: FALSE | U55: no | V55: 29.448927 | W55: standard | X55: ACT | Y55: 00-0035249
A56: 55 | B56: Ja'Tavion Sanders | C56: CAR | D56: TE | E56: 6.58 | F56: 70.37 | G56: =ROUND(100*((1-SETTINGS!$B$2)*N56+SETTINGS!$B$2*P56),2) | H56: 42.926435 | I56: -82 | J56: 0 | K56: 0 | L56: 115.80366 | M56: 51 | N56: 0.74358974 | O56: 0.45593974 | P56: 0.54406026 | Q56: 0.32882212 | R56: higher | S56: FALSE | U56: no | V56: 23.433746 | W56: standard | X56: ACT | Y56: 00-0039356
A57: 56 | B57: Tyler Higbee | C57: LA | D57: TE | E57: 7.75 | F57: 70.31 | G57: =ROUND(100*((1-SETTINGS!$B$2)*N57+SETTINGS!$B$2*P57),2) | H57: 38.812141 | I57: -86.12 | J57: 0 | K57: 0 | L57: 111.68936 | M57: 54 | N57: 0.72820513 | O57: 0.39724856 | P57: 0.60275144 | Q57: 0.38751329 | R57: higher | S57: FALSE | U57: no | V57: 33.665306 | W57: standard | X57: ACT | Y57: 00-0033110
A58: 57 | B58: Luke Schoonmaker | C58: DAL | D58: TE | E58: 8.54 | F58: 69.87 | G58: =ROUND(100*((1-SETTINGS!$B$2)*N58+SETTINGS!$B$2*P58),2) | H58: 36.005473 | I58: -88.92 | J58: 0 | K58: 0 | L58: 108.88269 | M58: 57 | N58: 0.71282051 | O58: 0.35775226 | P58: 0.64224774 | Q58: 0.42700959 | R58: higher | S58: FALSE | U58: no | V58: 27.926651 | W58: standard | X58: ACT | Y58: 00-0038547
A59: 58 | B59: Jeremy Ruckert | C59: NYJ | D59: TE | E59: 6.67 | F59: 69.64 | G59: =ROUND(100*((1-SETTINGS!$B$2)*N59+SETTINGS!$B$2*P59),2) | H59: 40.600364 | I59: -84.33 | J59: 0 | K59: 0 | L59: 113.47758 | M59: 53 | N59: 0.73333333 | O59: 0.45112836 | P59: 0.54887164 | Q59: 0.33363349 | R59: higher | S59: FALSE | U59: no | V59: 26.056662 | W59: standard | X59: ACT | Y59: 00-0037805
A60: 59 | B60: John Bates | C60: WAS | D60: TE | E60: 9.3 | F60: 69.4 | G60: =ROUND(100*((1-SETTINGS!$B$2)*N60+SETTINGS!$B$2*P60),2) | H60: 27.022276 | I60: -97.91 | J60: 0 | K60: 0 | L60: 99.899496 | M60: 60 | N60: 0.6974359 | O60: 0.31987375 | P60: 0.68012625 | Q60: 0.4648881 | R60: moderate | S60: TRUE | T60: Questionable | U60: no | V60: 28.81921 | W60: standard | X60: ACT | Y60: 00-0036628
A61: 60 | B61: Drew Sample | C61: CIN | D61: TE | E61: 8.64 | F61: 69.15 | G61: =ROUND(100*((1-SETTINGS!$B$2)*N61+SETTINGS!$B$2*P61),2) | H61: 29.718517 | I61: -95.21 | J61: 0 | K61: 0 | L61: 102.59574 | M61: 59 | N61: 0.7025641 | O61: 0.35296995 | P61: 0.64703005 | Q61: 0.4317919 | R61: higher | S61: FALSE | U61: no | V61: 30.377079 | W61: standard | X61: ACT | Y61: 00-0035631
A62: 61 | B62: Mo Alie-Cox | C62: IND | D62: TE | E62: 11.14 | F62: 68.78 | G62: =ROUND(100*((1-SETTINGS!$B$2)*N62+SETTINGS!$B$2*P62),2) | H62: 22.085779 | I62: -102.84 | J62: 0 | K62: 7.9658542 | L62: 40.190542 | M62: 66 | N62: 0.66666667 | O62: 0.22775397 | P62: 0.77224603 | Q62: 0.55700788 | R62: moderate | S62: FALSE | U62: no | V62: 32.95071 | W62: standard | X62: ACT | Y62: 00-0033217
A63: 62 | B63: Tyler Conklin | C63: DET | D63: TE | E63: 10.35 | F63: 68.4 | G63: =ROUND(100*((1-SETTINGS!$B$2)*N63+SETTINGS!$B$2*P63),2) | H63: 23.159246 | I63: -101.77 | J63: 0 | K63: 9.0393208 | L63: 41.264009 | M63: 65 | N63: 0.67179487 | O63: 0.26737415 | P63: 0.73262585 | Q63: 0.5173877 | R63: moderate | S63: FALSE | U63: no | V63: 31.091673 | W63: standard | X63: ACT | Y63: 00-0034270
A64: 63 | B64: Brock Wright | C64: DET | D64: TE | E64: 9.8 | F64: 68.26 | G64: =ROUND(100*((1-SETTINGS!$B$2)*N64+SETTINGS!$B$2*P64),2) | H64: 23.635127 | I64: -101.29 | J64: 0 | K64: 9.5152022 | L64: 41.739891 | M64: 64 | N64: 0.67692308 | O64: 0.29472111 | P64: 0.70527889 | Q64: 0.49004074 | R64: moderate | S64: FALSE | U64: no | V64: 27.762377 | W64: standard | X64: ACT | Y64: 00-0036754
A65: 64 | B65: Julian Hill | C65: NE | D65: TE | E65: 8.62 | F65: 67.9 | G65: =ROUND(100*((1-SETTINGS!$B$2)*N65+SETTINGS!$B$2*P65),2) | H65: 26.818075 | I65: -98.11 | J65: 0 | K65: 0 | L65: 99.695295 | M65: 62 | N65: 0.68717949 | O65: 0.35357203 | P65: 0.64642797 | Q65: 0.43118982 | R65: higher | S65: TRUE | T65: IR | U65: no | V65: 26.147013 | W65: standard | X65: RES | Y65: 00-0038720
A66: 65 | B66: Connor Heyward | C66: LV | D66: TE | E66: 10.38 | F66: 67.6 | G66: =ROUND(100*((1-SETTINGS!$B$2)*N66+SETTINGS!$B$2*P66),2) | H66: 21.381063 | I66: -103.55 | J66: 0 | K66: 7.2611377 | L66: 39.485826 | M66: 67 | N66: 0.66153846 | O66: 0.26596336 | P66: 0.73403664 | Q66: 0.51879849 | R66: moderate | S66: FALSE | U66: no | V66: 27.609055 | W66: standard | X66: ACT | Y66: 00-0037304
A67: 66 | B67: Cade Stover | C67: HOU | D67: TE | E67: 8.28 | F67: 67.14 | G67: =ROUND(100*((1-SETTINGS!$B$2)*N67+SETTINGS!$B$2*P67),2) | H67: 25.478032 | I67: -99.45 | J67: 0 | K67: 11.358107 | L67: 43.582795 | M67: 63 | N67: 0.68205128 | O67: 0.37096806 | P67: 0.62903194 | Q67: 0.41379379 | R67: higher | S67: FALSE | U67: no | V67: 26.220936 | W67: standard | X67: ACT | Y67: 00-0039359
A68: 67 | B68: Ben Sinnott | C68: WAS | D68: TE | E68: 7.14 | F68: 66.83 | G68: =ROUND(100*((1-SETTINGS!$B$2)*N68+SETTINGS!$B$2*P68),2) | H68: 26.976195 | I68: -97.95 | J68: 0 | K68: 0 | L68: 99.853415 | M68: 61 | N68: 0.69230769 | O68: 0.42782293 | P68: 0.57217707 | Q68: 0.35693892 | R68: higher | S68: FALSE | U68: no | V68: 24.216787 | W68: standard | X68: ACT | Y68: 00-0039912
A69: 68 | B69: Luke Farrell | C69: SF | D69: TE | E69: 9.58 | F69: 66.4 | G69: =ROUND(100*((1-SETTINGS!$B$2)*N69+SETTINGS!$B$2*P69),2) | H69: 20.935426 | I69: -103.99 | J69: 0 | K69: 6.8155012 | L69: 39.04019 | M69: 68 | N69: 0.65641026 | O69: 0.30572722 | P69: 0.69427278 | Q69: 0.47903463 | R69: moderate | S69: FALSE | U69: no | V69: 28.882181 | W69: standard | X69: ACT | Y69: 00-0036887
A70: 69 | B70: Johnny Mundt | C70: PHI | D70: TE | E70: 11.12 | F70: 66.3 | G70: =ROUND(100*((1-SETTINGS!$B$2)*N70+SETTINGS!$B$2*P70),2) | H70: 19.51785 | I70: -105.41 | J70: 0 | K70: 5.397925 | L70: 37.622613 | M70: 72 | N70: 0.63589744 | O70: 0.22851528 | P70: 0.77148472 | Q70: 0.55624658 | R70: moderate | S70: FALSE | U70: no | V70: 31.773411 | W70: standard | X70: ACT | Y70: 00-0033246
A71: 70 | B71: Ian Thomas | C71: LV | D71: TE | E71: 9.79 | F71: 65.38 | G71: =ROUND(100*((1-SETTINGS!$B$2)*N71+SETTINGS!$B$2*P71),2) | H71: 19.757349 | I71: -105.17 | J71: 0 | K71: 5.6374239 | L71: 37.862112 | M71: 71 | N71: 0.64102564 | O71: 0.29517058 | P71: 0.70482942 | Q71: 0.48959127 | R71: moderate | S71: FALSE | U71: no | V71: 30.237446 | W71: standard | X71: ACT | Y71: 00-0034365
A72: 71 | B72: Grant Calcaterra | C72: PHI | D72: TE | E72: 8.15 | F72: 64.56 | G72: =ROUND(100*((1-SETTINGS!$B$2)*N72+SETTINGS!$B$2*P72),2) | H72: 20.871519 | I72: -104.06 | J72: 0 | K72: 6.7515942 | L72: 38.976282 | M72: 69 | N72: 0.65128205 | O72: 0.37714635 | P72: 0.62285365 | Q72: 0.4076155 | R72: higher | S72: FALSE | U72: no | V72: 27.743212 | W72: standard | X72: ACT | Y72: 00-0037086
A73: 72 | B73: Kylen Granson | C73: TEN | D73: TE | E73: 9.97 | F73: 63.92 | G73: =ROUND(100*((1-SETTINGS!$B$2)*N73+SETTINGS!$B$2*P73),2) | H73: 15.349475 | I73: -109.58 | J73: 0 | K73: 1.2295497 | L73: 33.454238 | M73: 75 | N73: 0.62051282 | O73: 0.28616406 | P73: 0.71383594 | Q73: 0.49859779 | R73: moderate | S73: FALSE | U73: no | V73: 28.433165 | W73: standard | X73: ACT | Y73: 00-0036876
A74: 73 | B74: Hunter Long | C74: JAX | D74: TE | E74: 9.11 | F74: 63.88 | G74: =ROUND(100*((1-SETTINGS!$B$2)*N74+SETTINGS!$B$2*P74),2) | H74: 18.697348 | I74: -106.23 | J74: 0 | K74: 4.5774224 | L74: 36.802111 | M74: 73 | N74: 0.63076923 | O74: 0.32901796 | P74: 0.67098204 | Q74: 0.45574389 | R74: moderate | S74: FALSE | U74: no | V74: 28.036167 | W74: standard | X74: ACT | Y74: 00-0037004
A75: 74 | B75: Brevyn Spann-Ford | C75: DAL | D75: TE | E75: 7.79 | F75: 63.78 | G75: =ROUND(100*((1-SETTINGS!$B$2)*N75+SETTINGS!$B$2*P75),2) | H75: 19.960059 | I75: -104.97 | J75: 0 | K75: 5.8401342 | L75: 38.064822 | M75: 70 | N75: 0.64615385 | O75: 0.39547439 | P75: 0.60452561 | Q75: 0.38928746 | R75: higher | S75: FALSE | U75: no | V75: 26.680904 | W75: standard | X75: ACT | Y75: 00-0039530
A76: 75 | B76: Foster Moreau | C76: HOU | D76: TE | E76: 9.35 | F76: 63.71 | G76: =ROUND(100*((1-SETTINGS!$B$2)*N76+SETTINGS!$B$2*P76),2) | H76: 16.680772 | I76: -108.25 | J76: 0 | K76: 2.5608472 | L76: 34.785536 | M76: 74 | N76: 0.62564103 | O76: 0.31727444 | P76: 0.68272556 | Q76: 0.46748742 | R76: moderate | S76: FALSE | U76: no | V76: 29.322985 | W76: standard | X76: ACT | Y76: 00-0034981
A77: 76 | B77: Charlie Woerner | C77: ATL | D77: TE | E77: 9.49 | F77: 63.02 | G77: =ROUND(100*((1-SETTINGS!$B$2)*N77+SETTINGS!$B$2*P77),2) | H77: 15.257944 | I77: -109.67 | J77: 0 | K77: 1.138019 | L77: 33.362707 | M77: 76 | N77: 0.61538462 | O77: 0.31048984 | P77: 0.68951016 | Q77: 0.47427202 | R77: moderate | S77: FALSE | U77: no | V77: 28.876705 | W77: standard | X77: ACT | Y77: 00-0036429
... A81: 80 | B81: Andrew Ogletree | C81: IND | D81: TE | E81: 9.72 | F81: 61.2 | G81: =ROUND(100*((1-SETTINGS!$B$2)*N81+SETTINGS!$B$2*P81),2) | H81: 11.248242 | I81: -113.68 | J81: 0 | K81: 0 | L81: 29.353005 | M81: 81 | N81: 0.58974359 | O81: 0.29893178 | P81: 0.70106822 | Q81: 0.48583007 | R81: moderate | S81: FALSE | U81: no | V81: 28.096401 | W81: standard | X81: ACT | Y81: 00-0037292
A82: 81 | B82: Tip Reiman | C82: AZ | D82: TE | E82: 8.06 | F82: 60.78 | G82: =ROUND(100*((1-SETTINGS!$B$2)*N82+SETTINGS!$B$2*P82),2) | H82: 12.538269 | I82: -112.39 | J82: 0 | K82: 0 | L82: 30.643032 | M82: 78 | N82: 0.60512821 | O82: 0.38153671 | P82: 0.61846329 | Q82: 0.40322514 | R82: higher | S82: TRUE | T82: Out | U82: no | V82: 24.956022 | W82: standard | X82: ACT | Y82: 00-0039737
A83: 82 | B83: Keleki Latu | C83: BUF | D83: TE | E83: 9.66 | F83: 60.33 | G83: =ROUND(100*((1-SETTINGS!$B$2)*N83+SETTINGS!$B$2*P83),2) | H83: 10.761193 | I83: -114.17 | J83: 0 | K83: 0 | L83: 28.865956 | M83: 83 | N83: 0.57948718 | O83: 0.30152442 | P83: 0.69847558 | Q83: 0.48323743 | R83: moderate | S83: FALSE | U83: no | V83: 24.052513 | W83: standard | X83: ACT | Y83: 00-0040363
A84: 83 | B84: Brenden Bates | C84: CLE | D84: TE | E84: 9.16 | F84: 60.23 | G84: =ROUND(100*((1-SETTINGS!$B$2)*N84+SETTINGS!$B$2*P84),2) | H84: 10.784697 | I84: -114.14 | J84: 0 | K84: 0 | L84: 28.889461 | M84: 82 | N84: 0.58461538 | O84: 0.32676056 | P84: 0.67323944 | Q84: 0.45800129 | R84: moderate | S84: FALSE | U84: no | V84: 26.878033 | W84: standard | X84: ACT | Y84: 00-0039458
A85: 84 | B85: Tanner Conner | C85: NYG | D85: TE | E85: 9.53 | F85: 59.79 | G85: =ROUND(100*((1-SETTINGS!$B$2)*N85+SETTINGS!$B$2*P85),2) | H85: 10.669298 | I85: -114.26 | J85: 0 | K85: 0 | L85: 28.774061 | M85: 84 | N85: 0.57435897 | O85: 0.30806498 | P85: 0.69193502 | Q85: 0.47669687 | R85: moderate | S85: FALSE | U85: no | V85: 28.45233 | W85: standard | X85: ACT | Y85: 00-0037348
A86: 85 | B86: Eric Saubert | C86: SEA | D86: TE | E86: 10.15 | F86: 59.58 | G86: =ROUND(100*((1-SETTINGS!$B$2)*N86+SETTINGS!$B$2*P86),2) | H86: 10.115405 | I86: -114.81 | J86: 0 | K86: 0 | L86: 28.220168 | M86: 86 | N86: 0.56410256 | O86: 0.27740767 | P86: 0.72259233 | Q86: 0.50735418 | R86: moderate | S86: FALSE | U86: no | V86: 32.315517 | W86: standard | X86: ACT | Y86: 00-0033576
A87: 86 | B87: Stone Smartt | C87: PHI | D87: TE | E87: 10.81 | F87: 59.42 | G87: =ROUND(100*((1-SETTINGS!$B$2)*N87+SETTINGS!$B$2*P87),2) | H87: 9.6203399 | I87: -115.31 | J87: 0 | K87: 0 | L87: 27.725103 | M87: 88 | N87: 0.55384615 | O87: 0.24413721 | P87: 0.75586279 | Q87: 0.54062464 | R87: moderate | S87: FALSE | U87: no | V87: 27.910225 | W87: standard | X87: ACT | Y87: 00-0037475
A88: 87 | B88: Cameron Latu | C88: PHI | D88: TE | E88: 12.41 | F88: 58.57 | G88: =ROUND(100*((1-SETTINGS!$B$2)*N88+SETTINGS!$B$2*P88),2) | H88: 9.028446 | I88: -115.9 | J88: 0 | K88: 0 | L88: 27.133209 | M88: 94 | N88: 0.52307692 | O88: 0.16401387 | P88: 0.83598613 | Q88: 0.62074799 | R88: lower | S88: FALSE | U88: no | V88: 26.519367 | W88: standard | X88: ACT | Y88: 00-0038564
A89: 88 | B89: Harrison Bryant | C89: SEA | D89: TE | E89: 10.75 | F89: 58.13 | G89: =ROUND(100*((1-SETTINGS!$B$2)*N89+SETTINGS!$B$2*P89),2) | H89: 9.260676 | I89: -115.67 | J89: 0 | K89: 0 | L89: 27.365439 | M89: 91 | N89: 0.53846154 | O89: 0.24721774 | P89: 0.75278226 | Q89: 0.53754411 | R89: moderate | S89: FALSE | U89: no | V89: 28.359241 | W89: standard | X89: ACT | Y89: 00-0036232
A90: 89 | B90: David Martin-Robinson | C90: TEN | D90: TE | E90: 8.09 | F90: 57.93 | G90: =ROUND(100*((1-SETTINGS!$B$2)*N90+SETTINGS!$B$2*P90),2) | H90: 10.182938 | I90: -114.75 | J90: 0 | K90: 0 | L90: 28.287701 | M90: 85 | N90: 0.56923077 | O90: 0.38027136 | P90: 0.61972864 | Q90: 0.40449049 | R90: higher | S90: FALSE | U90: no | V90: 26.683641 | W90: standard | X90: ACT | Y90: 00-0039648
A91: 90 | B91: Ben Sims | C91: MIA | D91: TE | E91: 9.65 | F91: 57.86 | G91: =ROUND(100*((1-SETTINGS!$B$2)*N91+SETTINGS!$B$2*P91),2) | H91: 9.2850271 | I91: -115.64 | J91: 0 | K91: 0 | L91: 27.38979 | M91: 89 | N91: 0.54871795 | O91: 0.30210084 | P91: 0.69789916 | Q91: 0.48266101 | R91: moderate | S91: TRUE | T91: Questionable | U91: no | V91: 26.294859 | W91: standard | X91: ACT | Y91: 00-0038809
A92: 91 | B92: Moliki Matavao | C92: NO | D92: TE | E92: 8.71 | F92: 57.73 | G92: =ROUND(100*((1-SETTINGS!$B$2)*N92+SETTINGS!$B$2*P92),2) | H92: 9.9346178 | I92: -114.99 | J92: 0 | K92: 0 | L92: 28.039381 | M92: 87 | N92: 0.55897436 | O92: 0.34932526 | P92: 0.65067474 | Q92: 0.4354366 | R92: moderate | S92: FALSE | U92: no | V92: 23.461124 | W92: standard | X92: ACT | Y92: 00-0040244
A93: 92 | B93: Durham Smythe | C93: BAL | D93: TE | E93: 9.89 | F93: 57.68 | G93: =ROUND(100*((1-SETTINGS!$B$2)*N93+SETTINGS!$B$2*P93),2) | H93: 9.2609017 | I93: -115.67 | J93: 0 | K93: 0 | L93: 27.365665 | M93: 90 | N93: 0.54358974 | O93: 0.29025778 | P93: 0.70974222 | Q93: 0.49450407 | R93: moderate | S93: FALSE | U93: no | V93: 31.064293 | W93: standard | X93: ACT | Y93: 00-0034798
A94: 93 | B94: Quintin Morris | C94: JAX | D94: TE | E94: 10.15 | F94: 57.12 | G94: =ROUND(100*((1-SETTINGS!$B$2)*N94+SETTINGS!$B$2*P94),2) | H94: 9.1907866 | I94: -115.74 | J94: 0 | K94: 0 | L94: 27.29555 | M94: 92 | N94: 0.53333333 | O94: 0.27729182 | P94: 0.72270818 | Q94: 0.50747003 | R94: moderate | S94: FALSE | U94: no | V94: 27.611792 | W94: standard | X94: ACT | Y94: 00-0036590
A95: 94 | B95: Albert Okwuegbunam | C95: LV | D95: TE | E95: 11.66 | F95: 56.99 | G95: =ROUND(100*((1-SETTINGS!$B$2)*N95+SETTINGS!$B$2*P95),2) | H95: 8.9064471 | I95: -116.02 | J95: 0 | K95: 0 | L95: 27.01121 | M95: 96 | N95: 0.51282051 | O95: 0.20193684 | P95: 0.79806316 | Q95: 0.58282502 | R95: moderate | S95: FALSE | U95: no | V95: 28.353765 | W95: standard | X95: ACT | Y95: 00-0036423
A96: 95 | B96: Carter Runyon | C96: LV | D96: TE | E96: 12.25 | F96: 55.94 | G96: =ROUND(100*((1-SETTINGS!$B$2)*N96+SETTINGS!$B$2*P96),2) | H96: 8.0204395 | I96: -116.91 | J96: 0 | K96: 0 | L96: 26.125203 | M96: 100 | N96: 0.49230769 | O96: 0.17217433 | P96: 0.82782567 | Q96: 0.61258752 | R96: lower | S96: FALSE | U96: no | V96: 25.109344 | W96: standard | X96: ACT | Y96: 00-0040488
A97: 96 | B97: Devin Culp | C97: TB | D97: TE | E97: 8.99 | F97: 55.55 | G97: =ROUND(100*((1-SETTINGS!$B$2)*N97+SETTINGS!$B$2*P97),2) | H97: 9.058902 | I97: -115.87 | J97: 0 | K97: 0 | L97: 27.163665 | M97: 93 | N97: 0.52820513 | O97: 0.33548998 | P97: 0.66451002 | Q97: 0.44927188 | R97: moderate | S97: FALSE | U97: no | V97: 26.579601 | W97: standard | X97: ACT | Y97: 00-0039754
A98: 97 | B98: Teagan Quitoriano | C98: AZ | D98: TE | E98: 13.53 | F98: 55.17 | G98: =ROUND(100*((1-SETTINGS!$B$2)*N98+SETTINGS!$B$2*P98),2) | H98: 7.1389691 | I98: -117.79 | J98: 0 | K98: 0 | L98: 25.243732 | M98: 105 | N98: 0.46666667 | O98: 0.1082968 | P98: 0.8917032 | Q98: 0.67646506 | R98: lower | S98: FALSE | U98: no | V98: 26.464609 | W98: standard | X98: ACT | Y98: 00-0037277
A99: 98 | B99: Blake Whiteheart | C99: CLE | D99: TE | E99: 9.14 | F99: 54.88 | G99: =ROUND(100*((1-SETTINGS!$B$2)*N99+SETTINGS!$B$2*P99),2) | H99: 9.0044364 | I99: -115.92 | J99: 0 | K99: 0 | L99: 27.1092 | M99: 95 | N99: 0.51794872 | O99: 0.32768161 | P99: 0.67231839 | Q99: 0.45708024 | R99: moderate | S99: FALSE | U99: no | V99: 26.445444 | W99: standard | X99: ACT | Y99: 00-0038710
A100: 99 | B100: James Mitchell | C100: CAR | D100: TE | E100: 11.68 | F100: 54.55 | G100: =ROUND(100*((1-SETTINGS!$B$2)*N100+SETTINGS!$B$2*P100),2) | H100: 7.8395233 | I100: -117.09 | J100: 0 | K100: 0 | L100: 25.944286 | M100: 102 | N100: 0.48205128 | O100: 0.20070064 | P100: 0.79929936 | Q100: 0.58406121 | R100: moderate | S100: FALSE | U100: no | V100: 27.058735 | W100: standard | X100: ACT | Y100: 00-0037282
A101: 100 | B101: Anthony Firkser | C101: WAS | D101: TE | E101: 12.05 | F101: 54.1 | G101: =ROUND(100*((1-SETTINGS!$B$2)*N101+SETTINGS!$B$2*P101),2) | H101: 7.5605229 | I101: -117.37 | J101: 0 | K101: 0 | L101: 25.665286 | M101: 104 | N101: 0.47179487 | O101: 0.18222137 | P101: 0.81777863 | Q101: 0.60254048 | R101: lower | S101: FALSE | U101: no | V101: 31.532475 | W101: standard | X101: ACT | Y101: 00-0033455
A102: 101 | B102: Ben Yurosek | C102: MIN | D102: TE | E102: 9.44 | F102: 53.95 | G102: =ROUND(100*((1-SETTINGS!$B$2)*N102+SETTINGS!$B$2*P102),2) | H102: 8.3623923 | I102: -116.57 | J102: 0 | K102: 0 | L102: 26.467155 | M102: 98 | N102: 0.5025641 | O102: 0.31257162 | P102: 0.68742838 | Q102: 0.47219023 | R102: moderate | S102: FALSE | U102: no | V102: 24.460461 | W102: standard | X102: ACT | Y102: 00-0040509
A103: 102 | B103: Jack Stoll | C103: CLE | D103: TE | E103: 9.4 | F103: 53.5 | G103: =ROUND(100*((1-SETTINGS!$B$2)*N103+SETTINGS!$B$2*P103),2) | H103: 8.1554169 | I103: -116.77 | J103: 0 | K103: 0 | L103: 26.26018 | M103: 99 | N103: 0.4974359 | O103: 0.31477771 | P103: 0.68522229 | Q103: 0.46998414 | R103: moderate | S103: FALSE | U103: no | V103: 28.591963 | W103: standard | X103: ACT | Y103: 00-0036741
... A110: 109 | B110: Cam Grandy | C110: CIN | D110: TE | E110: 12.25 | F110: 51.84 | G110: =ROUND(100*((1-SETTINGS!$B$2)*N110+SETTINGS!$B$2*P110),2) | H110: 6.8399155 | I110: -118.09 | J110: 0 | K110: 0 | L110: 24.944679 | M110: 110 | N110: 0.44102564 | O110: 0.17205093 | P110: 0.82794907 | Q110: 0.61271092 | R110: lower | S110: FALSE | U110: no | V110: 26.784945 | W110: standard | X110: ACT | Y110: 00-0039631
A111: 110 | B111: Gavin Bartholomew | C111: MIN | D111: TE | E111: 10.44 | F111: 51.67 | G111: =ROUND(100*((1-SETTINGS!$B$2)*N111+SETTINGS!$B$2*P111),2) | H111: 7.0958523 | I111: -117.83 | J111: 0 | K111: 0 | L111: 25.200615 | M111: 106 | N111: 0.46153846 | O111: 0.2627152 | P111: 0.7372848 | Q111: 0.52204665 | R111: moderate | S111: TRUE | T111: Questionable | U111: no | V111: 23.340658 | W111: standard | X111: ACT | Y111: 00-0040215
A112: 111 | B112: Ko Kieft | C112: TB | D112: TE | E112: 12.22 | F112: 51.4 | G112: =ROUND(100*((1-SETTINGS!$B$2)*N112+SETTINGS!$B$2*P112),2) | H112: 6.6750849 | I112: -118.25 | J112: 0 | K112: 0 | L112: 24.779848 | M112: 111 | N112: 0.43589744 | O112: 0.1737694 | P112: 0.8262306 | Q112: 0.61099245 | R112: lower | S112: FALSE | U112: no | V112: 28.613867 | W112: standard | X112: ACT | Y112: 00-0037311
A113: 112 | B113: Shane Zylstra | C113: BUF | D113: TE | E113: 11.81 | F113: 49.75 | G113: =ROUND(100*((1-SETTINGS!$B$2)*N113+SETTINGS!$B$2*P113),2) | H113: 6.1307762 | I113: -118.8 | J113: 0 | K113: 0 | L113: 24.235539 | M113: 114 | N113: 0.42051282 | O113: 0.19439561 | P113: 0.80560439 | Q113: 0.59036624 | R113: lower | S113: FALSE | U113: no | V113: 29.791166 | W113: standard | X113: ACT | Y113: 00-0036534
A114: 113 | B114: Brevin Jordan | C114: HOU | D114: TE | E114: 13.27 | F114: 49.58 | G114: =ROUND(100*((1-SETTINGS!$B$2)*N114+SETTINGS!$B$2*P114),2) | H114: 5.5404718 | I114: -119.39 | J114: 0 | K114: 0 | L114: 23.645235 | M114: 118 | N114: 0.4 | O114: 0.12123771 | P114: 0.87876229 | Q114: 0.66352414 | R114: lower | S114: TRUE | T114: Questionable | U114: no | V114: 26.127846 | W114: standard | X114: ACT | Y114: 00-0036556
A115: 114 | B115: Lucas Krull | C115: DEN | D115: TE | E115: 12.09 | F115: 48.81 | G115: =ROUND(100*((1-SETTINGS!$B$2)*N115+SETTINGS!$B$2*P115),2) | H115: 5.736222 | I115: -119.19 | J115: 0 | K115: 0 | L115: 23.840985 | M115: 117 | N115: 0.40512821 | O115: 0.1802573 | P115: 0.8197427 | Q115: 0.60450455 | R115: lower | S115: FALSE | U115: no | V115: 28.142946 | W115: standard | X115: ACT | Y115: 00-0037539
A116: 115 | B116: Nick Kallerup | C116: SEA | D116: TE | E116: 11.5 | F116: 48.62 | G116: =ROUND(100*((1-SETTINGS!$B$2)*N116+SETTINGS!$B$2*P116),2) | H116: 5.7786693 | I116: -119.15 | J116: 0 | K116: 0 | L116: 23.883432 | M116: 116 | N116: 0.41025641 | O116: 0.20995683 | P116: 0.79004317 | Q116: 0.57480502 | R116: moderate | S116: FALSE | U116: no | V116: 25.432419 | W116: standard | X116: ACT | Y116: 00-0040058
A117: 116 | B117: Will Mallory | C117: IND | D117: TE | E117: 9.71 | F117: 48.48 | G117: =ROUND(100*((1-SETTINGS!$B$2)*N117+SETTINGS!$B$2*P117),2) | H117: 6.3534427 | I117: -118.58 | J117: 0 | K117: 0 | L117: 24.458206 | M117: 112 | N117: 0.43076923 | O117: 0.29913885 | P117: 0.70086115 | Q117: 0.485623 | R117: moderate | S117: FALSE | U117: no | V117: 27.195631 | W117: standard | X117: ACT | Y117: 00-0038394
A118: 117 | B118: Erick All | C118: CIN | D118: TE | E118: 10.13 | F118: 48.48 | G118: =ROUND(100*((1-SETTINGS!$B$2)*N118+SETTINGS!$B$2*P118),2) | H118: 6.3159483 | I118: -118.61 | J118: 0 | K118: 0 | L118: 24.420711 | M118: 113 | N118: 0.42564103 | O118: 0.27839381 | P118: 0.72160619 | Q118: 0.50636804 | R118: moderate | S118: FALSE | U118: no | V118: 25.966311 | W118: standard | X118: ACT | Y118: 00-0039814
A119: 118 | B119: Chris Manhertz | C119: NYG | D119: TE | E119: 12.2 | F119: 48.1 | G119: =ROUND(100*((1-SETTINGS!$B$2)*N119+SETTINGS!$B$2*P119),2) | H119: 5.4470609 | I119: -119.48 | J119: 0 | K119: 0 | L119: 23.551824 | M119: 119 | N119: 0.39487179 | O119: 0.17452458 | P119: 0.82547542 | Q119: 0.61023727 | R119: lower | S119: FALSE | U119: no | V119: 34.393589 | W119: standard | X119: ACT | Y119: 00-0031484
A120: 119 | B120: Feleipe Franks | C120: CAR | D120: TE | E120: 9.92 | F120: 47.46 | G120: =ROUND(100*((1-SETTINGS!$B$2)*N120+SETTINGS!$B$2*P120),2) | H120: 5.9264396 | I120: -119 | J120: 0 | K120: 0 | L120: 24.031203 | M120: 115 | N120: 0.41538462 | O120: 0.28866389 | P120: 0.71133611 | Q120: 0.49609796 | R120: moderate | S120: FALSE | U120: no | V120: 28.693266 | W120: standard | X120: ACT | Y120: 00-0036825
A121: 120 | B121: Zaire Mitchell-Paden | C121: NO | D121: TE | E121: 11.62 | F121: 47.1 | G121: =ROUND(100*((1-SETTINGS!$B$2)*N121+SETTINGS!$B$2*P121),2) | H121: 5.2126748 | I121: -119.72 | J121: 0 | K121: 0 | L121: 23.317438 | M121: 120 | N121: 0.38974359 | O121: 0.20375377 | P121: 0.79624623 | Q121: 0.58100808 | R121: moderate | S121: FALSE | U121: no | V121: 27.034094 | W121: standard | X121: ACT | Y121: 00-0037340
A122: 121 | B122: Kenyon Sadiq | C122: NYJ | D122: TE | E122: 11.88 | F122: 46.54 | G122: =ROUND(100*((1-SETTINGS!$B$2)*N122+SETTINGS!$B$2*P122),2) | H122: 5.0825721 | I122: -119.85 | J122: 0 | K122: 0 | L122: 23.187335 | M122: 122 | N122: 0.37948718 | O122: 0.19077229 | P122: 0.80922771 | Q122: 0.59398956 | R122: lower | S122: TRUE | T122: Questionable | U122: yes | V122: 21.495308 | W122: standard | X122: ACT | Y122: 00-0041032
A123: 122 | B123: Eli Stowers | C123: PHI | D123: TE | E123: 12.03 | F123: 46.28 | G123: =ROUND(100*((1-SETTINGS!$B$2)*N123+SETTINGS!$B$2*P123),2) | H123: 4.6044738 | I123: -120.32 | J123: 0 | K123: 0 | L123: 22.709237 | M123: 123 | N123: 0.37435897 | O123: 0.18339195 | P123: 0.81660805 | Q123: 0.6013699 | R123: lower | S123: FALSE | U123: yes | V123: 23.381725 | W123: standard | X123: ACT | Y123: 00-0041483
A124: 123 | B124: Riley Nowakowski | C124: PIT | D124: TE | E124: 12.06 | F124: 45.91 | G124: =ROUND(100*((1-SETTINGS!$B$2)*N124+SETTINGS!$B$2*P124),2) | H124: 4.4277794 | I124: -120.5 | J124: 0 | K124: 0 | L124: 22.532543 | M124: 124 | N124: 0.36923077 | O124: 0.18151447 | P124: 0.81848553 | Q124: 0.60324738 | R124: lower | S124: FALSE | U124: yes | V124: 24.172981 | W124: standard | X124: ACT | Y124: 00-0041398
A125: 124 | B125: Robert Tonyan | C125: PIT | D125: TE | E125: 13.9 | F125: 45.69 | G125: =ROUND(100*((1-SETTINGS!$B$2)*N125+SETTINGS!$B$2*P125),2) | H125: 4.0717495 | I125: -120.86 | J125: 0 | K125: 0 | L125: 22.176513 | M125: 129 | N125: 0.34358974 | O125: 0.089966641 | P125: 0.91003336 | Q125: 0.69479521 | R125: lower | S125: FALSE | U125: no | V125: 32.340157 | W125: standard | X125: ACT | Y125: 00-0033757
A126: 125 | B126: R.J. Maryland | C126: GB | D126: TE | E126: 11.97 | F126: 45.41 | G126: =ROUND(100*((1-SETTINGS!$B$2)*N126+SETTINGS!$B$2*P126),2) | H126: 4.4118725 | I126: -120.52 | J126: 0 | K126: 0 | L126: 22.516636 | M126: 125 | N126: 0.36410256 | O126: 0.18610546 | P126: 0.81389454 | Q126: 0.5986564 | R126: lower | S126: TRUE | T126: Questionable | U126: yes | V126: 22.146931 | W126: standard | X126: ACT | Y126: 00-0040945
A127: 126 | B127: Caleb Lohner | C127: DEN | D127: TE | E127: 10.28 | F127: 45.35 | G127: =ROUND(100*((1-SETTINGS!$B$2)*N127+SETTINGS!$B$2*P127),2) | H127: 5.1064964 | I127: -119.82 | J127: 0 | K127: 0 | L127: 23.21126 | M127: 121 | N127: 0.38461538 | O127: 0.27083989 | P127: 0.72916011 | Q127: 0.51392197 | R127: moderate | S127: TRUE | T127: Questionable | U127: no | V127: 24.917692 | W127: standard | X127: ACT | Y127: 00-0040240
...

Sheet K
A1: Rank | B1: Player | C1: Team | D1: Pos | E1: Overall Draft Score (replacement-adjusted) | F1: Position Draft Score (default weight) | G1: Custom-Weight Score (weight from SETTINGS) | H1: Projected 2026 Points | I1: Points Over Replacement | J1: Overall Value (points over replacement / max) | K1: Points P10 | L1: Points P90 | M1: Pos Points Rank | N1: Pos Points Percentile | O1: Missed-Time Injury Probability | P1: Healthy Probability | Q1: Healthy Probability vs Position Mean (+0.5) | R1: Injury Risk Band | S1: Current Injury Listing (screen date) | T1: Current Listing Status | U1: Rookie | V1: Age | W1: Points Model Confidence | X1: Roster Status (Aug 9) | Y1: Player ID
A2: 1 | B2: Cameron Dicker | C2: LAC | D2: K | E2: 25.71 | F2: 97.65 | G2: =ROUND(100*((1-SETTINGS!$B$2)*N2+SETTINGS!$B$2*P2),2) | H2: 141.69836 | I2: 24.49 | J2: 0.1925 | K2: 49.200332 | L2: 182.32159 | M2: 1 | N2: 1 | O2: 0.11754744 | P2: 0.88245256 | Q2: 0.51546774 | R2: lower | S2: FALSE | U2: no | V2: 26.322237 | W2: low (kicker) | X2: ACT | Y2: 00-0037224
A3: 2 | B3: Ka'imi Fairbairn | C3: HOU | D3: K | E3: 22.42 | F3: 95.44 | G3: =ROUND(100*((1-SETTINGS!$B$2)*N3+SETTINGS!$B$2*P3),2) | H3: 137.02056 | I3: 19.81 | J3: 0.1557 | K3: 44.522534 | L3: 177.6438 | M3: 2 | N3: 0.97674419 | O3: 0.13479602 | P3: 0.86520398 | Q3: 0.49821916 | R3: lower | S3: FALSE | U3: no | V3: 32.589306 | W3: low (kicker) | X3: ACT | Y3: 00-0032726
